Workbook

Sheet LEEME
A2: Modelo de compras y costes de producto de gazpacho
A3: Modelo anual para 2026 | EUR | kg y litros
A6: Objetivo de negocio
A7: Conectar el plan anual de producción con la receta, las necesidades de materias primas, las compras, los costes, el control de merma y los KPI de gestión.
A9: Funcionamiento del modelo
A10: Plan de producción → Receta/lista de materiales → Necesidades de materias primas → Compras → Precios de compra → Gasto de materias primas → Coste de producto → Control de merma → KPI
A12: Principales supuestos
A13: Año del modelo 2026. Escenario anual de producción de referencia: 1.200.000 L. Plan de enero: 100.000 L. Densidad: 1,00 kg/L. Unidad de compra: kg. Dos lotes de compra. Umbral de alerta de merma: 1,00%.
A16: Datos maestros y datos transaccionales
A17: Maestro_Ingredientes contiene la receta editable y los supuestos de merma esperada. Plan_Produccion, Plan_Compras y los campos manuales de Modelo_Costes contienen los datos transaccionales mensuales.
A20: Compra requerida y compra real
A21: La compra requerida es la cantidad bruta de ingrediente derivada de la producción y de la merma esperada. La compra real es la cantidad total introducida en un máximo de dos lotes de compra mensuales.
... A42: Este modelo de porfolio es ficticio y se ha creado con fines educativos. No contiene ni implica datos reales de operaciones, precios, costes, volúmenes, compras ni información confidencial de AMC Fresh, Lidl o ninguna otra empresa.

Sheet Supuestos
A2: Supuestos
A3: Modelo anual para 2026 | EUR | kg y litros
A6: Parámetro | B6: Valor | C6: Unidad | D6: Tipo de entrada | E6: Notas
A7: Año del modelo | B7: 2026 | C7: año | D7: Manual | E7: Año natural
A8: Escenario estimado de producción anual | B8: 1200000 | C8: L | D8: Manual | E8: Solo como referencia. No completa los meses futuros
A9: Densidad del producto terminado | B9: 1 | C9: kg/L | D9: Manual | E9: Se utiliza para convertir el porcentaje de receta en kg/L netos
A10: Moneda | B10: EUR | C10: código | D10: Manual | E10: Moneda de presentación del modelo
A11: Unidad de compra | B11: kg | C11: UdM | D11: Manual | E11: Unidad utilizada para todas las cantidades de compra
A12: Máximo de lotes de compra por ingrediente y mes | B12: 2 | C12: lotes | D12: Manual | E12: El Plan de compras permite dos lotes
A13: Umbral de alerta de desviación de merma | B13: 0.01 | C13: % de la producción | D13: Manual | E13: Umbral mensual de desviación absoluta de merma
A16: Convenciones del libro
A18: Celdas amarillas | B18: Entradas manuales
A19: Celdas gris claro | B19: Campos calculados
A20: Celdas azul claro | B20: KPI y resultados
A21: Celdas o texto rojos | B21: Alertas o controles fallidos

Sheet Maestro_Ingredientes
A2: Maestro de ingredientes y receta/lista de materiales
A3: Modelo anual para 2026 | EUR | kg y litros
A6: ID de ingrediente | B6: Ingrediente | C6: Categoría | D6: Unidad de compra | E6: % de receta | F6: % de merma esperada | G6: kg/L netos | H6: kg/L brutos | I6: Activo
A7: ING-001 | B7: Tomate pera | C7: Hortalizas frescas | D7: kg | E7: 0.703 | F7: 0.08 | G7: =Supuestos!$B$9*E7 -> 0.703 | H7: =G7/(1-F7) -> 0.76413043 | I7: Sí
A8: ING-002 | B8: Pepino | C8: Hortalizas frescas | D8: kg | E8: 0.122 | F8: 0.12 | G8: =Supuestos!$B$9*E8 -> 0.122 | H8: =G8/(1-F8) -> 0.13863636 | I8: Sí
A9: ING-003 | B9: Pimiento verde | C9: Hortalizas frescas | D9: kg | E9: 0.073 | F9: 0.15 | G9: =Supuestos!$B$9*E9 -> 0.073 | H9: =G9/(1-F9) -> 0.085882353 | I9: Sí
A10: ING-004 | B10: Cebolla | C10: Hortalizas frescas | D10: kg | E10: 0.044 | F10: 0.1 | G10: =Supuestos!$B$9*E10 -> 0.044 | H10: =G10/(1-F10) -> 0.048888889 | I10: Sí
A11: ING-005 | B11: Ajo | C11: Hortalizas frescas | D11: kg | E11: 0.008 | F11: 0.08 | G11: =Supuestos!$B$9*E11 -> 0.008 | H11: =G11/(1-F11) -> 0.0086956522 | I11: Sí
A12: ING-006 | B12: Aceite de oliva virgen extra | C12: Aceite | D12: kg | E12: 0.026 | F12: 0.005 | G12: =Supuestos!$B$9*E12 -> 0.026 | H12: =G12/(1-F12) -> 0.026130653 | I12: Sí
A13: ING-007 | B13: Vinagre de Jerez | C13: Ácidos y condimentos | D13: kg | E13: 0.013 | F13: 0.005 | G13: =Supuestos!$B$9*E13 -> 0.013 | H13: =G13/(1-F13) -> 0.013065327 | I13: Sí
A14: ING-008 | B14: Sal | C14: Condimentos | D14: kg | E14: 0.007 | F14: 0 | G14: =Supuestos!$B$9*E14 -> 0.007 | H14: =G14/(1-F14) -> 0.007 | I14: Sí
A15: ING-009 | B15: Zumo de limón | C15: Ácidos y condimentos | D15: kg | E15: 0.004 | F15: 0.02 | G15: =Supuestos!$B$9*E15 -> 0.004 | H15: =G15/(1-F15) -> 0.0040816327 | I15: Sí
A18: Control de receta
A20: Total de la receta | B20: =SUM(E7:E15) -> 1 | D20: Supuestos de un ejercicio ficticio. La receta y los porcentajes de merma esperada son editables.
A21: Estado del control | B21: =IF(ABS(B20-1)<0.0000001,"OK","ALERTA – LA RECETA NO SUMA EL 100%") -> OK

Sheet Plan_Produccion
A2: Plan de producción y necesidades de materias primas
A3: Modelo anual para 2026 | EUR | kg y litros
A6: Mes | B6: Producción planificada L | C6: Necesidad neta kg | D6: Compra requerida kg | E6: Merma esperada kg | F6: Estado de la entrada
A7: 46023 | B7: 100000 | C7: =IF(B7="","",B7*SUM(Maestro_Ingredientes!$G$7:$G$15)) -> 100000 | D7: =IF(B7="","",B7*SUM(Maestro_Ingredientes!$H$7:$H$15)) -> 109651.13 | E7: =IF(B7="","",D7-C7) -> 9651.1305 | F7: =IF(B7="","","Introducida") -> Introducida
A8: 46054 | C8: =IF(B8="","",B8*SUM(Maestro_Ingredientes!$G$7:$G$15)) | D8: =IF(B8="","",B8*SUM(Maestro_Ingredientes!$H$7:$H$15)) | E8: =IF(B8="","",D8-C8) | F8: =IF(B8="","","Introducida")
A9: 46082 | C9: =IF(B9="","",B9*SUM(Maestro_Ingredientes!$G$7:$G$15)) | D9: =IF(B9="","",B9*SUM(Maestro_Ingredientes!$H$7:$H$15)) | E9: =IF(B9="","",D9-C9) | F9: =IF(B9="","","Introducida")
A10: 46113 | C10: =IF(B10="","",B10*SUM(Maestro_Ingredientes!$G$7:$G$15)) | D10: =IF(B10="","",B10*SUM(Maestro_Ingredientes!$H$7:$H$15)) | E10: =IF(B10="","",D10-C10) | F10: =IF(B10="","","Introducida")
A11: 46143 | C11: =IF(B11="","",B11*SUM(Maestro_Ingredientes!$G$7:$G$15)) | D11: =IF(B11="","",B11*SUM(Maestro_Ingredientes!$H$7:$H$15)) | E11: =IF(B11="","",D11-C11) | F11: =IF(B11="","","Introducida")
A12: 46174 | C12: =IF(B12="","",B12*SUM(Maestro_Ingredientes!$G$7:$G$15)) | D12: =IF(B12="","",B12*SUM(Maestro_Ingredientes!$H$7:$H$15)) | E12: =IF(B12="","",D12-C12) | F12: =IF(B12="","","Introducida")
A13: 46204 | C13: =IF(B13="","",B13*SUM(Maestro_Ingredientes!$G$7:$G$15)) | D13: =IF(B13="","",B13*SUM(Maestro_Ingredientes!$H$7:$H$15)) | E13: =IF(B13="","",D13-C13) | F13: =IF(B13="","","Introducida")
A14: 46235 | C14: =IF(B14="","",B14*SUM(Maestro_Ingredientes!$G$7:$G$15)) | D14: =IF(B14="","",B14*SUM(Maestro_Ingredientes!$H$7:$H$15)) | E14: =IF(B14="","",D14-C14) | F14: =IF(B14="","","Introducida")
A15: 46266 | C15: =IF(B15="","",B15*SUM(Maestro_Ingredientes!$G$7:$G$15)) | D15: =IF(B15="","",B15*SUM(Maestro_Ingredientes!$H$7:$H$15)) | E15: =IF(B15="","",D15-C15) | F15: =IF(B15="","","Introducida")
A16: 46296 | C16: =IF(B16="","",B16*SUM(Maestro_Ingredientes!$G$7:$G$15)) | D16: =IF(B16="","",B16*SUM(Maestro_Ingredientes!$H$7:$H$15)) | E16: =IF(B16="","",D16-C16) | F16: =IF(B16="","","Introducida")
A17: 46327 | C17: =IF(B17="","",B17*SUM(Maestro_Ingredientes!$G$7:$G$15)) | D17: =IF(B17="","",B17*SUM(Maestro_Ingredientes!$H$7:$H$15)) | E17: =IF(B17="","",D17-C17) | F17: =IF(B17="","","Introducida")
A18: 46357 | C18: =IF(B18="","",B18*SUM(Maestro_Ingredientes!$G$7:$G$15)) | D18: =IF(B18="","",B18*SUM(Maestro_Ingredientes!$H$7:$H$15)) | E18: =IF(B18="","",D18-C18) | F18: =IF(B18="","","Introducida")
A20: Anual / acumulado
A21: Total de meses informados | B21: =SUM(B7:B18) -> 100000 | C21: =SUM(C7:C18) -> 100000 | D21: =SUM(D7:D18) -> 109651.13 | E21: =SUM(E7:E18) -> 9651.1305
A23: Los meses futuros permanecen en blanco hasta que se introduce la producción. El escenario de 1.200.000 L es solo una referencia.

Sheet Plan_Compras
A2: Plan de compras
A3: Modelo anual para 2026 | EUR | kg y litros
A6: Mes | B6: ID de ingrediente | C6: Ingrediente | D6: Producción planificada L | E6: Necesidad neta kg | F6: Compra requerida kg | G6: Cantidad de compra 1 kg | H6: Precio de compra 1 €/kg | I6: Gasto de compra 1 € | J6: Cantidad de compra 2 kg | K6: Precio de compra 2 €/kg | L6: Gasto de compra 2 € | M6: Cantidad comprada kg | N6: Gasto total € | O6: Precio medio ponderado €/kg | P6: Desviación de compra kg | Q6: Cobertura de compra %
A7: 46023 | B7: ING-001 | C7: =Maestro_Ingredientes!$B$7 -> Tomate pera | D7: =IF(Plan_Produccion!$B$7="","",Plan_Produccion!$B$7) -> 100000 | E7: =IF(D7="","",D7*Maestro_Ingredientes!$G$7) -> 70300 | F7: =IF(D7="","",D7*Maestro_Ingredientes!$H$7) -> 76413.043 | G7: =F7 -> 76413.043 | I7: =IF(OR(G7="",H7=""),"",G7*H7) | L7: =IF(OR(J7="",K7=""),"",J7*K7) | M7: =IF(COUNTA(G7,J7)=0,"",SUM(G7,J7)) -> 76413.043 | N7: =IF(M7="","",IF(OR(AND(G7<>0,H7=""),AND(J7<>0,K7="")),"",SUM(I7,L7))) | O7: =IF(OR(M7="",M7=0,N7=""),"",N7/M7) | P7: =IF(OR(M7="",F7=""),"",M7-F7) -> 0 | Q7: =IF(OR(M7="",F7="",F7=0),"",M7/F7) -> 1
A8: 46023 | B8: ING-002 | C8: =Maestro_Ingredientes!$B$8 -> Pepino | D8: =IF(Plan_Produccion!$B$7="","",Plan_Produccion!$B$7) -> 100000 | E8: =IF(D8="","",D8*Maestro_Ingredientes!$G$8) -> 12200 | F8: =IF(D8="","",D8*Maestro_Ingredientes!$H$8) -> 13863.636 | G8: =F8 -> 13863.636 | I8: =IF(OR(G8="",H8=""),"",G8*H8) | L8: =IF(OR(J8="",K8=""),"",J8*K8) | M8: =IF(COUNTA(G8,J8)=0,"",SUM(G8,J8)) -> 13863.636 | N8: =IF(M8="","",IF(OR(AND(G8<>0,H8=""),AND(J8<>0,K8="")),"",SUM(I8,L8))) | O8: =IF(OR(M8="",M8=0,N8=""),"",N8/M8) | P8: =IF(OR(M8="",F8=""),"",M8-F8) -> 0 | Q8: =IF(OR(M8="",F8="",F8=0),"",M8/F8) -> 1
A9: 46023 | B9: ING-003 | C9: =Maestro_Ingredientes!$B$9 -> Pimiento verde | D9: =IF(Plan_Produccion!$B$7="","",Plan_Produccion!$B$7) -> 100000 | E9: =IF(D9="","",D9*Maestro_Ingredientes!$G$9) -> 7300 | F9: =IF(D9="","",D9*Maestro_Ingredientes!$H$9) -> 8588.2353 | G9: =F9 -> 8588.2353 | I9: =IF(OR(G9="",H9=""),"",G9*H9) | L9: =IF(OR(J9="",K9=""),"",J9*K9) | M9: =IF(COUNTA(G9,J9)=0,"",SUM(G9,J9)) -> 8588.2353 | N9: =IF(M9="","",IF(OR(AND(G9<>0,H9=""),AND(J9<>0,K9="")),"",SUM(I9,L9))) | O9: =IF(OR(M9="",M9=0,N9=""),"",N9/M9) | P9: =IF(OR(M9="",F9=""),"",M9-F9) -> 0 | Q9: =IF(OR(M9="",F9="",F9=0),"",M9/F9) -> 1
A10: 46023 | B10: ING-004 | C10: =Maestro_Ingredientes!$B$10 -> Cebolla | D10: =IF(Plan_Produccion!$B$7="","",Plan_Produccion!$B$7) -> 100000 | E10: =IF(D10="","",D10*Maestro_Ingredientes!$G$10) -> 4400 | F10: =IF(D10="","",D10*Maestro_Ingredientes!$H$10) -> 4888.8889 | G10: =F10 -> 4888.8889 | I10: =IF(OR(G10="",H10=""),"",G10*H10) | L10: =IF(OR(J10="",K10=""),"",J10*K10) | M10: =IF(COUNTA(G10,J10)=0,"",SUM(G10,J10)) -> 4888.8889 | N10: =IF(M10="","",IF(OR(AND(G10<>0,H10=""),AND(J10<>0,K10="")),"",SUM(I10,L10))) | O10: =IF(OR(M10="",M10=0,N10=""),"",N10/M10) | P10: =IF(OR(M10="",F10=""),"",M10-F10) -> 0 | Q10: =IF(OR(M10="",F10="",F10=0),"",M10/F10) -> 1
A11: 46023 | B11: ING-005 | C11: =Maestro_Ingredientes!$B$11 -> Ajo | D11: =IF(Plan_Produccion!$B$7="","",Plan_Produccion!$B$7) -> 100000 | E11: =IF(D11="","",D11*Maestro_Ingredientes!$G$11) -> 800 | F11: =IF(D11="","",D11*Maestro_Ingredientes!$H$11) -> 869.56522 | G11: =F11 -> 869.56522 | I11: =IF(OR(G11="",H11=""),"",G11*H11) | L11: =IF(OR(J11="",K11=""),"",J11*K11) | M11: =IF(COUNTA(G11,J11)=0,"",SUM(G11,J11)) -> 869.56522 | N11: =IF(M11="","",IF(OR(AND(G11<>0,H11=""),AND(J11<>0,K11="")),"",SUM(I11,L11))) | O11: =IF(OR(M11="",M11=0,N11=""),"",N11/M11) | P11: =IF(OR(M11="",F11=""),"",M11-F11) -> 0 | Q11: =IF(OR(M11="",F11="",F11=0),"",M11/F11) -> 1
A12: 46023 | B12: ING-006 | C12: =Maestro_Ingredientes!$B$12 -> Aceite de oliva virgen extra | D12: =IF(Plan_Produccion!$B$7="","",Plan_Produccion!$B$7) -> 100000 | E12: =IF(D12="","",D12*Maestro_Ingredientes!$G$12) -> 2600 | F12: =IF(D12="","",D12*Maestro_Ingredientes!$H$12) -> 2613.0653 | G12: =F12 -> 2613.0653 | I12: =IF(OR(G12="",H12=""),"",G12*H12) | L12: =IF(OR(J12="",K12=""),"",J12*K12) | M12: =IF(COUNTA(G12,J12)=0,"",SUM(G12,J12)) -> 2613.0653 | N12: =IF(M12="","",IF(OR(AND(G12<>0,H12=""),AND(J12<>0,K12="")),"",SUM(I12,L12))) | O12: =IF(OR(M12="",M12=0,N12=""),"",N12/M12) | P12: =IF(OR(M12="",F12=""),"",M12-F12) -> 0 | Q12: =IF(OR(M12="",F12="",F12=0),"",M12/F12) -> 1
A13: 46023 | B13: ING-007 | C13: =Maestro_Ingredientes!$B$13 -> Vinagre de Jerez | D13: =IF(Plan_Produccion!$B$7="","",Plan_Produccion!$B$7) -> 100000 | E13: =IF(D13="","",D13*Maestro_Ingredientes!$G$13) -> 1300 | F13: =IF(D13="","",D13*Maestro_Ingredientes!$H$13) -> 1306.5327 | G13: =F13 -> 1306.5327 | I13: =IF(OR(G13="",H13=""),"",G13*H13) | L13: =IF(OR(J13="",K13=""),"",J13*K13) | M13: =IF(COUNTA(G13,J13)=0,"",SUM(G13,J13)) -> 1306.5327 | N13: =IF(M13="","",IF(OR(AND(G13<>0,H13=""),AND(J13<>0,K13="")),"",SUM(I13,L13))) | O13: =IF(OR(M13="",M13=0,N13=""),"",N13/M13) | P13: =IF(OR(M13="",F13=""),"",M13-F13) -> 0 | Q13: =IF(OR(M13="",F13="",F13=0),"",M13/F13) -> 1
A14: 46023 | B14: ING-008 | C14: =Maestro_Ingredientes!$B$14 -> Sal | D14: =IF(Plan_Produccion!$B$7="","",Plan_Produccion!$B$7) -> 100000 | E14: =IF(D14="","",D14*Maestro_Ingredientes!$G$14) -> 700 | F14: =IF(D14="","",D14*Maestro_Ingredientes!$H$14) -> 700 | G14: =F14 -> 700 | I14: =IF(OR(G14="",H14=""),"",G14*H14) | L14: =IF(OR(J14="",K14=""),"",J14*K14) | M14: =IF(COUNTA(G14,J14)=0,"",SUM(G14,J14)) -> 700 | N14: =IF(M14="","",IF(OR(AND(G14<>0,H14=""),AND(J14<>0,K14="")),"",SUM(I14,L14))) | O14: =IF(OR(M14="",M14=0,N14=""),"",N14/M14) | P14: =IF(OR(M14="",F14=""),"",M14-F14) -> 0 | Q14: =IF(OR(M14="",F14="",F14=0),"",M14/F14) -> 1
A15: 46023 | B15: ING-009 | C15: =Maestro_Ingredientes!$B$15 -> Zumo de limón | D15: =IF(Plan_Produccion!$B$7="","",Plan_Produccion!$B$7) -> 100000 | E15: =IF(D15="","",D15*Maestro_Ingredientes!$G$15) -> 400 | F15: =IF(D15="","",D15*Maestro_Ingredientes!$H$15) -> 408.16327 | G15: =F15 -> 408.16327 | I15: =IF(OR(G15="",H15=""),"",G15*H15) | L15: =IF(OR(J15="",K15=""),"",J15*K15) | M15: =IF(COUNTA(G15,J15)=0,"",SUM(G15,J15)) -> 408.16327 | N15: =IF(M15="","",IF(OR(AND(G15<>0,H15=""),AND(J15<>0,K15="")),"",SUM(I15,L15))) | O15: =IF(OR(M15="",M15=0,N15=""),"",N15/M15) | P15: =IF(OR(M15="",F15=""),"",M15-F15) -> 0 | Q15: =IF(OR(M15="",F15="",F15=0),"",M15/F15) -> 1
A16: 46054 | B16: ING-001 | C16: =Maestro_Ingredientes!$B$7 -> Tomate pera | D16: =IF(Plan_Produccion!$B$8="","",Plan_Produccion!$B$8) | E16: =IF(D16="","",D16*Maestro_Ingredientes!$G$7) | F16: =IF(D16="","",D16*Maestro_Ingredientes!$H$7) | I16: =IF(OR(G16="",H16=""),"",G16*H16) | L16: =IF(OR(J16="",K16=""),"",J16*K16) | M16: =IF(COUNTA(G16,J16)=0,"",SUM(G16,J16)) | N16: =IF(M16="","",IF(OR(AND(G16<>0,H16=""),AND(J16<>0,K16="")),"",SUM(I16,L16))) | O16: =IF(OR(M16="",M16=0,N16=""),"",N16/M16) | P16: =IF(OR(M16="",F16=""),"",M16-F16) | Q16: =IF(OR(M16="",F16="",F16=0),"",M16/F16)
A17: 46054 | B17: ING-002 | C17: =Maestro_Ingredientes!$B$8 -> Pepino | D17: =IF(Plan_Produccion!$B$8="","",Plan_Produccion!$B$8) | E17: =IF(D17="","",D17*Maestro_Ingredientes!$G$8) | F17: =IF(D17="","",D17*Maestro_Ingredientes!$H$8) | I17: =IF(OR(G17="",H17=""),"",G17*H17) | L17: =IF(OR(J17="",K17=""),"",J17*K17) | M17: =IF(COUNTA(G17,J17)=0,"",SUM(G17,J17)) | N17: =IF(M17="","",IF(OR(AND(G17<>0,H17=""),AND(J17<>0,K17="")),"",SUM(I17,L17))) | O17: =IF(OR(M17="",M17=0,N17=""),"",N17/M17) | P17: =IF(OR(M17="",F17=""),"",M17-F17) | Q17: =IF(OR(M17="",F17="",F17=0),"",M17/F17)
A18: 46054 | B18: ING-003 | C18: =Maestro_Ingredientes!$B$9 -> Pimiento verde | D18: =IF(Plan_Produccion!$B$8="","",Plan_Produccion!$B$8) | E18: =IF(D18="","",D18*Maestro_Ingredientes!$G$9) | F18: =IF(D18="","",D18*Maestro_Ingredientes!$H$9) | I18: =IF(OR(G18="",H18=""),"",G18*H18) | L18: =IF(OR(J18="",K18=""),"",J18*K18) | M18: =IF(COUNTA(G18,J18)=0,"",SUM(G18,J18)) | N18: =IF(M18="","",IF(OR(AND(G18<>0,H18=""),AND(J18<>0,K18="")),"",SUM(I18,L18))) | O18: =IF(OR(M18="",M18=0,N18=""),"",N18/M18) | P18: =IF(OR(M18="",F18=""),"",M18-F18) | Q18: =IF(OR(M18="",F18="",F18=0),"",M18/F18)
A19: 46054 | B19: ING-004 | C19: =Maestro_Ingredientes!$B$10 -> Cebolla | D19: =IF(Plan_Produccion!$B$8="","",Plan_Produccion!$B$8) | E19: =IF(D19="","",D19*Maestro_Ingredientes!$G$10) | F19: =IF(D19="","",D19*Maestro_Ingredientes!$H$10) | I19: =IF(OR(G19="",H19=""),"",G19*H19) | L19: =IF(OR(J19="",K19=""),"",J19*K19) | M19: =IF(COUNTA(G19,J19)=0,"",SUM(G19,J19)) | N19: =IF(M19="","",IF(OR(AND(G19<>0,H19=""),AND(J19<>0,K19="")),"",SUM(I19,L19))) | O19: =IF(OR(M19="",M19=0,N19=""),"",N19/M19) | P19: =IF(OR(M19="",F19=""),"",M19-F19) | Q19: =IF(OR(M19="",F19="",F19=0),"",M19/F19)
A20: 46054 | B20: ING-005 | C20: =Maestro_Ingredientes!$B$11 -> Ajo | D20: =IF(Plan_Produccion!$B$8="","",Plan_Produccion!$B$8) | E20: =IF(D20="","",D20*Maestro_Ingredientes!$G$11) | F20: =IF(D20="","",D20*Maestro_Ingredientes!$H$11) | I20: =IF(OR(G20="",H20=""),"",G20*H20) | L20: =IF(OR(J20="",K20=""),"",J20*K20) | M20: =IF(COUNTA(G20,J20)=0,"",SUM(G20,J20)) | N20: =IF(M20="","",IF(OR(AND(G20<>0,H20=""),AND(J20<>0,K20="")),"",SUM(I20,L20))) | O20: =IF(OR(M20="",M20=0,N20=""),"",N20/M20) | P20: =IF(OR(M20="",F20=""),"",M20-F20) | Q20: =IF(OR(M20="",F20="",F20=0),"",M20/F20)
A21: 46054 | B21: ING-006 | C21: =Maestro_Ingredientes!$B$12 -> Aceite de oliva virgen extra | D21: =IF(Plan_Produccion!$B$8="","",Plan_Produccion!$B$8) | E21: =IF(D21="","",D21*Maestro_Ingredientes!$G$12) | F21: =IF(D21="","",D21*Maestro_Ingredientes!$H$12) | I21: =IF(OR(G21="",H21=""),"",G21*H21) | L21: =IF(OR(J21="",K21=""),"",J21*K21) | M21: =IF(COUNTA(G21,J21)=0,"",SUM(G21,J21)) | N21: =IF(M21="","",IF(OR(AND(G21<>0,H21=""),AND(J21<>0,K21="")),"",SUM(I21,L21))) | O21: =IF(OR(M21="",M21=0,N21=""),"",N21/M21) | P21: =IF(OR(M21="",F21=""),"",M21-F21) | Q21: =IF(OR(M21="",F21="",F21=0),"",M21/F21)
A22: 46054 | B22: ING-007 | C22: =Maestro_Ingredientes!$B$13 -> Vinagre de Jerez | D22: =IF(Plan_Produccion!$B$8="","",Plan_Produccion!$B$8) | E22: =IF(D22="","",D22*Maestro_Ingredientes!$G$13) | F22: =IF(D22="","",D22*Maestro_Ingredientes!$H$13) | I22: =IF(OR(G22="",H22=""),"",G22*H22) | L22: =IF(OR(J22="",K22=""),"",J22*K22) | M22: =IF(COUNTA(G22,J22)=0,"",SUM(G22,J22)) | N22: =IF(M22="","",IF(OR(AND(G22<>0,H22=""),AND(J22<>0,K22="")),"",SUM(I22,L22))) | O22: =IF(OR(M22="",M22=0,N22=""),"",N22/M22) | P22: =IF(OR(M22="",F22=""),"",M22-F22) | Q22: =IF(OR(M22="",F22="",F22=0),"",M22/F22)
A23: 46054 | B23: ING-008 | C23: =Maestro_Ingredientes!$B$14 -> Sal | D23: =IF(Plan_Produccion!$B$8="","",Plan_Produccion!$B$8) | E23: =IF(D23="","",D23*Maestro_Ingredientes!$G$14) | F23: =IF(D23="","",D23*Maestro_Ingredientes!$H$14) | I23: =IF(OR(G23="",H23=""),"",G23*H23) | L23: =IF(OR(J23="",K23=""),"",J23*K23) | M23: =IF(COUNTA(G23,J23)=0,"",SUM(G23,J23)) | N23: =IF(M23="","",IF(OR(AND(G23<>0,H23=""),AND(J23<>0,K23="")),"",SUM(I23,L23))) | O23: =IF(OR(M23="",M23=0,N23=""),"",N23/M23) | P23: =IF(OR(M23="",F23=""),"",M23-F23) | Q23: =IF(OR(M23="",F23="",F23=0),"",M23/F23)
A24: 46054 | B24: ING-009 | C24: =Maestro_Ingredientes!$B$15 -> Zumo de limón | D24: =IF(Plan_Produccion!$B$8="","",Plan_Produccion!$B$8) | E24: =IF(D24="","",D24*Maestro_Ingredientes!$G$15) | F24: =IF(D24="","",D24*Maestro_Ingredientes!$H$15) | I24: =IF(OR(G24="",H24=""),"",G24*H24) | L24: =IF(OR(J24="",K24=""),"",J24*K24) | M24: =IF(COUNTA(G24,J24)=0,"",SUM(G24,J24)) | N24: =IF(M24="","",IF(OR(AND(G24<>0,H24=""),AND(J24<>0,K24="")),"",SUM(I24,L24))) | O24: =IF(OR(M24="",M24=0,N24=""),"",N24/M24) | P24: =IF(OR(M24="",F24=""),"",M24-F24) | Q24: =IF(OR(M24="",F24="",F24=0),"",M24/F24)
A25: 46082 | B25: ING-001 | C25: =Maestro_Ingredientes!$B$7 -> Tomate pera | D25: =IF(Plan_Produccion!$B$9="","",Plan_Produccion!$B$9) | E25: =IF(D25="","",D25*Maestro_Ingredientes!$G$7) | F25: =IF(D25="","",D25*Maestro_Ingredientes!$H$7) | I25: =IF(OR(G25="",H25=""),"",G25*H25) | L25: =IF(OR(J25="",K25=""),"",J25*K25) | M25: =IF(COUNTA(G25,J25)=0,"",SUM(G25,J25)) | N25: =IF(M25="","",IF(OR(AND(G25<>0,H25=""),AND(J25<>0,K25="")),"",SUM(I25,L25))) | O25: =IF(OR(M25="",M25=0,N25=""),"",N25/M25) | P25: =IF(OR(M25="",F25=""),"",M25-F25) | Q25: =IF(OR(M25="",F25="",F25=0),"",M25/F25)
A26: 46082 | B26: ING-002 | C26: =Maestro_Ingredientes!$B$8 -> Pepino | D26: =IF(Plan_Produccion!$B$9="","",Plan_Produccion!$B$9) | E26: =IF(D26="","",D26*Maestro_Ingredientes!$G$8) | F26: =IF(D26="","",D26*Maestro_Ingredientes!$H$8) | I26: =IF(OR(G26="",H26=""),"",G26*H26) | L26: =IF(OR(J26="",K26=""),"",J26*K26) | M26: =IF(COUNTA(G26,J26)=0,"",SUM(G26,J26)) | N26: =IF(M26="","",IF(OR(AND(G26<>0,H26=""),AND(J26<>0,K26="")),"",SUM(I26,L26))) | O26: =IF(OR(M26="",M26=0,N26=""),"",N26/M26) | P26: =IF(OR(M26="",F26=""),"",M26-F26) | Q26: =IF(OR(M26="",F26="",F26=0),"",M26/F26)
A27: 46082 | B27: ING-003 | C27: =Maestro_Ingredientes!$B$9 -> Pimiento verde | D27: =IF(Plan_Produccion!$B$9="","",Plan_Produccion!$B$9) | E27: =IF(D27="","",D27*Maestro_Ingredientes!$G$9) | F27: =IF(D27="","",D27*Maestro_Ingredientes!$H$9) | I27: =IF(OR(G27="",H27=""),"",G27*H27) | L27: =IF(OR(J27="",K27=""),"",J27*K27) | M27: =IF(COUNTA(G27,J27)=0,"",SUM(G27,J27)) | N27: =IF(M27="","",IF(OR(AND(G27<>0,H27=""),AND(J27<>0,K27="")),"",SUM(I27,L27))) | O27: =IF(OR(M27="",M27=0,N27=""),"",N27/M27) | P27: =IF(OR(M27="",F27=""),"",M27-F27) | Q27: =IF(OR(M27="",F27="",F27=0),"",M27/F27)
A28: 46082 | B28: ING-004 | C28: =Maestro_Ingredientes!$B$10 -> Cebolla | D28: =IF(Plan_Produccion!$B$9="","",Plan_Produccion!$B$9) | E28: =IF(D28="","",D28*Maestro_Ingredientes!$G$10) | F28: =IF(D28="","",D28*Maestro_Ingredientes!$H$10) | I28: =IF(OR(G28="",H28=""),"",G28*H28) | L28: =IF(OR(J28="",K28=""),"",J28*K28) | M28: =IF(COUNTA(G28,J28)=0,"",SUM(G28,J28)) | N28: =IF(M28="","",IF(OR(AND(G28<>0,H28=""),AND(J28<>0,K28="")),"",SUM(I28,L28))) | O28: =IF(OR(M28="",M28=0,N28=""),"",N28/M28) | P28: =IF(OR(M28="",F28=""),"",M28-F28) | Q28: =IF(OR(M28="",F28="",F28=0),"",M28/F28)
A29: 46082 | B29: ING-005 | C29: =Maestro_Ingredientes!$B$11 -> Ajo | D29: =IF(Plan_Produccion!$B$9="","",Plan_Produccion!$B$9) | E29: =IF(D29="","",D29*Maestro_Ingredientes!$G$11) | F29: =IF(D29="","",D29*Maestro_Ingredientes!$H$11) | I29: =IF(OR(G29="",H29=""),"",G29*H29) | L29: =IF(OR(J29="",K29=""),"",J29*K29) | M29: =IF(COUNTA(G29,J29)=0,"",SUM(G29,J29)) | N29: =IF(M29="","",IF(OR(AND(G29<>0,H29=""),AND(J29<>0,K29="")),"",SUM(I29,L29))) | O29: =IF(OR(M29="",M29=0,N29=""),"",N29/M29) | P29: =IF(OR(M29="",F29=""),"",M29-F29) | Q29: =IF(OR(M29="",F29="",F29=0),"",M29/F29)
A30: 46082 | B30: ING-006 | C30: =Maestro_Ingredientes!$B$12 -> Aceite de oliva virgen extra | D30: =IF(Plan_Produccion!$B$9="","",Plan_Produccion!$B$9) | E30: =IF(D30="","",D30*Maestro_Ingredientes!$G$12) | F30: =IF(D30="","",D30*Maestro_Ingredientes!$H$12) | I30: =IF(OR(G30="",H30=""),"",G30*H30) | L30: =IF(OR(J30="",K30=""),"",J30*K30) | M30: =IF(COUNTA(G30,J30)=0,"",SUM(G30,J30)) | N30: =IF(M30="","",IF(OR(AND(G30<>0,H30=""),AND(J30<>0,K30="")),"",SUM(I30,L30))) | O30: =IF(OR(M30="",M30=0,N30=""),"",N30/M30) | P30: =IF(OR(M30="",F30=""),"",M30-F30) | Q30: =IF(OR(M30="",F30="",F30=0),"",M30/F30)
A31: 46082 | B31: ING-007 | C31: =Maestro_Ingredientes!$B$13 -> Vinagre de Jerez | D31: =IF(Plan_Produccion!$B$9="","",Plan_Produccion!$B$9) | E31: =IF(D31="","",D31*Maestro_Ingredientes!$G$13) | F31: =IF(D31="","",D31*Maestro_Ingredientes!$H$13) | I31: =IF(OR(G31="",H31=""),"",G31*H31) | L31: =IF(OR(J31="",K31=""),"",J31*K31) | M31: =IF(COUNTA(G31,J31)=0,"",SUM(G31,J31)) | N31: =IF(M31="","",IF(OR(AND(G31<>0,H31=""),AND(J31<>0,K31="")),"",SUM(I31,L31))) | O31: =IF(OR(M31="",M31=0,N31=""),"",N31/M31) | P31: =IF(OR(M31="",F31=""),"",M31-F31) | Q31: =IF(OR(M31="",F31="",F31=0),"",M31/F31)
A32: 46082 | B32: ING-008 | C32: =Maestro_Ingredientes!$B$14 -> Sal | D32: =IF(Plan_Produccion!$B$9="","",Plan_Produccion!$B$9) | E32: =IF(D32="","",D32*Maestro_Ingredientes!$G$14) | F32: =IF(D32="","",D32*Maestro_Ingredientes!$H$14) | I32: =IF(OR(G32="",H32=""),"",G32*H32) | L32: =IF(OR(J32="",K32=""),"",J32*K32) | M32: =IF(COUNTA(G32,J32)=0,"",SUM(G32,J32)) | N32: =IF(M32="","",IF(OR(AND(G32<>0,H32=""),AND(J32<>0,K32="")),"",SUM(I32,L32))) | O32: =IF(OR(M32="",M32=0,N32=""),"",N32/M32) | P32: =IF(OR(M32="",F32=""),"",M32-F32) | Q32: =IF(OR(M32="",F32="",F32=0),"",M32/F32)
A33: 46082 | B33: ING-009 | C33: =Maestro_Ingredientes!$B$15 -> Zumo de limón | D33: =IF(Plan_Produccion!$B$9="","",Plan_Produccion!$B$9) | E33: =IF(D33="","",D33*Maestro_Ingredientes!$G$15) | F33: =IF(D33="","",D33*Maestro_Ingredientes!$H$15) | I33: =IF(OR(G33="",H33=""),"",G33*H33) | L33: =IF(OR(J33="",K33=""),"",J33*K33) | M33: =IF(COUNTA(G33,J33)=0,"",SUM(G33,J33)) | N33: =IF(M33="","",IF(OR(AND(G33<>0,H33=""),AND(J33<>0,K33="")),"",SUM(I33,L33))) | O33: =IF(OR(M33="",M33=0,N33=""),"",N33/M33) | P33: =IF(OR(M33="",F33=""),"",M33-F33) | Q33: =IF(OR(M33="",F33="",F33=0),"",M33/F33)
A34: 46113 | B34: ING-001 | C34: =Maestro_Ingredientes!$B$7 -> Tomate pera | D34: =IF(Plan_Produccion!$B$10="","",Plan_Produccion!$B$10) | E34: =IF(D34="","",D34*Maestro_Ingredientes!$G$7) | F34: =IF(D34="","",D34*Maestro_Ingredientes!$H$7) | I34: =IF(OR(G34="",H34=""),"",G34*H34) | L34: =IF(OR(J34="",K34=""),"",J34*K34) | M34: =IF(COUNTA(G34,J34)=0,"",SUM(G34,J34)) | N34: =IF(M34="","",IF(OR(AND(G34<>0,H34=""),AND(J34<>0,K34="")),"",SUM(I34,L34))) | O34: =IF(OR(M34="",M34=0,N34=""),"",N34/M34) | P34: =IF(OR(M34="",F34=""),"",M34-F34) | Q34: =IF(OR(M34="",F34="",F34=0),"",M34/F34)
A35: 46113 | B35: ING-002 | C35: =Maestro_Ingredientes!$B$8 -> Pepino | D35: =IF(Plan_Produccion!$B$10="","",Plan_Produccion!$B$10) | E35: =IF(D35="","",D35*Maestro_Ingredientes!$G$8) | F35: =IF(D35="","",D35*Maestro_Ingredientes!$H$8) | I35: =IF(OR(G35="",H35=""),"",G35*H35) | L35: =IF(OR(J35="",K35=""),"",J35*K35) | M35: =IF(COUNTA(G35,J35)=0,"",SUM(G35,J35)) | N35: =IF(M35="","",IF(OR(AND(G35<>0,H35=""),AND(J35<>0,K35="")),"",SUM(I35,L35))) | O35: =IF(OR(M35="",M35=0,N35=""),"",N35/M35) | P35: =IF(OR(M35="",F35=""),"",M35-F35) | Q35: =IF(OR(M35="",F35="",F35=0),"",M35/F35)
A36: 46113 | B36: ING-003 | C36: =Maestro_Ingredientes!$B$9 -> Pimiento verde | D36: =IF(Plan_Produccion!$B$10="","",Plan_Produccion!$B$10) | E36: =IF(D36="","",D36*Maestro_Ingredientes!$G$9) | F36: =IF(D36="","",D36*Maestro_Ingredientes!$H$9) | I36: =IF(OR(G36="",H36=""),"",G36*H36) | L36: =IF(OR(J36="",K36=""),"",J36*K36) | M36: =IF(COUNTA(G36,J36)=0,"",SUM(G36,J36)) | N36: =IF(M36="","",IF(OR(AND(G36<>0,H36=""),AND(J36<>0,K36="")),"",SUM(I36,L36))) | O36: =IF(OR(M36="",M36=0,N36=""),"",N36/M36) | P36: =IF(OR(M36="",F36=""),"",M36-F36) | Q36: =IF(OR(M36="",F36="",F36=0),"",M36/F36)
A37: 46113 | B37: ING-004 | C37: =Maestro_Ingredientes!$B$10 -> Cebolla | D37: =IF(Plan_Produccion!$B$10="","",Plan_Produccion!$B$10) | E37: =IF(D37="","",D37*Maestro_Ingredientes!$G$10) | F37: =IF(D37="","",D37*Maestro_Ingredientes!$H$10) | I37: =IF(OR(G37="",H37=""),"",G37*H37) | L37: =IF(OR(J37="",K37=""),"",J37*K37) | M37: =IF(COUNTA(G37,J37)=0,"",SUM(G37,J37)) | N37: =IF(M37="","",IF(OR(AND(G37<>0,H37=""),AND(J37<>0,K37="")),"",SUM(I37,L37))) | O37: =IF(OR(M37="",M37=0,N37=""),"",N37/M37) | P37: =IF(OR(M37="",F37=""),"",M37-F37) | Q37: =IF(OR(M37="",F37="",F37=0),"",M37/F37)
A38: 46113 | B38: ING-005 | C38: =Maestro_Ingredientes!$B$11 -> Ajo | D38: =IF(Plan_Produccion!$B$10="","",Plan_Produccion!$B$10) | E38: =IF(D38="","",D38*Maestro_Ingredientes!$G$11) | F38: =IF(D38="","",D38*Maestro_Ingredientes!$H$11) | I38: =IF(OR(G38="",H38=""),"",G38*H38) | L38: =IF(OR(J38="",K38=""),"",J38*K38) | M38: =IF(COUNTA(G38,J38)=0,"",SUM(G38,J38)) | N38: =IF(M38="","",IF(OR(AND(G38<>0,H38=""),AND(J38<>0,K38="")),"",SUM(I38,L38))) | O38: =IF(OR(M38="",M38=0,N38=""),"",N38/M38) | P38: =IF(OR(M38="",F38=""),"",M38-F38) | Q38: =IF(OR(M38="",F38="",F38=0),"",M38/F38)
A39: 46113 | B39: ING-006 | C39: =Maestro_Ingredientes!$B$12 -> Aceite de oliva virgen extra | D39: =IF(Plan_Produccion!$B$10="","",Plan_Produccion!$B$10) | E39: =IF(D39="","",D39*Maestro_Ingredientes!$G$12) | F39: =IF(D39="","",D39*Maestro_Ingredientes!$H$12) | I39: =IF(OR(G39="",H39=""),"",G39*H39) | L39: =IF(OR(J39="",K39=""),"",J39*K39) | M39: =IF(COUNTA(G39,J39)=0,"",SUM(G39,J39)) | N39: =IF(M39="","",IF(OR(AND(G39<>0,H39=""),AND(J39<>0,K39="")),"",SUM(I39,L39))) | O39: =IF(OR(M39="",M39=0,N39=""),"",N39/M39) | P39: =IF(OR(M39="",F39=""),"",M39-F39) | Q39: =IF(OR(M39="",F39="",F39=0),"",M39/F39)
A40: 46113 | B40: ING-007 | C40: =Maestro_Ingredientes!$B$13 -> Vinagre de Jerez | D40: =IF(Plan_Produccion!$B$10="","",Plan_Produccion!$B$10) | E40: =IF(D40="","",D40*Maestro_Ingredientes!$G$13) | F40: =IF(D40="","",D40*Maestro_Ingredientes!$H$13) | I40: =IF(OR(G40="",H40=""),"",G40*H40) | L40: =IF(OR(J40="",K40=""),"",J40*K40) | M40: =IF(COUNTA(G40,J40)=0,"",SUM(G40,J40)) | N40: =IF(M40="","",IF(OR(AND(G40<>0,H40=""),AND(J40<>0,K40="")),"",SUM(I40,L40))) | O40: =IF(OR(M40="",M40=0,N40=""),"",N40/M40) | P40: =IF(OR(M40="",F40=""),"",M40-F40) | Q40: =IF(OR(M40="",F40="",F40=0),"",M40/F40)
A41: 46113 | B41: ING-008 | C41: =Maestro_Ingredientes!$B$14 -> Sal | D41: =IF(Plan_Produccion!$B$10="","",Plan_Produccion!$B$10) | E41: =IF(D41="","",D41*Maestro_Ingredientes!$G$14) | F41: =IF(D41="","",D41*Maestro_Ingredientes!$H$14) | I41: =IF(OR(G41="",H41=""),"",G41*H41) | L41: =IF(OR(J41="",K41=""),"",J41*K41) | M41: =IF(COUNTA(G41,J41)=0,"",SUM(G41,J41)) | N41: =IF(M41="","",IF(OR(AND(G41<>0,H41=""),AND(J41<>0,K41="")),"",SUM(I41,L41))) | O41: =IF(OR(M41="",M41=0,N41=""),"",N41/M41) | P41: =IF(OR(M41="",F41=""),"",M41-F41) | Q41: =IF(OR(M41="",F41="",F41=0),"",M41/F41)
A42: 46113 | B42: ING-009 | C42: =Maestro_Ingredientes!$B$15 -> Zumo de limón | D42: =IF(Plan_Produccion!$B$10="","",Plan_Produccion!$B$10) | E42: =IF(D42="","",D42*Maestro_Ingredientes!$G$15) | F42: =IF(D42="","",D42*Maestro_Ingredientes!$H$15) | I42: =IF(OR(G42="",H42=""),"",G42*H42) | L42: =IF(OR(J42="",K42=""),"",J42*K42) | M42: =IF(COUNTA(G42,J42)=0,"",SUM(G42,J42)) | N42: =IF(M42="","",IF(OR(AND(G42<>0,H42=""),AND(J42<>0,K42="")),"",SUM(I42,L42))) | O42: =IF(OR(M42="",M42=0,N42=""),"",N42/M42) | P42: =IF(OR(M42="",F42=""),"",M42-F42) | Q42: =IF(OR(M42="",F42="",F42=0),"",M42/F42)
A43: 46143 | B43: ING-001 | C43: =Maestro_Ingredientes!$B$7 -> Tomate pera | D43: =IF(Plan_Produccion!$B$11="","",Plan_Produccion!$B$11) | E43: =IF(D43="","",D43*Maestro_Ingredientes!$G$7) | F43: =IF(D43="","",D43*Maestro_Ingredientes!$H$7) | I43: =IF(OR(G43="",H43=""),"",G43*H43) | L43: =IF(OR(J43="",K43=""),"",J43*K43) | M43: =IF(COUNTA(G43,J43)=0,"",SUM(G43,J43)) | N43: =IF(M43="","",IF(OR(AND(G43<>0,H43=""),AND(J43<>0,K43="")),"",SUM(I43,L43))) | O43: =IF(OR(M43="",M43=0,N43=""),"",N43/M43) | P43: =IF(OR(M43="",F43=""),"",M43-F43) | Q43: =IF(OR(M43="",F43="",F43=0),"",M43/F43)
A44: 46143 | B44: ING-002 | C44: =Maestro_Ingredientes!$B$8 -> Pepino | D44: =IF(Plan_Produccion!$B$11="","",Plan_Produccion!$B$11) | E44: =IF(D44="","",D44*Maestro_Ingredientes!$G$8) | F44: =IF(D44="","",D44*Maestro_Ingredientes!$H$8) | I44: =IF(OR(G44="",H44=""),"",G44*H44) | L44: =IF(OR(J44="",K44=""),"",J44*K44) | M44: =IF(COUNTA(G44,J44)=0,"",SUM(G44,J44)) | N44: =IF(M44="","",IF(OR(AND(G44<>0,H44=""),AND(J44<>0,K44="")),"",SUM(I44,L44))) | O44: =IF(OR(M44="",M44=0,N44=""),"",N44/M44) | P44: =IF(OR(M44="",F44=""),"",M44-F44) | Q44: =IF(OR(M44="",F44="",F44=0),"",M44/F44)
A45: 46143 | B45: ING-003 | C45: =Maestro_Ingredientes!$B$9 -> Pimiento verde | D45: =IF(Plan_Produccion!$B$11="","",Plan_Produccion!$B$11) | E45: =IF(D45="","",D45*Maestro_Ingredientes!$G$9) | F45: =IF(D45="","",D45*Maestro_Ingredientes!$H$9) | I45: =IF(OR(G45="",H45=""),"",G45*H45) | L45: =IF(OR(J45="",K45=""),"",J45*K45) | M45: =IF(COUNTA(G45,J45)=0,"",SUM(G45,J45)) | N45: =IF(M45="","",IF(OR(AND(G45<>0,H45=""),AND(J45<>0,K45="")),"",SUM(I45,L45))) | O45: =IF(OR(M45="",M45=0,N45=""),"",N45/M45) | P45: =IF(OR(M45="",F45=""),"",M45-F45) | Q45: =IF(OR(M45="",F45="",F45=0),"",M45/F45)
A46: 46143 | B46: ING-004 | C46: =Maestro_Ingredientes!$B$10 -> Cebolla | D46: =IF(Plan_Produccion!$B$11="","",Plan_Produccion!$B$11) | E46: =IF(D46="","",D46*Maestro_Ingredientes!$G$10) | F46: =IF(D46="","",D46*Maestro_Ingredientes!$H$10) | I46: =IF(OR(G46="",H46=""),"",G46*H46) | L46: =IF(OR(J46="",K46=""),"",J46*K46) | M46: =IF(COUNTA(G46,J46)=0,"",SUM(G46,J46)) | N46: =IF(M46="","",IF(OR(AND(G46<>0,H46=""),AND(J46<>0,K46="")),"",SUM(I46,L46))) | O46: =IF(OR(M46="",M46=0,N46=""),"",N46/M46) | P46: =IF(OR(M46="",F46=""),"",M46-F46) | Q46: =IF(OR(M46="",F46="",F46=0),"",M46/F46)
A47: 46143 | B47: ING-005 | C47: =Maestro_Ingredientes!$B$11 -> Ajo | D47: =IF(Plan_Produccion!$B$11="","",Plan_Produccion!$B$11) | E47: =IF(D47="","",D47*Maestro_Ingredientes!$G$11) | F47: =IF(D47="","",D47*Maestro_Ingredientes!$H$11) | I47: =IF(OR(G47="",H47=""),"",G47*H47) | L47: =IF(OR(J47="",K47=""),"",J47*K47) | M47: =IF(COUNTA(G47,J47)=0,"",SUM(G47,J47)) | N47: =IF(M47="","",IF(OR(AND(G47<>0,H47=""),AND(J47<>0,K47="")),"",SUM(I47,L47))) | O47: =IF(OR(M47="",M47=0,N47=""),"",N47/M47) | P47: =IF(OR(M47="",F47=""),"",M47-F47) | Q47: =IF(OR(M47="",F47="",F47=0),"",M47/F47)
A48: 46143 | B48: ING-006 | C48: =Maestro_Ingredientes!$B$12 -> Aceite de oliva virgen extra | D48: =IF(Plan_Produccion!$B$11="","",Plan_Produccion!$B$11) | E48: =IF(D48="","",D48*Maestro_Ingredientes!$G$12) | F48: =IF(D48="","",D48*Maestro_Ingredientes!$H$12) | I48: =IF(OR(G48="",H48=""),"",G48*H48) | L48: =IF(OR(J48="",K48=""),"",J48*K48) | M48: =IF(COUNTA(G48,J48)=0,"",SUM(G48,J48)) | N48: =IF(M48="","",IF(OR(AND(G48<>0,H48=""),AND(J48<>0,K48="")),"",SUM(I48,L48))) | O48: =IF(OR(M48="",M48=0,N48=""),"",N48/M48) | P48: =IF(OR(M48="",F48=""),"",M48-F48) | Q48: =IF(OR(M48="",F48="",F48=0),"",M48/F48)
A49: 46143 | B49: ING-007 | C49: =Maestro_Ingredientes!$B$13 -> Vinagre de Jerez | D49: =IF(Plan_Produccion!$B$11="","",Plan_Produccion!$B$11) | E49: =IF(D49="","",D49*Maestro_Ingredientes!$G$13) | F49: =IF(D49="","",D49*Maestro_Ingredientes!$H$13) | I49: =IF(OR(G49="",H49=""),"",G49*H49) | L49: =IF(OR(J49="",K49=""),"",J49*K49) | M49: =IF(COUNTA(G49,J49)=0,"",SUM(G49,J49)) | N49: =IF(M49="","",IF(OR(AND(G49<>0,H49=""),AND(J49<>0,K49="")),"",SUM(I49,L49))) | O49: =IF(OR(M49="",M49=0,N49=""),"",N49/M49) | P49: =IF(OR(M49="",F49=""),"",M49-F49) | Q49: =IF(OR(M49="",F49="",F49=0),"",M49/F49)
A50: 46143 | B50: ING-008 | C50: =Maestro_Ingredientes!$B$14 -> Sal | D50: =IF(Plan_Produccion!$B$11="","",Plan_Produccion!$B$11) | E50: =IF(D50="","",D50*Maestro_Ingredientes!$G$14) | F50: =IF(D50="","",D50*Maestro_Ingredientes!$H$14) | I50: =IF(OR(G50="",H50=""),"",G50*H50) | L50: =IF(OR(J50="",K50=""),"",J50*K50) | M50: =IF(COUNTA(G50,J50)=0,"",SUM(G50,J50)) | N50: =IF(M50="","",IF(OR(AND(G50<>0,H50=""),AND(J50<>0,K50="")),"",SUM(I50,L50))) | O50: =IF(OR(M50="",M50=0,N50=""),"",N50/M50) | P50: =IF(OR(M50="",F50=""),"",M50-F50) | Q50: =IF(OR(M50="",F50="",F50=0),"",M50/F50)
A51: 46143 | B51: ING-009 | C51: =Maestro_Ingredientes!$B$15 -> Zumo de limón | D51: =IF(Plan_Produccion!$B$11="","",Plan_Produccion!$B$11) | E51: =IF(D51="","",D51*Maestro_Ingredientes!$G$15) | F51: =IF(D51="","",D51*Maestro_Ingredientes!$H$15) | I51: =IF(OR(G51="",H51=""),"",G51*H51) | L51: =IF(OR(J51="",K51=""),"",J51*K51) | M51: =IF(COUNTA(G51,J51)=0,"",SUM(G51,J51)) | N51: =IF(M51="","",IF(OR(AND(G51<>0,H51=""),AND(J51<>0,K51="")),"",SUM(I51,L51))) | O51: =IF(OR(M51="",M51=0,N51=""),"",N51/M51) | P51: =IF(OR(M51="",F51=""),"",M51-F51) | Q51: =IF(OR(M51="",F51="",F51=0),"",M51/F51)
A52: 46174 | B52: ING-001 | C52: =Maestro_Ingredientes!$B$7 -> Tomate pera | D52: =IF(Plan_Produccion!$B$12="","",Plan_Produccion!$B$12) | E52: =IF(D52="","",D52*Maestro_Ingredientes!$G$7) | F52: =IF(D52="","",D52*Maestro_Ingredientes!$H$7) | I52: =IF(OR(G52="",H52=""),"",G52*H52) | L52: =IF(OR(J52="",K52=""),"",J52*K52) | M52: =IF(COUNTA(G52,J52)=0,"",SUM(G52,J52)) | N52: =IF(M52="","",IF(OR(AND(G52<>0,H52=""),AND(J52<>0,K52="")),"",SUM(I52,L52))) | O52: =IF(OR(M52="",M52=0,N52=""),"",N52/M52) | P52: =IF(OR(M52="",F52=""),"",M52-F52) | Q52: =IF(OR(M52="",F52="",F52=0),"",M52/F52)
A53: 46174 | B53: ING-002 | C53: =Maestro_Ingredientes!$B$8 -> Pepino | D53: =IF(Plan_Produccion!$B$12="","",Plan_Produccion!$B$12) | E53: =IF(D53="","",D53*Maestro_Ingredientes!$G$8) | F53: =IF(D53="","",D53*Maestro_Ingredientes!$H$8) | I53: =IF(OR(G53="",H53=""),"",G53*H53) | L53: =IF(OR(J53="",K53=""),"",J53*K53) | M53: =IF(COUNTA(G53,J53)=0,"",SUM(G53,J53)) | N53: =IF(M53="","",IF(OR(AND(G53<>0,H53=""),AND(J53<>0,K53="")),"",SUM(I53,L53))) | O53: =IF(OR(M53="",M53=0,N53=""),"",N53/M53) | P53: =IF(OR(M53="",F53=""),"",M53-F53) | Q53: =IF(OR(M53="",F53="",F53=0),"",M53/F53)
A54: 46174 | B54: ING-003 | C54: =Maestro_Ingredientes!$B$9 -> Pimiento verde | D54: =IF(Plan_Produccion!$B$12="","",Plan_Produccion!$B$12) | E54: =IF(D54="","",D54*Maestro_Ingredientes!$G$9) | F54: =IF(D54="","",D54*Maestro_Ingredientes!$H$9) | I54: =IF(OR(G54="",H54=""),"",G54*H54) | L54: =IF(OR(J54="",K54=""),"",J54*K54) | M54: =IF(COUNTA(G54,J54)=0,"",SUM(G54,J54)) | N54: =IF(M54="","",IF(OR(AND(G54<>0,H54=""),AND(J54<>0,K54="")),"",SUM(I54,L54))) | O54: =IF(OR(M54="",M54=0,N54=""),"",N54/M54) | P54: =IF(OR(M54="",F54=""),"",M54-F54) | Q54: =IF(OR(M54="",F54="",F54=0),"",M54/F54)
A55: 46174 | B55: ING-004 | C55: =Maestro_Ingredientes!$B$10 -> Cebolla | D55: =IF(Plan_Produccion!$B$12="","",Plan_Produccion!$B$12) | E55: =IF(D55="","",D55*Maestro_Ingredientes!$G$10) | F55: =IF(D55="","",D55*Maestro_Ingredientes!$H$10) | I55: =IF(OR(G55="",H55=""),"",G55*H55) | L55: =IF(OR(J55="",K55=""),"",J55*K55) | M55: =IF(COUNTA(G55,J55)=0,"",SUM(G55,J55)) | N55: =IF(M55="","",IF(OR(AND(G55<>0,H55=""),AND(J55<>0,K55="")),"",SUM(I55,L55))) | O55: =IF(OR(M55="",M55=0,N55=""),"",N55/M55) | P55: =IF(OR(M55="",F55=""),"",M55-F55) | Q55: =IF(OR(M55="",F55="",F55=0),"",M55/F55)
A56: 46174 | B56: ING-005 | C56: =Maestro_Ingredientes!$B$11 -> Ajo | D56: =IF(Plan_Produccion!$B$12="","",Plan_Produccion!$B$12) | E56: =IF(D56="","",D56*Maestro_Ingredientes!$G$11) | F56: =IF(D56="","",D56*Maestro_Ingredientes!$H$11) | I56: =IF(OR(G56="",H56=""),"",G56*H56) | L56: =IF(OR(J56="",K56=""),"",J56*K56) | M56: =IF(COUNTA(G56,J56)=0,"",SUM(G56,J56)) | N56: =IF(M56="","",IF(OR(AND(G56<>0,H56=""),AND(J56<>0,K56="")),"",SUM(I56,L56))) | O56: =IF(OR(M56="",M56=0,N56=""),"",N56/M56) | P56: =IF(OR(M56="",F56=""),"",M56-F56) | Q56: =IF(OR(M56="",F56="",F56=0),"",M56/F56)
A57: 46174 | B57: ING-006 | C57: =Maestro_Ingredientes!$B$12 -> Aceite de oliva virgen extra | D57: =IF(Plan_Produccion!$B$12="","",Plan_Produccion!$B$12) | E57: =IF(D57="","",D57*Maestro_Ingredientes!$G$12) | F57: =IF(D57="","",D57*Maestro_Ingredientes!$H$12) | I57: =IF(OR(G57="",H57=""),"",G57*H57) | L57: =IF(OR(J57="",K57=""),"",J57*K57) | M57: =IF(COUNTA(G57,J57)=0,"",SUM(G57,J57)) | N57: =IF(M57="","",IF(OR(AND(G57<>0,H57=""),AND(J57<>0,K57="")),"",SUM(I57,L57))) | O57: =IF(OR(M57="",M57=0,N57=""),"",N57/M57) | P57: =IF(OR(M57="",F57=""),"",M57-F57) | Q57: =IF(OR(M57="",F57="",F57=0),"",M57/F57)
A58: 46174 | B58: ING-007 | C58: =Maestro_Ingredientes!$B$13 -> Vinagre de Jerez | D58: =IF(Plan_Produccion!$B$12="","",Plan_Produccion!$B$12) | E58: =IF(D58="","",D58*Maestro_Ingredientes!$G$13) | F58: =IF(D58="","",D58*Maestro_Ingredientes!$H$13) | I58: =IF(OR(G58="",H58=""),"",G58*H58) | L58: =IF(OR(J58="",K58=""),"",J58*K58) | M58: =IF(COUNTA(G58,J58)=0,"",SUM(G58,J58)) | N58: =IF(M58="","",IF(OR(AND(G58<>0,H58=""),AND(J58<>0,K58="")),"",SUM(I58,L58))) | O58: =IF(OR(M58="",M58=0,N58=""),"",N58/M58) | P58: =IF(OR(M58="",F58=""),"",M58-F58) | Q58: =IF(OR(M58="",F58="",F58=0),"",M58/F58)
A59: 46174 | B59: ING-008 | C59: =Maestro_Ingredientes!$B$14 -> Sal | D59: =IF(Plan_Produccion!$B$12="","",Plan_Produccion!$B$12) | E59: =IF(D59="","",D59*Maestro_Ingredientes!$G$14) | F59: =IF(D59="","",D59*Maestro_Ingredientes!$H$14) | I59: =IF(OR(G59="",H59=""),"",G59*H59) | L59: =IF(OR(J59="",K59=""),"",J59*K59) | M59: =IF(COUNTA(G59,J59)=0,"",SUM(G59,J59)) | N59: =IF(M59="","",IF(OR(AND(G59<>0,H59=""),AND(J59<>0,K59="")),"",SUM(I59,L59))) | O59: =IF(OR(M59="",M59=0,N59=""),"",N59/M59) | P59: =IF(OR(M59="",F59=""),"",M59-F59) | Q59: =IF(OR(M59="",F59="",F59=0),"",M59/F59)
A60: 46174 | B60: ING-009 | C60: =Maestro_Ingredientes!$B$15 -> Zumo de limón | D60: =IF(Plan_Produccion!$B$12="","",Plan_Produccion!$B$12) | E60: =IF(D60="","",D60*Maestro_Ingredientes!$G$15) | F60: =IF(D60="","",D60*Maestro_Ingredientes!$H$15) | I60: =IF(OR(G60="",H60=""),"",G60*H60) | L60: =IF(OR(J60="",K60=""),"",J60*K60) | M60: =IF(COUNTA(G60,J60)=0,"",SUM(G60,J60)) | N60: =IF(M60="","",IF(OR(AND(G60<>0,H60=""),AND(J60<>0,K60="")),"",SUM(I60,L60))) | O60: =IF(OR(M60="",M60=0,N60=""),"",N60/M60) | P60: =IF(OR(M60="",F60=""),"",M60-F60) | Q60: =IF(OR(M60="",F60="",F60=0),"",M60/F60)
A61: 46204 | B61: ING-001 | C61: =Maestro_Ingredientes!$B$7 -> Tomate pera | D61: =IF(Plan_Produccion!$B$13="","",Plan_Produccion!$B$13) | E61: =IF(D61="","",D61*Maestro_Ingredientes!$G$7) | F61: =IF(D61="","",D61*Maestro_Ingredientes!$H$7) | I61: =IF(OR(G61="",H61=""),"",G61*H61) | L61: =IF(OR(J61="",K61=""),"",J61*K61) | M61: =IF(COUNTA(G61,J61)=0,"",SUM(G61,J61)) | N61: =IF(M61="","",IF(OR(AND(G61<>0,H61=""),AND(J61<>0,K61="")),"",SUM(I61,L61))) | O61: =IF(OR(M61="",M61=0,N61=""),"",N61/M61) | P61: =IF(OR(M61="",F61=""),"",M61-F61) | Q61: =IF(OR(M61="",F61="",F61=0),"",M61/F61)
A62: 46204 | B62: ING-002 | C62: =Maestro_Ingredientes!$B$8 -> Pepino | D62: =IF(Plan_Produccion!$B$13="","",Plan_Produccion!$B$13) | E62: =IF(D62="","",D62*Maestro_Ingredientes!$G$8) | F62: =IF(D62="","",D62*Maestro_Ingredientes!$H$8) | I62: =IF(OR(G62="",H62=""),"",G62*H62) | L62: =IF(OR(J62="",K62=""),"",J62*K62) | M62: =IF(COUNTA(G62,J62)=0,"",SUM(G62,J62)) | N62: =IF(M62="","",IF(OR(AND(G62<>0,H62=""),AND(J62<>0,K62="")),"",SUM(I62,L62))) | O62: =IF(OR(M62="",M62=0,N62=""),"",N62/M62) | P62: =IF(OR(M62="",F62=""),"",M62-F62) | Q62: =IF(OR(M62="",F62="",F62=0),"",M62/F62)
A63: 46204 | B63: ING-003 | C63: =Maestro_Ingredientes!$B$9 -> Pimiento verde | D63: =IF(Plan_Produccion!$B$13="","",Plan_Produccion!$B$13) | E63: =IF(D63="","",D63*Maestro_Ingredientes!$G$9) | F63: =IF(D63="","",D63*Maestro_Ingredientes!$H$9) | I63: =IF(OR(G63="",H63=""),"",G63*H63) | L63: =IF(OR(J63="",K63=""),"",J63*K63) | M63: =IF(COUNTA(G63,J63)=0,"",SUM(G63,J63)) | N63: =IF(M63="","",IF(OR(AND(G63<>0,H63=""),AND(J63<>0,K63="")),"",SUM(I63,L63))) | O63: =IF(OR(M63="",M63=0,N63=""),"",N63/M63) | P63: =IF(OR(M63="",F63=""),"",M63-F63) | Q63: =IF(OR(M63="",F63="",F63=0),"",M63/F63)
A64: 46204 | B64: ING-004 | C64: =Maestro_Ingredientes!$B$10 -> Cebolla | D64: =IF(Plan_Produccion!$B$13="","",Plan_Produccion!$B$13) | E64: =IF(D64="","",D64*Maestro_Ingredientes!$G$10) | F64: =IF(D64="","",D64*Maestro_Ingredientes!$H$10) | I64: =IF(OR(G64="",H64=""),"",G64*H64) | L64: =IF(OR(J64="",K64=""),"",J64*K64) | M64: =IF(COUNTA(G64,J64)=0,"",SUM(G64,J64)) | N64: =IF(M64="","",IF(OR(AND(G64<>0,H64=""),AND(J64<>0,K64="")),"",SUM(I64,L64))) | O64: =IF(OR(M64="",M64=0,N64=""),"",N64/M64) | P64: =IF(OR(M64="",F64=""),"",M64-F64) | Q64: =IF(OR(M64="",F64="",F64=0),"",M64/F64)
A65: 46204 | B65: ING-005 | C65: =Maestro_Ingredientes!$B$11 -> Ajo | D65: =IF(Plan_Produccion!$B$13="","",Plan_Produccion!$B$13) | E65: =IF(D65="","",D65*Maestro_Ingredientes!$G$11) | F65: =IF(D65="","",D65*Maestro_Ingredientes!$H$11) | I65: =IF(OR(G65="",H65=""),"",G65*H65) | L65: =IF(OR(J65="",K65=""),"",J65*K65) | M65: =IF(COUNTA(G65,J65)=0,"",SUM(G65,J65)) | N65: =IF(M65="","",IF(OR(AND(G65<>0,H65=""),AND(J65<>0,K65="")),"",SUM(I65,L65))) | O65: =IF(OR(M65="",M65=0,N65=""),"",N65/M65) | P65: =IF(OR(M65="",F65=""),"",M65-F65) | Q65: =IF(OR(M65="",F65="",F65=0),"",M65/F65)
A66: 46204 | B66: ING-006 | C66: =Maestro_Ingredientes!$B$12 -> Aceite de oliva virgen extra | D66: =IF(Plan_Produccion!$B$13="","",Plan_Produccion!$B$13) | E66: =IF(D66="","",D66*Maestro_Ingredientes!$G$12) | F66: =IF(D66="","",D66*Maestro_Ingredientes!$H$12) | I66: =IF(OR(G66="",H66=""),"",G66*H66) | L66: =IF(OR(J66="",K66=""),"",J66*K66) | M66: =IF(COUNTA(G66,J66)=0,"",SUM(G66,J66)) | N66: =IF(M66="","",IF(OR(AND(G66<>0,H66=""),AND(J66<>0,K66="")),"",SUM(I66,L66))) | O66: =IF(OR(M66="",M66=0,N66=""),"",N66/M66) | P66: =IF(OR(M66="",F66=""),"",M66-F66) | Q66: =IF(OR(M66="",F66="",F66=0),"",M66/F66)
A67: 46204 | B67: ING-007 | C67: =Maestro_Ingredientes!$B$13 -> Vinagre de Jerez | D67: =IF(Plan_Produccion!$B$13="","",Plan_Produccion!$B$13) | E67: =IF(D67="","",D67*Maestro_Ingredientes!$G$13) | F67: =IF(D67="","",D67*Maestro_Ingredientes!$H$13) | I67: =IF(OR(G67="",H67=""),"",G67*H67) | L67: =IF(OR(J67="",K67=""),"",J67*K67) | M67: =IF(COUNTA(G67,J67)=0,"",SUM(G67,J67)) | N67: =IF(M67="","",IF(OR(AND(G67<>0,H67=""),AND(J67<>0,K67="")),"",SUM(I67,L67))) | O67: =IF(OR(M67="",M67=0,N67=""),"",N67/M67) | P67: =IF(OR(M67="",F67=""),"",M67-F67) | Q67: =IF(OR(M67="",F67="",F67=0),"",M67/F67)
A68: 46204 | B68: ING-008 | C68: =Maestro_Ingredientes!$B$14 -> Sal | D68: =IF(Plan_Produccion!$B$13="","",Plan_Produccion!$B$13) | E68: =IF(D68="","",D68*Maestro_Ingredientes!$G$14) | F68: =IF(D68="","",D68*Maestro_Ingredientes!$H$14) | I68: =IF(OR(G68="",H68=""),"",G68*H68) | L68: =IF(OR(J68="",K68=""),"",J68*K68) | M68: =IF(COUNTA(G68,J68)=0,"",SUM(G68,J68)) | N68: =IF(M68="","",IF(OR(AND(G68<>0,H68=""),AND(J68<>0,K68="")),"",SUM(I68,L68))) | O68: =IF(OR(M68="",M68=0,N68=""),"",N68/M68) | P68: =IF(OR(M68="",F68=""),"",M68-F68) | Q68: =IF(OR(M68="",F68="",F68=0),"",M68/F68)
A69: 46204 | B69: ING-009 | C69: =Maestro_Ingredientes!$B$15 -> Zumo de limón | D69: =IF(Plan_Produccion!$B$13="","",Plan_Produccion!$B$13) | E69: =IF(D69="","",D69*Maestro_Ingredientes!$G$15) | F69: =IF(D69="","",D69*Maestro_Ingredientes!$H$15) | I69: =IF(OR(G69="",H69=""),"",G69*H69) | L69: =IF(OR(J69="",K69=""),"",J69*K69) | M69: =IF(COUNTA(G69,J69)=0,"",SUM(G69,J69)) | N69: =IF(M69="","",IF(OR(AND(G69<>0,H69=""),AND(J69<>0,K69="")),"",SUM(I69,L69))) | O69: =IF(OR(M69="",M69=0,N69=""),"",N69/M69) | P69: =IF(OR(M69="",F69=""),"",M69-F69) | Q69: =IF(OR(M69="",F69="",F69=0),"",M69/F69)
A70: 46235 | B70: ING-001 | C70: =Maestro_Ingredientes!$B$7 -> Tomate pera | D70: =IF(Plan_Produccion!$B$14="","",Plan_Produccion!$B$14) | E70: =IF(D70="","",D70*Maestro_Ingredientes!$G$7) | F70: =IF(D70="","",D70*Maestro_Ingredientes!$H$7) | I70: =IF(OR(G70="",H70=""),"",G70*H70) | L70: =IF(OR(J70="",K70=""),"",J70*K70) | M70: =IF(COUNTA(G70,J70)=0,"",SUM(G70,J70)) | N70: =IF(M70="","",IF(OR(AND(G70<>0,H70=""),AND(J70<>0,K70="")),"",SUM(I70,L70))) | O70: =IF(OR(M70="",M70=0,N70=""),"",N70/M70) | P70: =IF(OR(M70="",F70=""),"",M70-F70) | Q70: =IF(OR(M70="",F70="",F70=0),"",M70/F70)
A71: 46235 | B71: ING-002 | C71: =Maestro_Ingredientes!$B$8 -> Pepino | D71: =IF(Plan_Produccion!$B$14="","",Plan_Produccion!$B$14) | E71: =IF(D71="","",D71*Maestro_Ingredientes!$G$8) | F71: =IF(D71="","",D71*Maestro_Ingredientes!$H$8) | I71: =IF(OR(G71="",H71=""),"",G71*H71) | L71: =IF(OR(J71="",K71=""),"",J71*K71) | M71: =IF(COUNTA(G71,J71)=0,"",SUM(G71,J71)) | N71: =IF(M71="","",IF(OR(AND(G71<>0,H71=""),AND(J71<>0,K71="")),"",SUM(I71,L71))) | O71: =IF(OR(M71="",M71=0,N71=""),"",N71/M71) | P71: =IF(OR(M71="",F71=""),"",M71-F71) | Q71: =IF(OR(M71="",F71="",F71=0),"",M71/F71)
A72: 46235 | B72: ING-003 | C72: =Maestro_Ingredientes!$B$9 -> Pimiento verde | D72: =IF(Plan_Produccion!$B$14="","",Plan_Produccion!$B$14) | E72: =IF(D72="","",D72*Maestro_Ingredientes!$G$9) | F72: =IF(D72="","",D72*Maestro_Ingredientes!$H$9) | I72: =IF(OR(G72="",H72=""),"",G72*H72) | L72: =IF(OR(J72="",K72=""),"",J72*K72) | M72: =IF(COUNTA(G72,J72)=0,"",SUM(G72,J72)) | N72: =IF(M72="","",IF(OR(AND(G72<>0,H72=""),AND(J72<>0,K72="")),"",SUM(I72,L72))) | O72: =IF(OR(M72="",M72=0,N72=""),"",N72/M72) | P72: =IF(OR(M72="",F72=""),"",M72-F72) | Q72: =IF(OR(M72="",F72="",F72=0),"",M72/F72)
A73: 46235 | B73: ING-004 | C73: =Maestro_Ingredientes!$B$10 -> Cebolla | D73: =IF(Plan_Produccion!$B$14="","",Plan_Produccion!$B$14) | E73: =IF(D73="","",D73*Maestro_Ingredientes!$G$10) | F73: =IF(D73="","",D73*Maestro_Ingredientes!$H$10) | I73: =IF(OR(G73="",H73=""),"",G73*H73) | L73: =IF(OR(J73="",K73=""),"",J73*K73) | M73: =IF(COUNTA(G73,J73)=0,"",SUM(G73,J73)) | N73: =IF(M73="","",IF(OR(AND(G73<>0,H73=""),AND(J73<>0,K73="")),"",SUM(I73,L73))) | O73: =IF(OR(M73="",M73=0,N73=""),"",N73/M73) | P73: =IF(OR(M73="",F73=""),"",M73-F73) | Q73: =IF(OR(M73="",F73="",F73=0),"",M73/F73)
A74: 46235 | B74: ING-005 | C74: =Maestro_Ingredientes!$B$11 -> Ajo | D74: =IF(Plan_Produccion!$B$14="","",Plan_Produccion!$B$14) | E74: =IF(D74="","",D74*Maestro_Ingredientes!$G$11) | F74: =IF(D74="","",D74*Maestro_Ingredientes!$H$11) | I74: =IF(OR(G74="",H74=""),"",G74*H74) | L74: =IF(OR(J74="",K74=""),"",J74*K74) | M74: =IF(COUNTA(G74,J74)=0,"",SUM(G74,J74)) | N74: =IF(M74="","",IF(OR(AND(G74<>0,H74=""),AND(J74<>0,K74="")),"",SUM(I74,L74))) | O74: =IF(OR(M74="",M74=0,N74=""),"",N74/M74) | P74: =IF(OR(M74="",F74=""),"",M74-F74) | Q74: =IF(OR(M74="",F74="",F74=0),"",M74/F74)
A75: 46235 | B75: ING-006 | C75: =Maestro_Ingredientes!$B$12 -> Aceite de oliva virgen extra | D75: =IF(Plan_Produccion!$B$14="","",Plan_Produccion!$B$14) | E75: =IF(D75="","",D75*Maestro_Ingredientes!$G$12) | F75: =IF(D75="","",D75*Maestro_Ingredientes!$H$12) | I75: =IF(OR(G75="",H75=""),"",G75*H75) | L75: =IF(OR(J75="",K75=""),"",J75*K75) | M75: =IF(COUNTA(G75,J75)=0,"",SUM(G75,J75)) | N75: =IF(M75="","",IF(OR(AND(G75<>0,H75=""),AND(J75<>0,K75="")),"",SUM(I75,L75))) | O75: =IF(OR(M75="",M75=0,N75=""),"",N75/M75) | P75: =IF(OR(M75="",F75=""),"",M75-F75) | Q75: =IF(OR(M75="",F75="",F75=0),"",M75/F75)
A76: 46235 | B76: ING-007 | C76: =Maestro_Ingredientes!$B$13 -> Vinagre de Jerez | D76: =IF(Plan_Produccion!$B$14="","",Plan_Produccion!$B$14) | E76: =IF(D76="","",D76*Maestro_Ingredientes!$G$13) | F76: =IF(D76="","",D76*Maestro_Ingredientes!$H$13) | I76: =IF(OR(G76="",H76=""),"",G76*H76) | L76: =IF(OR(J76="",K76=""),"",J76*K76) | M76: =IF(COUNTA(G76,J76)=0,"",SUM(G76,J76)) | N76: =IF(M76="","",IF(OR(AND(G76<>0,H76=""),AND(J76<>0,K76="")),"",SUM(I76,L76))) | O76: =IF(OR(M76="",M76=0,N76=""),"",N76/M76) | P76: =IF(OR(M76="",F76=""),"",M76-F76) | Q76: =IF(OR(M76="",F76="",F76=0),"",M76/F76)
A77: 46235 | B77: ING-008 | C77: =Maestro_Ingredientes!$B$14 -> Sal | D77: =IF(Plan_Produccion!$B$14="","",Plan_Produccion!$B$14) | E77: =IF(D77="","",D77*Maestro_Ingredientes!$G$14) | F77: =IF(D77="","",D77*Maestro_Ingredientes!$H$14) | I77: =IF(OR(G77="",H77=""),"",G77*H77) | L77: =IF(OR(J77="",K77=""),"",J77*K77) | M77: =IF(COUNTA(G77,J77)=0,"",SUM(G77,J77)) | N77: =IF(M77="","",IF(OR(AND(G77<>0,H77=""),AND(J77<>0,K77="")),"",SUM(I77,L77))) | O77: =IF(OR(M77="",M77=0,N77=""),"",N77/M77) | P77: =IF(OR(M77="",F77=""),"",M77-F77) | Q77: =IF(OR(M77="",F77="",F77=0),"",M77/F77)
A78: 46235 | B78: ING-009 | C78: =Maestro_Ingredientes!$B$15 -> Zumo de limón | D78: =IF(Plan_Produccion!$B$14="","",Plan_Produccion!$B$14) | E78: =IF(D78="","",D78*Maestro_Ingredientes!$G$15) | F78: =IF(D78="","",D78*Maestro_Ingredientes!$H$15) | I78: =IF(OR(G78="",H78=""),"",G78*H78) | L78: =IF(OR(J78="",K78=""),"",J78*K78) | M78: =IF(COUNTA(G78,J78)=0,"",SUM(G78,J78)) | N78: =IF(M78="","",IF(OR(AND(G78<>0,H78=""),AND(J78<>0,K78="")),"",SUM(I78,L78))) | O78: =IF(OR(M78="",M78=0,N78=""),"",N78/M78) | P78: =IF(OR(M78="",F78=""),"",M78-F78) | Q78: =IF(OR(M78="",F78="",F78=0),"",M78/F78)
A79: 46266 | B79: ING-001 | C79: =Maestro_Ingredientes!$B$7 -> Tomate pera | D79: =IF(Plan_Produccion!$B$15="","",Plan_Produccion!$B$15) | E79: =IF(D79="","",D79*Maestro_Ingredientes!$G$7) | F79: =IF(D79="","",D79*Maestro_Ingredientes!$H$7) | I79: =IF(OR(G79="",H79=""),"",G79*H79) | L79: =IF(OR(J79="",K79=""),"",J79*K79) | M79: =IF(COUNTA(G79,J79)=0,"",SUM(G79,J79)) | N79: =IF(M79="","",IF(OR(AND(G79<>0,H79=""),AND(J79<>0,K79="")),"",SUM(I79,L79))) | O79: =IF(OR(M79="",M79=0,N79=""),"",N79/M79) | P79: =IF(OR(M79="",F79=""),"",M79-F79) | Q79: =IF(OR(M79="",F79="",F79=0),"",M79/F79)
A80: 46266 | B80: ING-002 | C80: =Maestro_Ingredientes!$B$8 -> Pepino | D80: =IF(Plan_Produccion!$B$15="","",Plan_Produccion!$B$15) | E80: =IF(D80="","",D80*Maestro_Ingredientes!$G$8) | F80: =IF(D80="","",D80*Maestro_Ingredientes!$H$8) | I80: =IF(OR(G80="",H80=""),"",G80*H80) | L80: =IF(OR(J80="",K80=""),"",J80*K80) | M80: =IF(COUNTA(G80,J80)=0,"",SUM(G80,J80)) | N80: =IF(M80="","",IF(OR(AND(G80<>0,H80=""),AND(J80<>0,K80="")),"",SUM(I80,L80))) | O80: =IF(OR(M80="",M80=0,N80=""),"",N80/M80) | P80: =IF(OR(M80="",F80=""),"",M80-F80) | Q80: =IF(OR(M80="",F80="",F80=0),"",M80/F80)
A81: 46266 | B81: ING-003 | C81: =Maestro_Ingredientes!$B$9 -> Pimiento verde | D81: =IF(Plan_Produccion!$B$15="","",Plan_Produccion!$B$15) | E81: =IF(D81="","",D81*Maestro_Ingredientes!$G$9) | F81: =IF(D81="","",D81*Maestro_Ingredientes!$H$9) | I81: =IF(OR(G81="",H81=""),"",G81*H81) | L81: =IF(OR(J81="",K81=""),"",J81*K81) | M81: =IF(COUNTA(G81,J81)=0,"",SUM(G81,J81)) | N81: =IF(M81="","",IF(OR(AND(G81<>0,H81=""),AND(J81<>0,K81="")),"",SUM(I81,L81))) | O81: =IF(OR(M81="",M81=0,N81=""),"",N81/M81) | P81: =IF(OR(M81="",F81=""),"",M81-F81) | Q81: =IF(OR(M81="",F81="",F81=0),"",M81/F81)
A82: 46266 | B82: ING-004 | C82: =Maestro_Ingredientes!$B$10 -> Cebolla | D82: =IF(Plan_Produccion!$B$15="","",Plan_Produccion!$B$15) | E82: =IF(D82="","",D82*Maestro_Ingredientes!$G$10) | F82: =IF(D82="","",D82*Maestro_Ingredientes!$H$10) | I82: =IF(OR(G82="",H82=""),"",G82*H82) | L82: =IF(OR(J82="",K82=""),"",J82*K82) | M82: =IF(COUNTA(G82,J82)=0,"",SUM(G82,J82)) | N82: =IF(M82="","",IF(OR(AND(G82<>0,H82=""),AND(J82<>0,K82="")),"",SUM(I82,L82))) | O82: =IF(OR(M82="",M82=0,N82=""),"",N82/M82) | P82: =IF(OR(M82="",F82=""),"",M82-F82) | Q82: =IF(OR(M82="",F82="",F82=0),"",M82/F82)
A83: 46266 | B83: ING-005 | C83: =Maestro_Ingredientes!$B$11 -> Ajo | D83: =IF(Plan_Produccion!$B$15="","",Plan_Produccion!$B$15) | E83: =IF(D83="","",D83*Maestro_Ingredientes!$G$11) | F83: =IF(D83="","",D83*Maestro_Ingredientes!$H$11) | I83: =IF(OR(G83="",H83=""),"",G83*H83) | L83: =IF(OR(J83="",K83=""),"",J83*K83) | M83: =IF(COUNTA(G83,J83)=0,"",SUM(G83,J83)) | N83: =IF(M83="","",IF(OR(AND(G83<>0,H83=""),AND(J83<>0,K83="")),"",SUM(I83,L83))) | O83: =IF(OR(M83="",M83=0,N83=""),"",N83/M83) | P83: =IF(OR(M83="",F83=""),"",M83-F83) | Q83: =IF(OR(M83="",F83="",F83=0),"",M83/F83)
A84: 46266 | B84: ING-006 | C84: =Maestro_Ingredientes!$B$12 -> Aceite de oliva virgen extra | D84: =IF(Plan_Produccion!$B$15="","",Plan_Produccion!$B$15) | E84: =IF(D84="","",D84*Maestro_Ingredientes!$G$12) | F84: =IF(D84="","",D84*Maestro_Ingredientes!$H$12) | I84: =IF(OR(G84="",H84=""),"",G84*H84) | L84: =IF(OR(J84="",K84=""),"",J84*K84) | M84: =IF(COUNTA(G84,J84)=0,"",SUM(G84,J84)) | N84: =IF(M84="","",IF(OR(AND(G84<>0,H84=""),AND(J84<>0,K84="")),"",SUM(I84,L84))) | O84: =IF(OR(M84="",M84=0,N84=""),"",N84/M84) | P84: =IF(OR(M84="",F84=""),"",M84-F84) | Q84: =IF(OR(M84="",F84="",F84=0),"",M84/F84)
A85: 46266 | B85: ING-007 | C85: =Maestro_Ingredientes!$B$13 -> Vinagre de Jerez | D85: =IF(Plan_Produccion!$B$15="","",Plan_Produccion!$B$15) | E85: =IF(D85="","",D85*Maestro_Ingredientes!$G$13) | F85: =IF(D85="","",D85*Maestro_Ingredientes!$H$13) | I85: =IF(OR(G85="",H85=""),"",G85*H85) | L85: =IF(OR(J85="",K85=""),"",J85*K85) | M85: =IF(COUNTA(G85,J85)=0,"",SUM(G85,J85)) | N85: =IF(M85="","",IF(OR(AND(G85<>0,H85=""),AND(J85<>0,K85="")),"",SUM(I85,L85))) | O85: =IF(OR(M85="",M85=0,N85=""),"",N85/M85) | P85: =IF(OR(M85="",F85=""),"",M85-F85) | Q85: =IF(OR(M85="",F85="",F85=0),"",M85/F85)
A86: 46266 | B86: ING-008 | C86: =Maestro_Ingredientes!$B$14 -> Sal | D86: =IF(Plan_Produccion!$B$15="","",Plan_Produccion!$B$15) | E86: =IF(D86="","",D86*Maestro_Ingredientes!$G$14) | F86: =IF(D86="","",D86*Maestro_Ingredientes!$H$14) | I86: =IF(OR(G86="",H86=""),"",G86*H86) | L86: =IF(OR(J86="",K86=""),"",J86*K86) | M86: =IF(COUNTA(G86,J86)=0,"",SUM(G86,J86)) | N86: =IF(M86="","",IF(OR(AND(G86<>0,H86=""),AND(J86<>0,K86="")),"",SUM(I86,L86))) | O86: =IF(OR(M86="",M86=0,N86=""),"",N86/M86) | P86: =IF(OR(M86="",F86=""),"",M86-F86) | Q86: =IF(OR(M86="",F86="",F86=0),"",M86/F86)
A87: 46266 | B87: ING-009 | C87: =Maestro_Ingredientes!$B$15 -> Zumo de limón | D87: =IF(Plan_Produccion!$B$15="","",Plan_Produccion!$B$15) | E87: =IF(D87="","",D87*Maestro_Ingredientes!$G$15) | F87: =IF(D87="","",D87*Maestro_Ingredientes!$H$15) | I87: =IF(OR(G87="",H87=""),"",G87*H87) | L87: =IF(OR(J87="",K87=""),"",J87*K87) | M87: =IF(COUNTA(G87,J87)=0,"",SUM(G87,J87)) | N87: =IF(M87="","",IF(OR(AND(G87<>0,H87=""),AND(J87<>0,K87="")),"",SUM(I87,L87))) | O87: =IF(OR(M87="",M87=0,N87=""),"",N87/M87) | P87: =IF(OR(M87="",F87=""),"",M87-F87) | Q87: =IF(OR(M87="",F87="",F87=0),"",M87/F87)
A88: 46296 | B88: ING-001 | C88: =Maestro_Ingredientes!$B$7 -> Tomate pera | D88: =IF(Plan_Produccion!$B$16="","",Plan_Produccion!$B$16) | E88: =IF(D88="","",D88*Maestro_Ingredientes!$G$7) | F88: =IF(D88="","",D88*Maestro_Ingredientes!$H$7) | I88: =IF(OR(G88="",H88=""),"",G88*H88) | L88: =IF(OR(J88="",K88=""),"",J88*K88) | M88: =IF(COUNTA(G88,J88)=0,"",SUM(G88,J88)) | N88: =IF(M88="","",IF(OR(AND(G88<>0,H88=""),AND(J88<>0,K88="")),"",SUM(I88,L88))) | O88: =IF(OR(M88="",M88=0,N88=""),"",N88/M88) | P88: =IF(OR(M88="",F88=""),"",M88-F88) | Q88: =IF(OR(M88="",F88="",F88=0),"",M88/F88)
A89: 46296 | B89: ING-002 | C89: =Maestro_Ingredientes!$B$8 -> Pepino | D89: =IF(Plan_Produccion!$B$16="","",Plan_Produccion!$B$16) | E89: =IF(D89="","",D89*Maestro_Ingredientes!$G$8) | F89: =IF(D89="","",D89*Maestro_Ingredientes!$H$8) | I89: =IF(OR(G89="",H89=""),"",G89*H89) | L89: =IF(OR(J89="",K89=""),"",J89*K89) | M89: =IF(COUNTA(G89,J89)=0,"",SUM(G89,J89)) | N89: =IF(M89="","",IF(OR(AND(G89<>0,H89=""),AND(J89<>0,K89="")),"",SUM(I89,L89))) | O89: =IF(OR(M89="",M89=0,N89=""),"",N89/M89) | P89: =IF(OR(M89="",F89=""),"",M89-F89) | Q89: =IF(OR(M89="",F89="",F89=0),"",M89/F89)
A90: 46296 | B90: ING-003 | C90: =Maestro_Ingredientes!$B$9 -> Pimiento verde | D90: =IF(Plan_Produccion!$B$16="","",Plan_Produccion!$B$16) | E90: =IF(D90="","",D90*Maestro_Ingredientes!$G$9) | F90: =IF(D90="","",D90*Maestro_Ingredientes!$H$9) | I90: =IF(OR(G90="",H90=""),"",G90*H90) | L90: =IF(OR(J90="",K90=""),"",J90*K90) | M90: =IF(COUNTA(G90,J90)=0,"",SUM(G90,J90)) | N90: =IF(M90="","",IF(OR(AND(G90<>0,H90=""),AND(J90<>0,K90="")),"",SUM(I90,L90))) | O90: =IF(OR(M90="",M90=0,N90=""),"",N90/M90) | P90: =IF(OR(M90="",F90=""),"",M90-F90) | Q90: =IF(OR(M90="",F90="",F90=0),"",M90/F90)
A91: 46296 | B91: ING-004 | C91: =Maestro_Ingredientes!$B$10 -> Cebolla | D91: =IF(Plan_Produccion!$B$16="","",Plan_Produccion!$B$16) | E91: =IF(D91="","",D91*Maestro_Ingredientes!$G$10) | F91: =IF(D91="","",D91*Maestro_Ingredientes!$H$10) | I91: =IF(OR(G91="",H91=""),"",G91*H91) | L91: =IF(OR(J91="",K91=""),"",J91*K91) | M91: =IF(COUNTA(G91,J91)=0,"",SUM(G91,J91)) | N91: =IF(M91="","",IF(OR(AND(G91<>0,H91=""),AND(J91<>0,K91="")),"",SUM(I91,L91))) | O91: =IF(OR(M91="",M91=0,N91=""),"",N91/M91) | P91: =IF(OR(M91="",F91=""),"",M91-F91) | Q91: =IF(OR(M91="",F91="",F91=0),"",M91/F91)
A92: 46296 | B92: ING-005 | C92: =Maestro_Ingredientes!$B$11 -> Ajo | D92: =IF(Plan_Produccion!$B$16="","",Plan_Produccion!$B$16) | E92: =IF(D92="","",D92*Maestro_Ingredientes!$G$11) | F92: =IF(D92="","",D92*Maestro_Ingredientes!$H$11) | I92: =IF(OR(G92="",H92=""),"",G92*H92) | L92: =IF(OR(J92="",K92=""),"",J92*K92) | M92: =IF(COUNTA(G92,J92)=0,"",SUM(G92,J92)) | N92: =IF(M92="","",IF(OR(AND(G92<>0,H92=""),AND(J92<>0,K92="")),"",SUM(I92,L92))) | O92: =IF(OR(M92="",M92=0,N92=""),"",N92/M92) | P92: =IF(OR(M92="",F92=""),"",M92-F92) | Q92: =IF(OR(M92="",F92="",F92=0),"",M92/F92)
A93: 46296 | B93: ING-006 | C93: =Maestro_Ingredientes!$B$12 -> Aceite de oliva virgen extra | D93: =IF(Plan_Produccion!$B$16="","",Plan_Produccion!$B$16) | E93: =IF(D93="","",D93*Maestro_Ingredientes!$G$12) | F93: =IF(D93="","",D93*Maestro_Ingredientes!$H$12) | I93: =IF(OR(G93="",H93=""),"",G93*H93) | L93: =IF(OR(J93="",K93=""),"",J93*K93) | M93: =IF(COUNTA(G93,J93)=0,"",SUM(G93,J93)) | N93: =IF(M93="","",IF(OR(AND(G93<>0,H93=""),AND(J93<>0,K93="")),"",SUM(I93,L93))) | O93: =IF(OR(M93="",M93=0,N93=""),"",N93/M93) | P93: =IF(OR(M93="",F93=""),"",M93-F93) | Q93: =IF(OR(M93="",F93="",F93=0),"",M93/F93)
A94: 46296 | B94: ING-007 | C94: =Maestro_Ingredientes!$B$13 -> Vinagre de Jerez | D94: =IF(Plan_Produccion!$B$16="","",Plan_Produccion!$B$16) | E94: =IF(D94="","",D94*Maestro_Ingredientes!$G$13) | F94: =IF(D94="","",D94*Maestro_Ingredientes!$H$13) | I94: =IF(OR(G94="",H94=""),"",G94*H94) | L94: =IF(OR(J94="",K94=""),"",J94*K94) | M94: =IF(COUNTA(G94,J94)=0,"",SUM(G94,J94)) | N94: =IF(M94="","",IF(OR(AND(G94<>0,H94=""),AND(J94<>0,K94="")),"",SUM(I94,L94))) | O94: =IF(OR(M94="",M94=0,N94=""),"",N94/M94) | P94: =IF(OR(M94="",F94=""),"",M94-F94) | Q94: =IF(OR(M94="",F94="",F94=0),"",M94/F94)
A95: 46296 | B95: ING-008 | C95: =Maestro_Ingredientes!$B$14 -> Sal | D95: =IF(Plan_Produccion!$B$16="","",Plan_Produccion!$B$16) | E95: =IF(D95="","",D95*Maestro_Ingredientes!$G$14) | F95: =IF(D95="","",D95*Maestro_Ingredientes!$H$14) | I95: =IF(OR(G95="",H95=""),"",G95*H95) | L95: =IF(OR(J95="",K95=""),"",J95*K95) | M95: =IF(COUNTA(G95,J95)=0,"",SUM(G95,J95)) | N95: =IF(M95="","",IF(OR(AND(G95<>0,H95=""),AND(J95<>0,K95="")),"",SUM(I95,L95))) | O95: =IF(OR(M95="",M95=0,N95=""),"",N95/M95) | P95: =IF(OR(M95="",F95=""),"",M95-F95) | Q95: =IF(OR(M95="",F95="",F95=0),"",M95/F95)
A96: 46296 | B96: ING-009 | C96: =Maestro_Ingredientes!$B$15 -> Zumo de limón | D96: =IF(Plan_Produccion!$B$16="","",Plan_Produccion!$B$16) | E96: =IF(D96="","",D96*Maestro_Ingredientes!$G$15) | F96: =IF(D96="","",D96*Maestro_Ingredientes!$H$15) | I96: =IF(OR(G96="",H96=""),"",G96*H96) | L96: =IF(OR(J96="",K96=""),"",J96*K96) | M96: =IF(COUNTA(G96,J96)=0,"",SUM(G96,J96)) | N96: =IF(M96="","",IF(OR(AND(G96<>0,H96=""),AND(J96<>0,K96="")),"",SUM(I96,L96))) | O96: =IF(OR(M96="",M96=0,N96=""),"",N96/M96) | P96: =IF(OR(M96="",F96=""),"",M96-F96) | Q96: =IF(OR(M96="",F96="",F96=0),"",M96/F96)
A97: 46327 | B97: ING-001 | C97: =Maestro_Ingredientes!$B$7 -> Tomate pera | D97: =IF(Plan_Produccion!$B$17="","",Plan_Produccion!$B$17) | E97: =IF(D97="","",D97*Maestro_Ingredientes!$G$7) | F97: =IF(D97="","",D97*Maestro_Ingredientes!$H$7) | I97: =IF(OR(G97="",H97=""),"",G97*H97) | L97: =IF(OR(J97="",K97=""),"",J97*K97) | M97: =IF(COUNTA(G97,J97)=0,"",SUM(G97,J97)) | N97: =IF(M97="","",IF(OR(AND(G97<>0,H97=""),AND(J97<>0,K97="")),"",SUM(I97,L97))) | O97: =IF(OR(M97="",M97=0,N97=""),"",N97/M97) | P97: =IF(OR(M97="",F97=""),"",M97-F97) | Q97: =IF(OR(M97="",F97="",F97=0),"",M97/F97)
A98: 46327 | B98: ING-002 | C98: =Maestro_Ingredientes!$B$8 -> Pepino | D98: =IF(Plan_Produccion!$B$17="","",Plan_Produccion!$B$17) | E98: =IF(D98="","",D98*Maestro_Ingredientes!$G$8) | F98: =IF(D98="","",D98*Maestro_Ingredientes!$H$8) | I98: =IF(OR(G98="",H98=""),"",G98*H98) | L98: =IF(OR(J98="",K98=""),"",J98*K98) | M98: =IF(COUNTA(G98,J98)=0,"",SUM(G98,J98)) | N98: =IF(M98="","",IF(OR(AND(G98<>0,H98=""),AND(J98<>0,K98="")),"",SUM(I98,L98))) | O98: =IF(OR(M98="",M98=0,N98=""),"",N98/M98) | P98: =IF(OR(M98="",F98=""),"",M98-F98) | Q98: =IF(OR(M98="",F98="",F98=0),"",M98/F98)
A99: 46327 | B99: ING-003 | C99: =Maestro_Ingredientes!$B$9 -> Pimiento verde | D99: =IF(Plan_Produccion!$B$17="","",Plan_Produccion!$B$17) | E99: =IF(D99="","",D99*Maestro_Ingredientes!$G$9) | F99: =IF(D99="","",D99*Maestro_Ingredientes!$H$9) | I99: =IF(OR(G99="",H99=""),"",G99*H99) | L99: =IF(OR(J99="",K99=""),"",J99*K99) | M99: =IF(COUNTA(G99,J99)=0,"",SUM(G99,J99)) | N99: =IF(M99="","",IF(OR(AND(G99<>0,H99=""),AND(J99<>0,K99="")),"",SUM(I99,L99))) | O99: =IF(OR(M99="",M99=0,N99=""),"",N99/M99) | P99: =IF(OR(M99="",F99=""),"",M99-F99) | Q99: =IF(OR(M99="",F99="",F99=0),"",M99/F99)
A100: 46327 | B100: ING-004 | C100: =Maestro_Ingredientes!$B$10 -> Cebolla | D100: =IF(Plan_Produccion!$B$17="","",Plan_Produccion!$B$17) | E100: =IF(D100="","",D100*Maestro_Ingredientes!$G$10) | F100: =IF(D100="","",D100*Maestro_Ingredientes!$H$10) | I100: =IF(OR(G100="",H100=""),"",G100*H100) | L100: =IF(OR(J100="",K100=""),"",J100*K100) | M100: =IF(COUNTA(G100,J100)=0,"",SUM(G100,J100)) | N100: =IF(M100="","",IF(OR(AND(G100<>0,H100=""),AND(J100<>0,K100="")),"",SUM(I100,L100))) | O100: =IF(OR(M100="",M100=0,N100=""),"",N100/M100) | P100: =IF(OR(M100="",F100=""),"",M100-F100) | Q100: =IF(OR(M100="",F100="",F100=0),"",M100/F100)
A101: 46327 | B101: ING-005 | C101: =Maestro_Ingredientes!$B$11 -> Ajo | D101: =IF(Plan_Produccion!$B$17="","",Plan_Produccion!$B$17) | E101: =IF(D101="","",D101*Maestro_Ingredientes!$G$11) | F101: =IF(D101="","",D101*Maestro_Ingredientes!$H$11) | I101: =IF(OR(G101="",H101=""),"",G101*H101) | L101: =IF(OR(J101="",K101=""),"",J101*K101) | M101: =IF(COUNTA(G101,J101)=0,"",SUM(G101,J101)) | N101: =IF(M101="","",IF(OR(AND(G101<>0,H101=""),AND(J101<>0,K101="")),"",SUM(I101,L101))) | O101: =IF(OR(M101="",M101=0,N101=""),"",N101/M101) | P101: =IF(OR(M101="",F101=""),"",M101-F101) | Q101: =IF(OR(M101="",F101="",F101=0),"",M101/F101)
A102: 46327 | B102: ING-006 | C102: =Maestro_Ingredientes!$B$12 -> Aceite de oliva virgen extra | D102: =IF(Plan_Produccion!$B$17="","",Plan_Produccion!$B$17) | E102: =IF(D102="","",D102*Maestro_Ingredientes!$G$12) | F102: =IF(D102="","",D102*Maestro_Ingredientes!$H$12) | I102: =IF(OR(G102="",H102=""),"",G102*H102) | L102: =IF(OR(J102="",K102=""),"",J102*K102) | M102: =IF(COUNTA(G102,J102)=0,"",SUM(G102,J102)) | N102: =IF(M102="","",IF(OR(AND(G102<>0,H102=""),AND(J102<>0,K102="")),"",SUM(I102,L102))) | O102: =IF(OR(M102="",M102=0,N102=""),"",N102/M102) | P102: =IF(OR(M102="",F102=""),"",M102-F102) | Q102: =IF(OR(M102="",F102="",F102=0),"",M102/F102)
A103: 46327 | B103: ING-007 | C103: =Maestro_Ingredientes!$B$13 -> Vinagre de Jerez | D103: =IF(Plan_Produccion!$B$17="","",Plan_Produccion!$B$17) | E103: =IF(D103="","",D103*Maestro_Ingredientes!$G$13) | F103: =IF(D103="","",D103*Maestro_Ingredientes!$H$13) | I103: =IF(OR(G103="",H103=""),"",G103*H103) | L103: =IF(OR(J103="",K103=""),"",J103*K103) | M103: =IF(COUNTA(G103,J103)=0,"",SUM(G103,J103)) | N103: =IF(M103="","",IF(OR(AND(G103<>0,H103=""),AND(J103<>0,K103="")),"",SUM(I103,L103))) | O103: =IF(OR(M103="",M103=0,N103=""),"",N103/M103) | P103: =IF(OR(M103="",F103=""),"",M103-F103) | Q103: =IF(OR(M103="",F103="",F103=0),"",M103/F103)
...

Sheet Modelo_Costes
A2: Modelo de costes y KPI
A3: Modelo anual para 2026 | EUR | kg y litros
A6: KPI anuales / acumulados | R6: Los gráficos se completan después de introducir los precios de compra.
A8: Producción planificada / registrada acumulada | B8: =SUM(Plan_Produccion!$B$7:$B$18) -> 100000 | D8: Definición | E8: Valor
A9: Necesidad neta de materia prima | B9: =SUM(Plan_Produccion!$C$7:$C$18) -> 100000 | D9: Año del modelo | E9: =Supuestos!$B$7 -> 2026
A10: Necesidad bruta de materia prima | B10: =SUM(Plan_Produccion!$D$7:$D$18) -> 109651.13 | D10: Escenario anual de referencia L | E10: =Supuestos!$B$8 -> 1200000
A11: Materia prima comprada | B11: =SUM(Plan_Compras!$M$7:$M$114) -> 109651.13 | D11: Umbral de alerta de merma | E11: =Supuestos!$B$13 -> 0.01
A12: Merma esperada kg | B12: =SUM(Plan_Produccion!$E$7:$E$18) -> 9651.1305 | D12: Control de receta | E12: =Maestro_Ingredientes!$B$21 -> OK
A13: Merma real kg | B13: =IF(COUNT($F$50:$F$61)=0,"",SUM($F$50:$F$61))
A14: Rendimiento de materia prima % | B14: =IF(B10=0,"",B9/B10) -> 0.9119833
A15: Gasto total de materia prima € | B15: =IF(COUNT(Plan_Compras!$N$7:$N$114)=0,"",SUM(Plan_Compras!$N$7:$N$114))
A16: Cobertura de compra % | B16: =IF(B10=0,"",B11/B10) -> 1
A17: Mayor desviación de compra | B17: =IF(COUNT(Plan_Compras!$P$7:$P$114)=0,"",CHOOSE(MONTH(INDEX(Plan_Compras!$A$7:$A$114,MATCH(IF(MAX(Plan_Compras!$P$7:$P$114)>=-MIN(Plan_Compras!$P$7:$P$114),MAX(Plan_Compras!$P$7:$P$114),MIN(Plan_Compras!$P$7:$P$114)),Plan_Compras!$P$7:$P$114,0))),"Enero","Febrero","Marzo","Abril","Mayo","Junio","Julio","Agosto","Septiembre","Octubre","Noviembre","Diciembre")&" | "&INDEX(Plan_Compras!$C$7:$C$114,MATCH(IF(MAX(Plan_Compras!$P$7:$P$114)>=-MIN(Plan_Compras!$P$7:$P$114),MAX(Plan_Compras!$P$7:$P$114),MIN(Plan_Compras!$P$7:$P$114)),Plan_Compras!$P$7:$P$114,0))&" | "&TEXT(IF(MAX(Plan_Compras!$P$7:$P$114)>=-MIN(Plan_Compras!$P$7:$P$114),MAX(Plan_Compras!$P$7:$P$114),MIN(Plan_Compras!$P$7:$P$114)),"+#,##0;-#,##0;+0")&" kg") -> Enero | Tomate pera | +0 kg
A18: Ingrediente con mayor coste | B18: =IF(COUNT($D$67:$D$75)=0,"",INDEX($A$67:$A$75,MATCH(MAX($D$67:$D$75),$D$67:$D$75,0)))
A19: Coste de materia prima €/L | B19: =IF(OR(B8=0,B15=""),"",B15/B8)
A20: Coste total de producto €/L | B20: =IF(SUMPRODUCT(--ISNUMBER($O$50:$O$61),$B$50:$B$61)=0,"",SUMPRODUCT($O$50:$O$61,$B$50:$B$61)/SUMPRODUCT(--ISNUMBER($O$50:$O$61),$B$50:$B$61))
A21: Coste estimado de merma € | B21: =IF(COUNT($K$67:$K$75)=0,"",SUM($K$67:$K$75))
A22: Coste de merma % del gasto de materia prima | B22: =IF(OR(NOT(ISNUMBER(B21)),NOT(ISNUMBER(B15)),B15=0),"",B21/B15)
A23: Merma esperada acumulada (meses informados) | B23: =IF(COUNT($F$50:$F$61)=0,"",SUMIF($F$50:$F$61,">=0",$E$50:$E$61))
A24: Merma real acumulada | B24: =IF(COUNT($F$50:$F$61)=0,"",SUM($F$50:$F$61))
A25: Desviación de merma acumulada | B25: =IF(OR(B23="",B24=""),"",B24-B23)
A26: Meses con alertas de merma | B26: =COUNTIF($P$50:$P$61,"ALERTA*") -> 0
A27: Precisión de la estimación de merma | B27: =IF(OR(B23="",B23=0,B25=""),"",MAX(0,1-ABS(B25)/B23))
A30: KPI mensuales
A32: Métrica | B32: Ene | C32: Feb | D32: Mar | E32: Abr | F32: May | G32: Jun | H32: Jul | I32: Ago | J32: Sep | K32: Oct | L32: Nov | M32: Dic | N32: Acumulado
A33: Volumen de producto terminado L | B33: =IF($B$50="","",$B$50) -> 100000 | C33: =IF($B$51="","",$B$51) | D33: =IF($B$52="","",$B$52) | E33: =IF($B$53="","",$B$53) | F33: =IF($B$54="","",$B$54) | G33: =IF($B$55="","",$B$55) | H33: =IF($B$56="","",$B$56) | I33: =IF($B$57="","",$B$57) | J33: =IF($B$58="","",$B$58) | K33: =IF($B$59="","",$B$59) | L33: =IF($B$60="","",$B$60) | M33: =IF($B$61="","",$B$61) | N33: =B8 -> 100000
A34: Materia prima requerida kg | B34: =IF($C$50="","",$C$50) -> 109651.13 | C34: =IF($C$51="","",$C$51) | D34: =IF($C$52="","",$C$52) | E34: =IF($C$53="","",$C$53) | F34: =IF($C$54="","",$C$54) | G34: =IF($C$55="","",$C$55) | H34: =IF($C$56="","",$C$56) | I34: =IF($C$57="","",$C$57) | J34: =IF($C$58="","",$C$58) | K34: =IF($C$59="","",$C$59) | L34: =IF($C$60="","",$C$60) | M34: =IF($C$61="","",$C$61) | N34: =B10 -> 109651.13
A35: Materia prima comprada kg | B35: =IF($D$50="","",$D$50) -> 109651.13 | C35: =IF($D$51="","",$D$51) | D35: =IF($D$52="","",$D$52) | E35: =IF($D$53="","",$D$53) | F35: =IF($D$54="","",$D$54) | G35: =IF($D$55="","",$D$55) | H35: =IF($D$56="","",$D$56) | I35: =IF($D$57="","",$D$57) | J35: =IF($D$58="","",$D$58) | K35: =IF($D$59="","",$D$59) | L35: =IF($D$60="","",$D$60) | M35: =IF($D$61="","",$D$61) | N35: =B11 -> 109651.13
A36: Cobertura de compra % | B36: =IF(OR($C$50="",$C$50=0,$D$50=""),"",$D$50/$C$50) -> 1 | C36: =IF(OR($C$51="",$C$51=0,$D$51=""),"",$D$51/$C$51) | D36: =IF(OR($C$52="",$C$52=0,$D$52=""),"",$D$52/$C$52) | E36: =IF(OR($C$53="",$C$53=0,$D$53=""),"",$D$53/$C$53) | F36: =IF(OR($C$54="",$C$54=0,$D$54=""),"",$D$54/$C$54) | G36: =IF(OR($C$55="",$C$55=0,$D$55=""),"",$D$55/$C$55) | H36: =IF(OR($C$56="",$C$56=0,$D$56=""),"",$D$56/$C$56) | I36: =IF(OR($C$57="",$C$57=0,$D$57=""),"",$D$57/$C$57) | J36: =IF(OR($C$58="",$C$58=0,$D$58=""),"",$D$58/$C$58) | K36: =IF(OR($C$59="",$C$59=0,$D$59=""),"",$D$59/$C$59) | L36: =IF(OR($C$60="",$C$60=0,$D$60=""),"",$D$60/$C$60) | M36: =IF(OR($C$61="",$C$61=0,$D$61=""),"",$D$61/$C$61) | N36: =B16 -> 1
A37: Gasto de materia prima € | B37: =IF($J$50="","",$J$50) | C37: =IF($J$51="","",$J$51) | D37: =IF($J$52="","",$J$52) | E37: =IF($J$53="","",$J$53) | F37: =IF($J$54="","",$J$54) | G37: =IF($J$55="","",$J$55) | H37: =IF($J$56="","",$J$56) | I37: =IF($J$57="","",$J$57) | J37: =IF($J$58="","",$J$58) | K37: =IF($J$59="","",$J$59) | L37: =IF($J$60="","",$J$60) | M37: =IF($J$61="","",$J$61) | N37: =IF(B15="","",B15)
A38: Coste de materia prima €/L | B38: =IF($K$50="","",$K$50) | C38: =IF($K$51="","",$K$51) | D38: =IF($K$52="","",$K$52) | E38: =IF($K$53="","",$K$53) | F38: =IF($K$54="","",$K$54) | G38: =IF($K$55="","",$K$55) | H38: =IF($K$56="","",$K$56) | I38: =IF($K$57="","",$K$57) | J38: =IF($K$58="","",$K$58) | K38: =IF($K$59="","",$K$59) | L38: =IF($K$60="","",$K$60) | M38: =IF($K$61="","",$K$61) | N38: =IF(B19="","",B19)
A39: Coste total de producto €/L | B39: =IF($O$50="","",$O$50) | C39: =IF($O$51="","",$O$51) | D39: =IF($O$52="","",$O$52) | E39: =IF($O$53="","",$O$53) | F39: =IF($O$54="","",$O$54) | G39: =IF($O$55="","",$O$55) | H39: =IF($O$56="","",$O$56) | I39: =IF($O$57="","",$O$57) | J39: =IF($O$58="","",$O$58) | K39: =IF($O$59="","",$O$59) | L39: =IF($O$60="","",$O$60) | M39: =IF($O$61="","",$O$61) | N39: =IF(B20="","",B20)
A40: Merma esperada kg | B40: =IF($E$50="","",$E$50) -> 9651.1305 | C40: =IF($E$51="","",$E$51) | D40: =IF($E$52="","",$E$52) | E40: =IF($E$53="","",$E$53) | F40: =IF($E$54="","",$E$54) | G40: =IF($E$55="","",$E$55) | H40: =IF($E$56="","",$E$56) | I40: =IF($E$57="","",$E$57) | J40: =IF($E$58="","",$E$58) | K40: =IF($E$59="","",$E$59) | L40: =IF($E$60="","",$E$60) | M40: =IF($E$61="","",$E$61) | N40: =B12 -> 9651.1305
A41: Merma real kg | B41: =IF($F$50="","",$F$50) | C41: =IF($F$51="","",$F$51) | D41: =IF($F$52="","",$F$52) | E41: =IF($F$53="","",$F$53) | F41: =IF($F$54="","",$F$54) | G41: =IF($F$55="","",$F$55) | H41: =IF($F$56="","",$F$56) | I41: =IF($F$57="","",$F$57) | J41: =IF($F$58="","",$F$58) | K41: =IF($F$59="","",$F$59) | L41: =IF($F$60="","",$F$60) | M41: =IF($F$61="","",$F$61) | N41: =IF(B24="","",B24)
A42: Desviación de merma kg | B42: =IF($G$50="","",$G$50) | C42: =IF($G$51="","",$G$51) | D42: =IF($G$52="","",$G$52) | E42: =IF($G$53="","",$G$53) | F42: =IF($G$54="","",$G$54) | G42: =IF($G$55="","",$G$55) | H42: =IF($G$56="","",$G$56) | I42: =IF($G$57="","",$G$57) | J42: =IF($G$58="","",$G$58) | K42: =IF($G$59="","",$G$59) | L42: =IF($G$60="","",$G$60) | M42: =IF($G$61="","",$G$61) | N42: =IF(B25="","",B25)
A43: Desviación de merma % de la producción | B43: =IF($H$50="","",$H$50) | C43: =IF($H$51="","",$H$51) | D43: =IF($H$52="","",$H$52) | E43: =IF($H$53="","",$H$53) | F43: =IF($H$54="","",$H$54) | G43: =IF($H$55="","",$H$55) | H43: =IF($H$56="","",$H$56) | I43: =IF($H$57="","",$H$57) | J43: =IF($H$58="","",$H$58) | K43: =IF($H$59="","",$H$59) | L43: =IF($H$60="","",$H$60) | M43: =IF($H$61="","",$H$61) | N43: =IF(OR(B8=0,B25=""),"",B25/B8)
A44: Estado del control de merma | B44: =IF($P$50="","",$P$50) | C44: =IF($P$51="","",$P$51) | D44: =IF($P$52="","",$P$52) | E44: =IF($P$53="","",$P$53) | F44: =IF($P$54="","",$P$54) | G44: =IF($P$55="","",$P$55) | H44: =IF($P$56="","",$P$56) | I44: =IF($P$57="","",$P$57) | J44: =IF($P$58="","",$P$58) | K44: =IF($P$59="","",$P$59) | L44: =IF($P$60="","",$P$60) | M44: =IF($P$61="","",$P$61)
A47: Modelo mensual de costes y merma
A49: Mes | B49: Producción terminada L | C49: Materia prima requerida kg | D49: Materia prima comprada kg | E49: Merma esperada kg | F49: Merma real kg | G49: Desviación de merma kg | H49: Desviación de merma % de la producción | I49: Precisión de la estimación de merma | J49: Gasto de materia prima € | K49: Coste de materia prima €/L | L49: Coste variable de fabricación €/L | M49: Coste de envasado €/L | N49: Otros costes variables €/L | O49: Coste total de producto €/L | P49: Estado del control de merma
A50: Ene | B50: =IF(Plan_Produccion!$B$7="","",Plan_Produccion!$B$7) -> 100000 | C50: =IF(B50="","",Plan_Produccion!$D$7) -> 109651.13 | D50: =IF(B50="","",IF(COUNT(Plan_Compras!$M$7:$M$15)=0,"",SUM(Plan_Compras!$M$7:$M$15))) -> 109651.13 | E50: =IF(B50="","",Plan_Produccion!$E$7) -> 9651.1305 | G50: =IF(F50="","",F50-E50) | H50: =IF(OR(F50="",B50="",B50=0),"",G50/B50) | I50: =IF(OR(F50="",E50="",E50=0),"",MAX(0,1-ABS(G50)/E50)) | J50: =IF(B50="","",IF(COUNT(Plan_Compras!$N$7:$N$15)=0,"",SUM(Plan_Compras!$N$7:$N$15))) | K50: =IF(OR(J50="",B50="",B50=0),"",J50/B50) | O50: =IF(OR(K50="",L50="",M50="",N50=""),"",SUM(K50:N50)) | P50: =IF(OR(F50="",H50=""),"",IF(ABS(H50)<=Supuestos!$B$13,"OK",IF(H50>Supuestos!$B$13,"ALERTA – MERMA SUPERIOR A LA ESPERADA","ALERTA – MERMA INFERIOR A LA ESPERADA")))
A51: Feb | B51: =IF(Plan_Produccion!$B$8="","",Plan_Produccion!$B$8) | C51: =IF(B51="","",Plan_Produccion!$D$8) | D51: =IF(B51="","",IF(COUNT(Plan_Compras!$M$16:$M$24)=0,"",SUM(Plan_Compras!$M$16:$M$24))) | E51: =IF(B51="","",Plan_Produccion!$E$8) | G51: =IF(F51="","",F51-E51) | H51: =IF(OR(F51="",B51="",B51=0),"",G51/B51) | I51: =IF(OR(F51="",E51="",E51=0),"",MAX(0,1-ABS(G51)/E51)) | J51: =IF(B51="","",IF(COUNT(Plan_Compras!$N$16:$N$24)=0,"",SUM(Plan_Compras!$N$16:$N$24))) | K51: =IF(OR(J51="",B51="",B51=0),"",J51/B51) | O51: =IF(OR(K51="",L51="",M51="",N51=""),"",SUM(K51:N51)) | P51: =IF(OR(F51="",H51=""),"",IF(ABS(H51)<=Supuestos!$B$13,"OK",IF(H51>Supuestos!$B$13,"ALERTA – MERMA SUPERIOR A LA ESPERADA","ALERTA – MERMA INFERIOR A LA ESPERADA")))
A52: Mar | B52: =IF(Plan_Produccion!$B$9="","",Plan_Produccion!$B$9) | C52: =IF(B52="","",Plan_Produccion!$D$9) | D52: =IF(B52="","",IF(COUNT(Plan_Compras!$M$25:$M$33)=0,"",SUM(Plan_Compras!$M$25:$M$33))) | E52: =IF(B52="","",Plan_Produccion!$E$9) | G52: =IF(F52="","",F52-E52) | H52: =IF(OR(F52="",B52="",B52=0),"",G52/B52) | I52: =IF(OR(F52="",E52="",E52=0),"",MAX(0,1-ABS(G52)/E52)) | J52: =IF(B52="","",IF(COUNT(Plan_Compras!$N$25:$N$33)=0,"",SUM(Plan_Compras!$N$25:$N$33))) | K52: =IF(OR(J52="",B52="",B52=0),"",J52/B52) | O52: =IF(OR(K52="",L52="",M52="",N52=""),"",SUM(K52:N52)) | P52: =IF(OR(F52="",H52=""),"",IF(ABS(H52)<=Supuestos!$B$13,"OK",IF(H52>Supuestos!$B$13,"ALERTA – MERMA SUPERIOR A LA ESPERADA","ALERTA – MERMA INFERIOR A LA ESPERADA")))
A53: Abr | B53: =IF(Plan_Produccion!$B$10="","",Plan_Produccion!$B$10) | C53: =IF(B53="","",Plan_Produccion!$D$10) | D53: =IF(B53="","",IF(COUNT(Plan_Compras!$M$34:$M$42)=0,"",SUM(Plan_Compras!$M$34:$M$42))) | E53: =IF(B53="","",Plan_Produccion!$E$10) | G53: =IF(F53="","",F53-E53) | H53: =IF(OR(F53="",B53="",B53=0),"",G53/B53) | I53: =IF(OR(F53="",E53="",E53=0),"",MAX(0,1-ABS(G53)/E53)) | J53: =IF(B53="","",IF(COUNT(Plan_Compras!$N$34:$N$42)=0,"",SUM(Plan_Compras!$N$34:$N$42))) | K53: =IF(OR(J53="",B53="",B53=0),"",J53/B53) | O53: =IF(OR(K53="",L53="",M53="",N53=""),"",SUM(K53:N53)) | P53: =IF(OR(F53="",H53=""),"",IF(ABS(H53)<=Supuestos!$B$13,"OK",IF(H53>Supuestos!$B$13,"ALERTA – MERMA SUPERIOR A LA ESPERADA","ALERTA – MERMA INFERIOR A LA ESPERADA")))
A54: May | B54: =IF(Plan_Produccion!$B$11="","",Plan_Produccion!$B$11) | C54: =IF(B54="","",Plan_Produccion!$D$11) | D54: =IF(B54="","",IF(COUNT(Plan_Compras!$M$43:$M$51)=0,"",SUM(Plan_Compras!$M$43:$M$51))) | E54: =IF(B54="","",Plan_Produccion!$E$11) | G54: =IF(F54="","",F54-E54) | H54: =IF(OR(F54="",B54="",B54=0),"",G54/B54) | I54: =IF(OR(F54="",E54="",E54=0),"",MAX(0,1-ABS(G54)/E54)) | J54: =IF(B54="","",IF(COUNT(Plan_Compras!$N$43:$N$51)=0,"",SUM(Plan_Compras!$N$43:$N$51))) | K54: =IF(OR(J54="",B54="",B54=0),"",J54/B54) | O54: =IF(OR(K54="",L54="",M54="",N54=""),"",SUM(K54:N54)) | P54: =IF(OR(F54="",H54=""),"",IF(ABS(H54)<=Supuestos!$B$13,"OK",IF(H54>Supuestos!$B$13,"ALERTA – MERMA SUPERIOR A LA ESPERADA","ALERTA – MERMA INFERIOR A LA ESPERADA")))
A55: Jun | B55: =IF(Plan_Produccion!$B$12="","",Plan_Produccion!$B$12) | C55: =IF(B55="","",Plan_Produccion!$D$12) | D55: =IF(B55="","",IF(COUNT(Plan_Compras!$M$52:$M$60)=0,"",SUM(Plan_Compras!$M$52:$M$60))) | E55: =IF(B55="","",Plan_Produccion!$E$12) | G55: =IF(F55="","",F55-E55) | H55: =IF(OR(F55="",B55="",B55=0),"",G55/B55) | I55: =IF(OR(F55="",E55="",E55=0),"",MAX(0,1-ABS(G55)/E55)) | J55: =IF(B55="","",IF(COUNT(Plan_Compras!$N$52:$N$60)=0,"",SUM(Plan_Compras!$N$52:$N$60))) | K55: =IF(OR(J55="",B55="",B55=0),"",J55/B55) | O55: =IF(OR(K55="",L55="",M55="",N55=""),"",SUM(K55:N55)) | P55: =IF(OR(F55="",H55=""),"",IF(ABS(H55)<=Supuestos!$B$13,"OK",IF(H55>Supuestos!$B$13,"ALERTA – MERMA SUPERIOR A LA ESPERADA","ALERTA – MERMA INFERIOR A LA ESPERADA")))
A56: Jul | B56: =IF(Plan_Produccion!$B$13="","",Plan_Produccion!$B$13) | C56: =IF(B56="","",Plan_Produccion!$D$13) | D56: =IF(B56="","",IF(COUNT(Plan_Compras!$M$61:$M$69)=0,"",SUM(Plan_Compras!$M$61:$M$69))) | E56: =IF(B56="","",Plan_Produccion!$E$13) | G56: =IF(F56="","",F56-E56) | H56: =IF(OR(F56="",B56="",B56=0),"",G56/B56) | I56: =IF(OR(F56="",E56="",E56=0),"",MAX(0,1-ABS(G56)/E56)) | J56: =IF(B56="","",IF(COUNT(Plan_Compras!$N$61:$N$69)=0,"",SUM(Plan_Compras!$N$61:$N$69))) | K56: =IF(OR(J56="",B56="",B56=0),"",J56/B56) | O56: =IF(OR(K56="",L56="",M56="",N56=""),"",SUM(K56:N56)) | P56: =IF(OR(F56="",H56=""),"",IF(ABS(H56)<=Supuestos!$B$13,"OK",IF(H56>Supuestos!$B$13,"ALERTA – MERMA SUPERIOR A LA ESPERADA","ALERTA – MERMA INFERIOR A LA ESPERADA")))
A57: Ago | B57: =IF(Plan_Produccion!$B$14="","",Plan_Produccion!$B$14) | C57: =IF(B57="","",Plan_Produccion!$D$14) | D57: =IF(B57="","",IF(COUNT(Plan_Compras!$M$70:$M$78)=0,"",SUM(Plan_Compras!$M$70:$M$78))) | E57: =IF(B57="","",Plan_Produccion!$E$14) | G57: =IF(F57="","",F57-E57) | H57: =IF(OR(F57="",B57="",B57=0),"",G57/B57) | I57: =IF(OR(F57="",E57="",E57=0),"",MAX(0,1-ABS(G57)/E57)) | J57: =IF(B57="","",IF(COUNT(Plan_Compras!$N$70:$N$78)=0,"",SUM(Plan_Compras!$N$70:$N$78))) | K57: =IF(OR(J57="",B57="",B57=0),"",J57/B57) | O57: =IF(OR(K57="",L57="",M57="",N57=""),"",SUM(K57:N57)) | P57: =IF(OR(F57="",H57=""),"",IF(ABS(H57)<=Supuestos!$B$13,"OK",IF(H57>Supuestos!$B$13,"ALERTA – MERMA SUPERIOR A LA ESPERADA","ALERTA – MERMA INFERIOR A LA ESPERADA")))
A58: Sep | B58: =IF(Plan_Produccion!$B$15="","",Plan_Produccion!$B$15) | C58: =IF(B58="","",Plan_Produccion!$D$15) | D58: =IF(B58="","",IF(COUNT(Plan_Compras!$M$79:$M$87)=0,"",SUM(Plan_Compras!$M$79:$M$87))) | E58: =IF(B58="","",Plan_Produccion!$E$15) | G58: =IF(F58="","",F58-E58) | H58: =IF(OR(F58="",B58="",B58=0),"",G58/B58) | I58: =IF(OR(F58="",E58="",E58=0),"",MAX(0,1-ABS(G58)/E58)) | J58: =IF(B58="","",IF(COUNT(Plan_Compras!$N$79:$N$87)=0,"",SUM(Plan_Compras!$N$79:$N$87))) | K58: =IF(OR(J58="",B58="",B58=0),"",J58/B58) | O58: =IF(OR(K58="",L58="",M58="",N58=""),"",SUM(K58:N58)) | P58: =IF(OR(F58="",H58=""),"",IF(ABS(H58)<=Supuestos!$B$13,"OK",IF(H58>Supuestos!$B$13,"ALERTA – MERMA SUPERIOR A LA ESPERADA","ALERTA – MERMA INFERIOR A LA ESPERADA")))
A59: Oct | B59: =IF(Plan_Produccion!$B$16="","",Plan_Produccion!$B$16) | C59: =IF(B59="","",Plan_Produccion!$D$16) | D59: =IF(B59="","",IF(COUNT(Plan_Compras!$M$88:$M$96)=0,"",SUM(Plan_Compras!$M$88:$M$96))) | E59: =IF(B59="","",Plan_Produccion!$E$16) | G59: =IF(F59="","",F59-E59) | H59: =IF(OR(F59="",B59="",B59=0),"",G59/B59) | I59: =IF(OR(F59="",E59="",E59=0),"",MAX(0,1-ABS(G59)/E59)) | J59: =IF(B59="","",IF(COUNT(Plan_Compras!$N$88:$N$96)=0,"",SUM(Plan_Compras!$N$88:$N$96))) | K59: =IF(OR(J59="",B59="",B59=0),"",J59/B59) | O59: =IF(OR(K59="",L59="",M59="",N59=""),"",SUM(K59:N59)) | P59: =IF(OR(F59="",H59=""),"",IF(ABS(H59)<=Supuestos!$B$13,"OK",IF(H59>Supuestos!$B$13,"ALERTA – MERMA SUPERIOR A LA ESPERADA","ALERTA – MERMA INFERIOR A LA ESPERADA")))
A60: Nov | B60: =IF(Plan_Produccion!$B$17="","",Plan_Produccion!$B$17) | C60: =IF(B60="","",Plan_Produccion!$D$17) | D60: =IF(B60="","",IF(COUNT(Plan_Compras!$M$97:$M$105)=0,"",SUM(Plan_Compras!$M$97:$M$105))) | E60: =IF(B60="","",Plan_Produccion!$E$17) | G60: =IF(F60="","",F60-E60) | H60: =IF(OR(F60="",B60="",B60=0),"",G60/B60) | I60: =IF(OR(F60="",E60="",E60=0),"",MAX(0,1-ABS(G60)/E60)) | J60: =IF(B60="","",IF(COUNT(Plan_Compras!$N$97:$N$105)=0,"",SUM(Plan_Compras!$N$97:$N$105))) | K60: =IF(OR(J60="",B60="",B60=0),"",J60/B60) | O60: =IF(OR(K60="",L60="",M60="",N60=""),"",SUM(K60:N60)) | P60: =IF(OR(F60="",H60=""),"",IF(ABS(H60)<=Supuestos!$B$13,"OK",IF(H60>Supuestos!$B$13,"ALERTA – MERMA SUPERIOR A LA ESPERADA","ALERTA – MERMA INFERIOR A LA ESPERADA")))
A61: Dic | B61: =IF(Plan_Produccion!$B$18="","",Plan_Produccion!$B$18) | C61: =IF(B61="","",Plan_Produccion!$D$18) | D61: =IF(B61="","",IF(COUNT(Plan_Compras!$M$106:$M$114)=0,"",SUM(Plan_Compras!$M$106:$M$114))) | E61: =IF(B61="","",Plan_Produccion!$E$18) | G61: =IF(F61="","",F61-E61) | H61: =IF(OR(F61="",B61="",B61=0),"",G61/B61) | I61: =IF(OR(F61="",E61="",E61=0),"",MAX(0,1-ABS(G61)/E61)) | J61: =IF(B61="","",IF(COUNT(Plan_Compras!$N$106:$N$114)=0,"",SUM(Plan_Compras!$N$106:$N$114))) | K61: =IF(OR(J61="",B61="",B61=0),"",J61/B61) | O61: =IF(OR(K61="",L61="",M61="",N61=""),"",SUM(K61:N61)) | P61: =IF(OR(F61="",H61=""),"",IF(ABS(H61)<=Supuestos!$B$13,"OK",IF(H61>Supuestos!$B$13,"ALERTA – MERMA SUPERIOR A LA ESPERADA","ALERTA – MERMA INFERIOR A LA ESPERADA")))
A64: Análisis de costes por ingrediente
A66: Ingrediente | B66: Cantidad requerida kg | C66: Cantidad comprada kg | D66: Gasto total € | E66: Precio medio ponderado €/kg | F66: Precio mínimo €/kg | G66: Precio máximo €/kg | H66: Diferencial de precios €/kg | I66: Contribución al coste % | J66: Merma esperada kg | K66: Coste estimado de merma €
A67: =Maestro_Ingredientes!$B$7 -> Tomate pera | B67: =IF(COUNT(Plan_Compras!$F$7,Plan_Compras!$F$16,Plan_Compras!$F$25,Plan_Compras!$F$34,Plan_Compras!$F$43,Plan_Compras!$F$52,Plan_Compras!$F$61,Plan_Compras!$F$70,Plan_Compras!$F$79,Plan_Compras!$F$88,Plan_Compras!$F$97,Plan_Compras!$F$106)=0,"",SUM(Plan_Compras!$F$7,Plan_Compras!$F$16,Plan_Compras!$F$25,Plan_Compras!$F$34,Plan_Compras!$F$43,Plan_Compras!$F$52,Plan_Compras!$F$61,Plan_Compras!$F$70,Plan_Compras!$F$79,Plan_Compras!$F$88,Plan_Compras!$F$97,Plan_Compras!$F$106)) -> 76413.043 | C67: =IF(COUNT(Plan_Compras!$M$7,Plan_Compras!$M$16,Plan_Compras!$M$25,Plan_Compras!$M$34,Plan_Compras!$M$43,Plan_Compras!$M$52,Plan_Compras!$M$61,Plan_Compras!$M$70,Plan_Compras!$M$79,Plan_Compras!$M$88,Plan_Compras!$M$97,Plan_Compras!$M$106)=0,"",SUM(Plan_Compras!$M$7,Plan_Compras!$M$16,Plan_Compras!$M$25,Plan_Compras!$M$34,Plan_Compras!$M$43,Plan_Compras!$M$52,Plan_Compras!$M$61,Plan_Compras!$M$70,Plan_Compras!$M$79,Plan_Compras!$M$88,Plan_Compras!$M$97,Plan_Compras!$M$106)) -> 76413.043 | D67: =IF(COUNT(Plan_Compras!$N$7,Plan_Compras!$N$16,Plan_Compras!$N$25,Plan_Compras!$N$34,Plan_Compras!$N$43,Plan_Compras!$N$52,Plan_Compras!$N$61,Plan_Compras!$N$70,Plan_Compras!$N$79,Plan_Compras!$N$88,Plan_Compras!$N$97,Plan_Compras!$N$106)=0,"",SUM(Plan_Compras!$N$7,Plan_Compras!$N$16,Plan_Compras!$N$25,Plan_Compras!$N$34,Plan_Compras!$N$43,Plan_Compras!$N$52,Plan_Compras!$N$61,Plan_Compras!$N$70,Plan_Compras!$N$79,Plan_Compras!$N$88,Plan_Compras!$N$97,Plan_Compras!$N$106)) | E67: =IF(OR(C67="",C67=0,OR(AND(Plan_Compras!$G$7>0,Plan_Compras!$H$7=""),AND(Plan_Compras!$J$7>0,Plan_Compras!$K$7=""),AND(Plan_Compras!$G$16>0,Plan_Compras!$H$16=""),AND(Plan_Compras!$J$16>0,Plan_Compras!$K$16=""),AND(Plan_Compras!$G$25>0,Plan_Compras!$H$25=""),AND(Plan_Compras!$J$25>0,Plan_Compras!$K$25=""),AND(Plan_Compras!$G$34>0,Plan_Compras!$H$34=""),AND(Plan_Compras!$J$34>0,Plan_Compras!$K$34=""),AND(Plan_Compras!$G$43>0,Plan_Compras!$H$43=""),AND(Plan_Compras!$J$43>0,Plan_Compras!$K$43=""),AND(Plan_Compras!$G$52>0,Plan_Compras!$H$52=""),AND(Plan_Compras!$J$52>0,Plan_Compras!$K$52=""),AND(Plan_Compras!$G$61>0,Plan_Compras!$H$61=""),AND(Plan_Compras!$J$61>0,Plan_Compras!$K$61=""),AND(Plan_Compras!$G$70>0,Plan_Compras!$H$70=""),AND(Plan_Compras!$J$70>0,Plan_Compras!$K$70=""),AND(Plan_Compras!$G$79>0,Plan_Compras!$H$79=""),AND(Plan_Compras!$J$79>0,Plan_Compras!$K$79=""),AND(Plan_Compras!$G$88>0,Plan_Compras!$H$88=""),AND(Plan_Compras!$J$88>0,Plan_Compras!$K$88=""),AND(Plan_Compras!$G$97>0,Plan_Compras!$H$97=""),AND(Plan_Compras!$J$97>0,Plan_Compras!$K$97=""),AND(Plan_Compras!$G$106>0,Plan_Compras!$H$106=""),AND(Plan_Compras!$J$106>0,Plan_Compras!$K$106=""))),"",D67/C67) | F67: =IF(OR(E67="",OR(AND(Plan_Compras!$G$7>0,Plan_Compras!$H$7=""),AND(Plan_Compras!$J$7>0,Plan_Compras!$K$7=""),AND(Plan_Compras!$G$16>0,Plan_Compras!$H$16=""),AND(Plan_Compras!$J$16>0,Plan_Compras!$K$16=""),AND(Plan_Compras!$G$25>0,Plan_Compras!$H$25=""),AND(Plan_Compras!$J$25>0,Plan_Compras!$K$25=""),AND(Plan_Compras!$G$34>0,Plan_Compras!$H$34=""),AND(Plan_Compras!$J$34>0,Plan_Compras!$K$34=""),AND(Plan_Compras!$G$43>0,Plan_Compras!$H$43=""),AND(Plan_Compras!$J$43>0,Plan_Compras!$K$43=""),AND(Plan_Compras!$G$52>0,Plan_Compras!$H$52=""),AND(Plan_Compras!$J$52>0,Plan_Compras!$K$52=""),AND(Plan_Compras!$G$61>0,Plan_Compras!$H$61=""),AND(Plan_Compras!$J$61>0,Plan_Compras!$K$61=""),AND(Plan_Compras!$G$70>0,Plan_Compras!$H$70=""),AND(Plan_Compras!$J$70>0,Plan_Compras!$K$70=""),AND(Plan_Compras!$G$79>0,Plan_Compras!$H$79=""),AND(Plan_Compras!$J$79>0,Plan_Compras!$K$79=""),AND(Plan_Compras!$G$88>0,Plan_Compras!$H$88=""),AND(Plan_Compras!$J$88>0,Plan_Compras!$K$88=""),AND(Plan_Compras!$G$97>0,Plan_Compras!$H$97=""),AND(Plan_Compras!$J$97>0,Plan_Compras!$K$97=""),AND(Plan_Compras!$G$106>0,Plan_Compras!$H$106=""),AND(Plan_Compras!$J$106>0,Plan_Compras!$K$106=""))),"",MIN(IF(Plan_Compras!$G$7>0,Plan_Compras!$H$7,1E+99),IF(Plan_Compras!$J$7>0,Plan_Compras!$K$7,1E+99),IF(Plan_Compras!$G$16>0,Plan_Compras!$H$16,1E+99),IF(Plan_Compras!$J$16>0,Plan_Compras!$K$16,1E+99),IF(Plan_Compras!$G$25>0,Plan_Compras!$H$25,1E+99),IF(Plan_Compras!$J$25>0,Plan_Compras!$K$25,1E+99),IF(Plan_Compras!$G$34>0,Plan_Compras!$H$34,1E+99),IF(Plan_Compras!$J$34>0,Plan_Compras!$K$34,1E+99),IF(Plan_Compras!$G$43>0,Plan_Compras!$H$43,1E+99),IF(Plan_Compras!$J$43>0,Plan_Compras!$K$43,1E+99),IF(Plan_Compras!$G$52>0,Plan_Compras!$H$52,1E+99),IF(Plan_Compras!$J$52>0,Plan_Compras!$K$52,1E+99),IF(Plan_Compras!$G$61>0,Plan_Compras!$H$61,1E+99),IF(Plan_Compras!$J$61>0,Plan_Compras!$K$61,1E+99),IF(Plan_Compras!$G$70>0,Plan_Compras!$H$70,1E+99),IF(Plan_Compras!$J$70>0,Plan_Compras!$K$70,1E+99),IF(Plan_Compras!$G$79>0,Plan_Compras!$H$79,1E+99),IF(Plan_Compras!$J$79>0,Plan_Compras!$K$79,1E+99),IF(Plan_Compras!$G$88>0,Plan_Compras!$H$88,1E+99),IF(Plan_Compras!$J$88>0,Plan_Compras!$K$88,1E+99),IF(Plan_Compras!$G$97>0,Plan_Compras!$H$97,1E+99),IF(Plan_Compras!$J$97>0,Plan_Compras!$K$97,1E+99),IF(Plan_Compras!$G$106>0,Plan_Compras!$H$106,1E+99),IF(Plan_Compras!$J$106>0,Plan_Compras!$K$106,1E+99))) | G67: =IF(OR(E67="",OR(AND(Plan_Compras!$G$7>0,Plan_Compras!$H$7=""),AND(Plan_Compras!$J$7>0,Plan_Compras!$K$7=""),AND(Plan_Compras!$G$16>0,Plan_Compras!$H$16=""),AND(Plan_Compras!$J$16>0,Plan_Compras!$K$16=""),AND(Plan_Compras!$G$25>0,Plan_Compras!$H$25=""),AND(Plan_Compras!$J$25>0,Plan_Compras!$K$25=""),AND(Plan_Compras!$G$34>0,Plan_Compras!$H$34=""),AND(Plan_Compras!$J$34>0,Plan_Compras!$K$34=""),AND(Plan_Compras!$G$43>0,Plan_Compras!$H$43=""),AND(Plan_Compras!$J$43>0,Plan_Compras!$K$43=""),AND(Plan_Compras!$G$52>0,Plan_Compras!$H$52=""),AND(Plan_Compras!$J$52>0,Plan_Compras!$K$52=""),AND(Plan_Compras!$G$61>0,Plan_Compras!$H$61=""),AND(Plan_Compras!$J$61>0,Plan_Compras!$K$61=""),AND(Plan_Compras!$G$70>0,Plan_Compras!$H$70=""),AND(Plan_Compras!$J$70>0,Plan_Compras!$K$70=""),AND(Plan_Compras!$G$79>0,Plan_Compras!$H$79=""),AND(Plan_Compras!$J$79>0,Plan_Compras!$K$79=""),AND(Plan_Compras!$G$88>0,Plan_Compras!$H$88=""),AND(Plan_Compras!$J$88>0,Plan_Compras!$K$88=""),AND(Plan_Compras!$G$97>0,Plan_Compras!$H$97=""),AND(Plan_Compras!$J$97>0,Plan_Compras!$K$97=""),AND(Plan_Compras!$G$106>0,Plan_Compras!$H$106=""),AND(Plan_Compras!$J$106>0,Plan_Compras!$K$106=""))),"",MAX(IF(Plan_Compras!$G$7>0,Plan_Compras!$H$7,-1E+99),IF(Plan_Compras!$J$7>0,Plan_Compras!$K$7,-1E+99),IF(Plan_Compras!$G$16>0,Plan_Compras!$H$16,-1E+99),IF(Plan_Compras!$J$16>0,Plan_Compras!$K$16,-1E+99),IF(Plan_Compras!$G$25>0,Plan_Compras!$H$25,-1E+99),IF(Plan_Compras!$J$25>0,Plan_Compras!$K$25,-1E+99),IF(Plan_Compras!$G$34>0,Plan_Compras!$H$34,-1E+99),IF(Plan_Compras!$J$34>0,Plan_Compras!$K$34,-1E+99),IF(Plan_Compras!$G$43>0,Plan_Compras!$H$43,-1E+99),IF(Plan_Compras!$J$43>0,Plan_Compras!$K$43,-1E+99),IF(Plan_Compras!$G$52>0,Plan_Compras!$H$52,-1E+99),IF(Plan_Compras!$J$52>0,Plan_Compras!$K$52,-1E+99),IF(Plan_Compras!$G$61>0,Plan_Compras!$H$61,-1E+99),IF(Plan_Compras!$J$61>0,Plan_Compras!$K$61,-1E+99),IF(Plan_Compras!$G$70>0,Plan_Compras!$H$70,-1E+99),IF(Plan_Compras!$J$70>0,Plan_Compras!$K$70,-1E+99),IF(Plan_Compras!$G$79>0,Plan_Compras!$H$79,-1E+99),IF(Plan_Compras!$J$79>0,Plan_Compras!$K$79,-1E+99),IF(Plan_Compras!$G$88>0,Plan_Compras!$H$88,-1E+99),IF(Plan_Compras!$J$88>0,Plan_Compras!$K$88,-1E+99),IF(Plan_Compras!$G$97>0,Plan_Compras!$H$97,-1E+99),IF(Plan_Compras!$J$97>0,Plan_Compras!$K$97,-1E+99),IF(Plan_Compras!$G$106>0,Plan_Compras!$H$106,-1E+99),IF(Plan_Compras!$J$106>0,Plan_Compras!$K$106,-1E+99))) | H67: =IF(OR(F67="",G67=""),"",G67-F67) | I67: =IF(OR(D67="",SUM($D$67:$D$75)=0),"",D67/SUM($D$67:$D$75)) | J67: =IF(COUNT(Plan_Compras!$F$7,Plan_Compras!$F$16,Plan_Compras!$F$25,Plan_Compras!$F$34,Plan_Compras!$F$43,Plan_Compras!$F$52,Plan_Compras!$F$61,Plan_Compras!$F$70,Plan_Compras!$F$79,Plan_Compras!$F$88,Plan_Compras!$F$97,Plan_Compras!$F$106)=0,"",SUM(Plan_Compras!$F$7,Plan_Compras!$F$16,Plan_Compras!$F$25,Plan_Compras!$F$34,Plan_Compras!$F$43,Plan_Compras!$F$52,Plan_Compras!$F$61,Plan_Compras!$F$70,Plan_Compras!$F$79,Plan_Compras!$F$88,Plan_Compras!$F$97,Plan_Compras!$F$106)-SUM(Plan_Compras!$E$7,Plan_Compras!$E$16,Plan_Compras!$E$25,Plan_Compras!$E$34,Plan_Compras!$E$43,Plan_Compras!$E$52,Plan_Compras!$E$61,Plan_Compras!$E$70,Plan_Compras!$E$79,Plan_Compras!$E$88,Plan_Compras!$E$97,Plan_Compras!$E$106)) -> 6113.0435 | K67: =IF(AND(ISNUMBER(E67),ISNUMBER(J67)),J67*E67,"")
A68: =Maestro_Ingredientes!$B$8 -> Pepino | B68: =IF(COUNT(Plan_Compras!$F$8,Plan_Compras!$F$17,Plan_Compras!$F$26,Plan_Compras!$F$35,Plan_Compras!$F$44,Plan_Compras!$F$53,Plan_Compras!$F$62,Plan_Compras!$F$71,Plan_Compras!$F$80,Plan_Compras!$F$89,Plan_Compras!$F$98,Plan_Compras!$F$107)=0,"",SUM(Plan_Compras!$F$8,Plan_Compras!$F$17,Plan_Compras!$F$26,Plan_Compras!$F$35,Plan_Compras!$F$44,Plan_Compras!$F$53,Plan_Compras!$F$62,Plan_Compras!$F$71,Plan_Compras!$F$80,Plan_Compras!$F$89,Plan_Compras!$F$98,Plan_Compras!$F$107)) -> 13863.636 | C68: =IF(COUNT(Plan_Compras!$M$8,Plan_Compras!$M$17,Plan_Compras!$M$26,Plan_Compras!$M$35,Plan_Compras!$M$44,Plan_Compras!$M$53,Plan_Compras!$M$62,Plan_Compras!$M$71,Plan_Compras!$M$80,Plan_Compras!$M$89,Plan_Compras!$M$98,Plan_Compras!$M$107)=0,"",SUM(Plan_Compras!$M$8,Plan_Compras!$M$17,Plan_Compras!$M$26,Plan_Compras!$M$35,Plan_Compras!$M$44,Plan_Compras!$M$53,Plan_Compras!$M$62,Plan_Compras!$M$71,Plan_Compras!$M$80,Plan_Compras!$M$89,Plan_Compras!$M$98,Plan_Compras!$M$107)) -> 13863.636 | D68: =IF(COUNT(Plan_Compras!$N$8,Plan_Compras!$N$17,Plan_Compras!$N$26,Plan_Compras!$N$35,Plan_Compras!$N$44,Plan_Compras!$N$53,Plan_Compras!$N$62,Plan_Compras!$N$71,Plan_Compras!$N$80,Plan_Compras!$N$89,Plan_Compras!$N$98,Plan_Compras!$N$107)=0,"",SUM(Plan_Compras!$N$8,Plan_Compras!$N$17,Plan_Compras!$N$26,Plan_Compras!$N$35,Plan_Compras!$N$44,Plan_Compras!$N$53,Plan_Compras!$N$62,Plan_Compras!$N$71,Plan_Compras!$N$80,Plan_Compras!$N$89,Plan_Compras!$N$98,Plan_Compras!$N$107)) | E68: =IF(OR(C68="",C68=0,OR(AND(Plan_Compras!$G$8>0,Plan_Compras!$H$8=""),AND(Plan_Compras!$J$8>0,Plan_Compras!$K$8=""),AND(Plan_Compras!$G$17>0,Plan_Compras!$H$17=""),AND(Plan_Compras!$J$17>0,Plan_Compras!$K$17=""),AND(Plan_Compras!$G$26>0,Plan_Compras!$H$26=""),AND(Plan_Compras!$J$26>0,Plan_Compras!$K$26=""),AND(Plan_Compras!$G$35>0,Plan_Compras!$H$35=""),AND(Plan_Compras!$J$35>0,Plan_Compras!$K$35=""),AND(Plan_Compras!$G$44>0,Plan_Compras!$H$44=""),AND(Plan_Compras!$J$44>0,Plan_Compras!$K$44=""),AND(Plan_Compras!$G$53>0,Plan_Compras!$H$53=""),AND(Plan_Compras!$J$53>0,Plan_Compras!$K$53=""),AND(Plan_Compras!$G$62>0,Plan_Compras!$H$62=""),AND(Plan_Compras!$J$62>0,Plan_Compras!$K$62=""),AND(Plan_Compras!$G$71>0,Plan_Compras!$H$71=""),AND(Plan_Compras!$J$71>0,Plan_Compras!$K$71=""),AND(Plan_Compras!$G$80>0,Plan_Compras!$H$80=""),AND(Plan_Compras!$J$80>0,Plan_Compras!$K$80=""),AND(Plan_Compras!$G$89>0,Plan_Compras!$H$89=""),AND(Plan_Compras!$J$89>0,Plan_Compras!$K$89=""),AND(Plan_Compras!$G$98>0,Plan_Compras!$H$98=""),AND(Plan_Compras!$J$98>0,Plan_Compras!$K$98=""),AND(Plan_Compras!$G$107>0,Plan_Compras!$H$107=""),AND(Plan_Compras!$J$107>0,Plan_Compras!$K$107=""))),"",D68/C68) | F68: =IF(OR(E68="",OR(AND(Plan_Compras!$G$8>0,Plan_Compras!$H$8=""),AND(Plan_Compras!$J$8>0,Plan_Compras!$K$8=""),AND(Plan_Compras!$G$17>0,Plan_Compras!$H$17=""),AND(Plan_Compras!$J$17>0,Plan_Compras!$K$17=""),AND(Plan_Compras!$G$26>0,Plan_Compras!$H$26=""),AND(Plan_Compras!$J$26>0,Plan_Compras!$K$26=""),AND(Plan_Compras!$G$35>0,Plan_Compras!$H$35=""),AND(Plan_Compras!$J$35>0,Plan_Compras!$K$35=""),AND(Plan_Compras!$G$44>0,Plan_Compras!$H$44=""),AND(Plan_Compras!$J$44>0,Plan_Compras!$K$44=""),AND(Plan_Compras!$G$53>0,Plan_Compras!$H$53=""),AND(Plan_Compras!$J$53>0,Plan_Compras!$K$53=""),AND(Plan_Compras!$G$62>0,Plan_Compras!$H$62=""),AND(Plan_Compras!$J$62>0,Plan_Compras!$K$62=""),AND(Plan_Compras!$G$71>0,Plan_Compras!$H$71=""),AND(Plan_Compras!$J$71>0,Plan_Compras!$K$71=""),AND(Plan_Compras!$G$80>0,Plan_Compras!$H$80=""),AND(Plan_Compras!$J$80>0,Plan_Compras!$K$80=""),AND(Plan_Compras!$G$89>0,Plan_Compras!$H$89=""),AND(Plan_Compras!$J$89>0,Plan_Compras!$K$89=""),AND(Plan_Compras!$G$98>0,Plan_Compras!$H$98=""),AND(Plan_Compras!$J$98>0,Plan_Compras!$K$98=""),AND(Plan_Compras!$G$107>0,Plan_Compras!$H$107=""),AND(Plan_Compras!$J$107>0,Plan_Compras!$K$107=""))),"",MIN(IF(Plan_Compras!$G$8>0,Plan_Compras!$H$8,1E+99),IF(Plan_Compras!$J$8>0,Plan_Compras!$K$8,1E+99),IF(Plan_Compras!$G$17>0,Plan_Compras!$H$17,1E+99),IF(Plan_Compras!$J$17>0,Plan_Compras!$K$17,1E+99),IF(Plan_Compras!$G$26>0,Plan_Compras!$H$26,1E+99),IF(Plan_Compras!$J$26>0,Plan_Compras!$K$26,1E+99),IF(Plan_Compras!$G$35>0,Plan_Compras!$H$35,1E+99),IF(Plan_Compras!$J$35>0,Plan_Compras!$K$35,1E+99),IF(Plan_Compras!$G$44>0,Plan_Compras!$H$44,1E+99),IF(Plan_Compras!$J$44>0,Plan_Compras!$K$44,1E+99),IF(Plan_Compras!$G$53>0,Plan_Compras!$H$53,1E+99),IF(Plan_Compras!$J$53>0,Plan_Compras!$K$53,1E+99),IF(Plan_Compras!$G$62>0,Plan_Compras!$H$62,1E+99),IF(Plan_Compras!$J$62>0,Plan_Compras!$K$62,1E+99),IF(Plan_Compras!$G$71>0,Plan_Compras!$H$71,1E+99),IF(Plan_Compras!$J$71>0,Plan_Compras!$K$71,1E+99),IF(Plan_Compras!$G$80>0,Plan_Compras!$H$80,1E+99),IF(Plan_Compras!$J$80>0,Plan_Compras!$K$80,1E+99),IF(Plan_Compras!$G$89>0,Plan_Compras!$H$89,1E+99),IF(Plan_Compras!$J$89>0,Plan_Compras!$K$89,1E+99),IF(Plan_Compras!$G$98>0,Plan_Compras!$H$98,1E+99),IF(Plan_Compras!$J$98>0,Plan_Compras!$K$98,1E+99),IF(Plan_Compras!$G$107>0,Plan_Compras!$H$107,1E+99),IF(Plan_Compras!$J$107>0,Plan_Compras!$K$107,1E+99))) | G68: =IF(OR(E68="",OR(AND(Plan_Compras!$G$8>0,Plan_Compras!$H$8=""),AND(Plan_Compras!$J$8>0,Plan_Compras!$K$8=""),AND(Plan_Compras!$G$17>0,Plan_Compras!$H$17=""),AND(Plan_Compras!$J$17>0,Plan_Compras!$K$17=""),AND(Plan_Compras!$G$26>0,Plan_Compras!$H$26=""),AND(Plan_Compras!$J$26>0,Plan_Compras!$K$26=""),AND(Plan_Compras!$G$35>0,Plan_Compras!$H$35=""),AND(Plan_Compras!$J$35>0,Plan_Compras!$K$35=""),AND(Plan_Compras!$G$44>0,Plan_Compras!$H$44=""),AND(Plan_Compras!$J$44>0,Plan_Compras!$K$44=""),AND(Plan_Compras!$G$53>0,Plan_Compras!$H$53=""),AND(Plan_Compras!$J$53>0,Plan_Compras!$K$53=""),AND(Plan_Compras!$G$62>0,Plan_Compras!$H$62=""),AND(Plan_Compras!$J$62>0,Plan_Compras!$K$62=""),AND(Plan_Compras!$G$71>0,Plan_Compras!$H$71=""),AND(Plan_Compras!$J$71>0,Plan_Compras!$K$71=""),AND(Plan_Compras!$G$80>0,Plan_Compras!$H$80=""),AND(Plan_Compras!$J$80>0,Plan_Compras!$K$80=""),AND(Plan_Compras!$G$89>0,Plan_Compras!$H$89=""),AND(Plan_Compras!$J$89>0,Plan_Compras!$K$89=""),AND(Plan_Compras!$G$98>0,Plan_Compras!$H$98=""),AND(Plan_Compras!$J$98>0,Plan_Compras!$K$98=""),AND(Plan_Compras!$G$107>0,Plan_Compras!$H$107=""),AND(Plan_Compras!$J$107>0,Plan_Compras!$K$107=""))),"",MAX(IF(Plan_Compras!$G$8>0,Plan_Compras!$H$8,-1E+99),IF(Plan_Compras!$J$8>0,Plan_Compras!$K$8,-1E+99),IF(Plan_Compras!$G$17>0,Plan_Compras!$H$17,-1E+99),IF(Plan_Compras!$J$17>0,Plan_Compras!$K$17,-1E+99),IF(Plan_Compras!$G$26>0,Plan_Compras!$H$26,-1E+99),IF(Plan_Compras!$J$26>0,Plan_Compras!$K$26,-1E+99),IF(Plan_Compras!$G$35>0,Plan_Compras!$H$35,-1E+99),IF(Plan_Compras!$J$35>0,Plan_Compras!$K$35,-1E+99),IF(Plan_Compras!$G$44>0,Plan_Compras!$H$44,-1E+99),IF(Plan_Compras!$J$44>0,Plan_Compras!$K$44,-1E+99),IF(Plan_Compras!$G$53>0,Plan_Compras!$H$53,-1E+99),IF(Plan_Compras!$J$53>0,Plan_Compras!$K$53,-1E+99),IF(Plan_Compras!$G$62>0,Plan_Compras!$H$62,-1E+99),IF(Plan_Compras!$J$62>0,Plan_Compras!$K$62,-1E+99),IF(Plan_Compras!$G$71>0,Plan_Compras!$H$71,-1E+99),IF(Plan_Compras!$J$71>0,Plan_Compras!$K$71,-1E+99),IF(Plan_Compras!$G$80>0,Plan_Compras!$H$80,-1E+99),IF(Plan_Compras!$J$80>0,Plan_Compras!$K$80,-1E+99),IF(Plan_Compras!$G$89>0,Plan_Compras!$H$89,-1E+99),IF(Plan_Compras!$J$89>0,Plan_Compras!$K$89,-1E+99),IF(Plan_Compras!$G$98>0,Plan_Compras!$H$98,-1E+99),IF(Plan_Compras!$J$98>0,Plan_Compras!$K$98,-1E+99),IF(Plan_Compras!$G$107>0,Plan_Compras!$H$107,-1E+99),IF(Plan_Compras!$J$107>0,Plan_Compras!$K$107,-1E+99))) | H68: =IF(OR(F68="",G68=""),"",G68-F68) | I68: =IF(OR(D68="",SUM($D$67:$D$75)=0),"",D68/SUM($D$67:$D$75)) | J68: =IF(COUNT(Plan_Compras!$F$8,Plan_Compras!$F$17,Plan_Compras!$F$26,Plan_Compras!$F$35,Plan_Compras!$F$44,Plan_Compras!$F$53,Plan_Compras!$F$62,Plan_Compras!$F$71,Plan_Compras!$F$80,Plan_Compras!$F$89,Plan_Compras!$F$98,Plan_Compras!$F$107)=0,"",SUM(Plan_Compras!$F$8,Plan_Compras!$F$17,Plan_Compras!$F$26,Plan_Compras!$F$35,Plan_Compras!$F$44,Plan_Compras!$F$53,Plan_Compras!$F$62,Plan_Compras!$F$71,Plan_Compras!$F$80,Plan_Compras!$F$89,Plan_Compras!$F$98,Plan_Compras!$F$107)-SUM(Plan_Compras!$E$8,Plan_Compras!$E$17,Plan_Compras!$E$26,Plan_Compras!$E$35,Plan_Compras!$E$44,Plan_Compras!$E$53,Plan_Compras!$E$62,Plan_Compras!$E$71,Plan_Compras!$E$80,Plan_Compras!$E$89,Plan_Compras!$E$98,Plan_Compras!$E$107)) -> 1663.6364 | K68: =IF(AND(ISNUMBER(E68),ISNUMBER(J68)),J68*E68,"")
A69: =Maestro_Ingredientes!$B$9 -> Pimiento verde | B69: =IF(COUNT(Plan_Compras!$F$9,Plan_Compras!$F$18,Plan_Compras!$F$27,Plan_Compras!$F$36,Plan_Compras!$F$45,Plan_Compras!$F$54,Plan_Compras!$F$63,Plan_Compras!$F$72,Plan_Compras!$F$81,Plan_Compras!$F$90,Plan_Compras!$F$99,Plan_Compras!$F$108)=0,"",SUM(Plan_Compras!$F$9,Plan_Compras!$F$18,Plan_Compras!$F$27,Plan_Compras!$F$36,Plan_Compras!$F$45,Plan_Compras!$F$54,Plan_Compras!$F$63,Plan_Compras!$F$72,Plan_Compras!$F$81,Plan_Compras!$F$90,Plan_Compras!$F$99,Plan_Compras!$F$108)) -> 8588.2353 | C69: =IF(COUNT(Plan_Compras!$M$9,Plan_Compras!$M$18,Plan_Compras!$M$27,Plan_Compras!$M$36,Plan_Compras!$M$45,Plan_Compras!$M$54,Plan_Compras!$M$63,Plan_Compras!$M$72,Plan_Compras!$M$81,Plan_Compras!$M$90,Plan_Compras!$M$99,Plan_Compras!$M$108)=0,"",SUM(Plan_Compras!$M$9,Plan_Compras!$M$18,Plan_Compras!$M$27,Plan_Compras!$M$36,Plan_Compras!$M$45,Plan_Compras!$M$54,Plan_Compras!$M$63,Plan_Compras!$M$72,Plan_Compras!$M$81,Plan_Compras!$M$90,Plan_Compras!$M$99,Plan_Compras!$M$108)) -> 8588.2353 | D69: =IF(COUNT(Plan_Compras!$N$9,Plan_Compras!$N$18,Plan_Compras!$N$27,Plan_Compras!$N$36,Plan_Compras!$N$45,Plan_Compras!$N$54,Plan_Compras!$N$63,Plan_Compras!$N$72,Plan_Compras!$N$81,Plan_Compras!$N$90,Plan_Compras!$N$99,Plan_Compras!$N$108)=0,"",SUM(Plan_Compras!$N$9,Plan_Compras!$N$18,Plan_Compras!$N$27,Plan_Compras!$N$36,Plan_Compras!$N$45,Plan_Compras!$N$54,Plan_Compras!$N$63,Plan_Compras!$N$72,Plan_Compras!$N$81,Plan_Compras!$N$90,Plan_Compras!$N$99,Plan_Compras!$N$108)) | E69: =IF(OR(C69="",C69=0,OR(AND(Plan_Compras!$G$9>0,Plan_Compras!$H$9=""),AND(Plan_Compras!$J$9>0,Plan_Compras!$K$9=""),AND(Plan_Compras!$G$18>0,Plan_Compras!$H$18=""),AND(Plan_Compras!$J$18>0,Plan_Compras!$K$18=""),AND(Plan_Compras!$G$27>0,Plan_Compras!$H$27=""),AND(Plan_Compras!$J$27>0,Plan_Compras!$K$27=""),AND(Plan_Compras!$G$36>0,Plan_Compras!$H$36=""),AND(Plan_Compras!$J$36>0,Plan_Compras!$K$36=""),AND(Plan_Compras!$G$45>0,Plan_Compras!$H$45=""),AND(Plan_Compras!$J$45>0,Plan_Compras!$K$45=""),AND(Plan_Compras!$G$54>0,Plan_Compras!$H$54=""),AND(Plan_Compras!$J$54>0,Plan_Compras!$K$54=""),AND(Plan_Compras!$G$63>0,Plan_Compras!$H$63=""),AND(Plan_Compras!$J$63>0,Plan_Compras!$K$63=""),AND(Plan_Compras!$G$72>0,Plan_Compras!$H$72=""),AND(Plan_Compras!$J$72>0,Plan_Compras!$K$72=""),AND(Plan_Compras!$G$81>0,Plan_Compras!$H$81=""),AND(Plan_Compras!$J$81>0,Plan_Compras!$K$81=""),AND(Plan_Compras!$G$90>0,Plan_Compras!$H$90=""),AND(Plan_Compras!$J$90>0,Plan_Compras!$K$90=""),AND(Plan_Compras!$G$99>0,Plan_Compras!$H$99=""),AND(Plan_Compras!$J$99>0,Plan_Compras!$K$99=""),AND(Plan_Compras!$G$108>0,Plan_Compras!$H$108=""),AND(Plan_Compras!$J$108>0,Plan_Compras!$K$108=""))),"",D69/C69) | F69: =IF(OR(E69="",OR(AND(Plan_Compras!$G$9>0,Plan_Compras!$H$9=""),AND(Plan_Compras!$J$9>0,Plan_Compras!$K$9=""),AND(Plan_Compras!$G$18>0,Plan_Compras!$H$18=""),AND(Plan_Compras!$J$18>0,Plan_Compras!$K$18=""),AND(Plan_Compras!$G$27>0,Plan_Compras!$H$27=""),AND(Plan_Compras!$J$27>0,Plan_Compras!$K$27=""),AND(Plan_Compras!$G$36>0,Plan_Compras!$H$36=""),AND(Plan_Compras!$J$36>0,Plan_Compras!$K$36=""),AND(Plan_Compras!$G$45>0,Plan_Compras!$H$45=""),AND(Plan_Compras!$J$45>0,Plan_Compras!$K$45=""),AND(Plan_Compras!$G$54>0,Plan_Compras!$H$54=""),AND(Plan_Compras!$J$54>0,Plan_Compras!$K$54=""),AND(Plan_Compras!$G$63>0,Plan_Compras!$H$63=""),AND(Plan_Compras!$J$63>0,Plan_Compras!$K$63=""),AND(Plan_Compras!$G$72>0,Plan_Compras!$H$72=""),AND(Plan_Compras!$J$72>0,Plan_Compras!$K$72=""),AND(Plan_Compras!$G$81>0,Plan_Compras!$H$81=""),AND(Plan_Compras!$J$81>0,Plan_Compras!$K$81=""),AND(Plan_Compras!$G$90>0,Plan_Compras!$H$90=""),AND(Plan_Compras!$J$90>0,Plan_Compras!$K$90=""),AND(Plan_Compras!$G$99>0,Plan_Compras!$H$99=""),AND(Plan_Compras!$J$99>0,Plan_Compras!$K$99=""),AND(Plan_Compras!$G$108>0,Plan_Compras!$H$108=""),AND(Plan_Compras!$J$108>0,Plan_Compras!$K$108=""))),"",MIN(IF(Plan_Compras!$G$9>0,Plan_Compras!$H$9,1E+99),IF(Plan_Compras!$J$9>0,Plan_Compras!$K$9,1E+99),IF(Plan_Compras!$G$18>0,Plan_Compras!$H$18,1E+99),IF(Plan_Compras!$J$18>0,Plan_Compras!$K$18,1E+99),IF(Plan_Compras!$G$27>0,Plan_Compras!$H$27,1E+99),IF(Plan_Compras!$J$27>0,Plan_Compras!$K$27,1E+99),IF(Plan_Compras!$G$36>0,Plan_Compras!$H$36,1E+99),IF(Plan_Compras!$J$36>0,Plan_Compras!$K$36,1E+99),IF(Plan_Compras!$G$45>0,Plan_Compras!$H$45,1E+99),IF(Plan_Compras!$J$45>0,Plan_Compras!$K$45,1E+99),IF(Plan_Compras!$G$54>0,Plan_Compras!$H$54,1E+99),IF(Plan_Compras!$J$54>0,Plan_Compras!$K$54,1E+99),IF(Plan_Compras!$G$63>0,Plan_Compras!$H$63,1E+99),IF(Plan_Compras!$J$63>0,Plan_Compras!$K$63,1E+99),IF(Plan_Compras!$G$72>0,Plan_Compras!$H$72,1E+99),IF(Plan_Compras!$J$72>0,Plan_Compras!$K$72,1E+99),IF(Plan_Compras!$G$81>0,Plan_Compras!$H$81,1E+99),IF(Plan_Compras!$J$81>0,Plan_Compras!$K$81,1E+99),IF(Plan_Compras!$G$90>0,Plan_Compras!$H$90,1E+99),IF(Plan_Compras!$J$90>0,Plan_Compras!$K$90,1E+99),IF(Plan_Compras!$G$99>0,Plan_Compras!$H$99,1E+99),IF(Plan_Compras!$J$99>0,Plan_Compras!$K$99,1E+99),IF(Plan_Compras!$G$108>0,Plan_Compras!$H$108,1E+99),IF(Plan_Compras!$J$108>0,Plan_Compras!$K$108,1E+99))) | G69: =IF(OR(E69="",OR(AND(Plan_Compras!$G$9>0,Plan_Compras!$H$9=""),AND(Plan_Compras!$J$9>0,Plan_Compras!$K$9=""),AND(Plan_Compras!$G$18>0,Plan_Compras!$H$18=""),AND(Plan_Compras!$J$18>0,Plan_Compras!$K$18=""),AND(Plan_Compras!$G$27>0,Plan_Compras!$H$27=""),AND(Plan_Compras!$J$27>0,Plan_Compras!$K$27=""),AND(Plan_Compras!$G$36>0,Plan_Compras!$H$36=""),AND(Plan_Compras!$J$36>0,Plan_Compras!$K$36=""),AND(Plan_Compras!$G$45>0,Plan_Compras!$H$45=""),AND(Plan_Compras!$J$45>0,Plan_Compras!$K$45=""),AND(Plan_Compras!$G$54>0,Plan_Compras!$H$54=""),AND(Plan_Compras!$J$54>0,Plan_Compras!$K$54=""),AND(Plan_Compras!$G$63>0,Plan_Compras!$H$63=""),AND(Plan_Compras!$J$63>0,Plan_Compras!$K$63=""),AND(Plan_Compras!$G$72>0,Plan_Compras!$H$72=""),AND(Plan_Compras!$J$72>0,Plan_Compras!$K$72=""),AND(Plan_Compras!$G$81>0,Plan_Compras!$H$81=""),AND(Plan_Compras!$J$81>0,Plan_Compras!$K$81=""),AND(Plan_Compras!$G$90>0,Plan_Compras!$H$90=""),AND(Plan_Compras!$J$90>0,Plan_Compras!$K$90=""),AND(Plan_Compras!$G$99>0,Plan_Compras!$H$99=""),AND(Plan_Compras!$J$99>0,Plan_Compras!$K$99=""),AND(Plan_Compras!$G$108>0,Plan_Compras!$H$108=""),AND(Plan_Compras!$J$108>0,Plan_Compras!$K$108=""))),"",MAX(IF(Plan_Compras!$G$9>0,Plan_Compras!$H$9,-1E+99),IF(Plan_Compras!$J$9>0,Plan_Compras!$K$9,-1E+99),IF(Plan_Compras!$G$18>0,Plan_Compras!$H$18,-1E+99),IF(Plan_Compras!$J$18>0,Plan_Compras!$K$18,-1E+99),IF(Plan_Compras!$G$27>0,Plan_Compras!$H$27,-1E+99),IF(Plan_Compras!$J$27>0,Plan_Compras!$K$27,-1E+99),IF(Plan_Compras!$G$36>0,Plan_Compras!$H$36,-1E+99),IF(Plan_Compras!$J$36>0,Plan_Compras!$K$36,-1E+99),IF(Plan_Compras!$G$45>0,Plan_Compras!$H$45,-1E+99),IF(Plan_Compras!$J$45>0,Plan_Compras!$K$45,-1E+99),IF(Plan_Compras!$G$54>0,Plan_Compras!$H$54,-1E+99),IF(Plan_Compras!$J$54>0,Plan_Compras!$K$54,-1E+99),IF(Plan_Compras!$G$63>0,Plan_Compras!$H$63,-1E+99),IF(Plan_Compras!$J$63>0,Plan_Compras!$K$63,-1E+99),IF(Plan_Compras!$G$72>0,Plan_Compras!$H$72,-1E+99),IF(Plan_Compras!$J$72>0,Plan_Compras!$K$72,-1E+99),IF(Plan_Compras!$G$81>0,Plan_Compras!$H$81,-1E+99),IF(Plan_Compras!$J$81>0,Plan_Compras!$K$81,-1E+99),IF(Plan_Compras!$G$90>0,Plan_Compras!$H$90,-1E+99),IF(Plan_Compras!$J$90>0,Plan_Compras!$K$90,-1E+99),IF(Plan_Compras!$G$99>0,Plan_Compras!$H$99,-1E+99),IF(Plan_Compras!$J$99>0,Plan_Compras!$K$99,-1E+99),IF(Plan_Compras!$G$108>0,Plan_Compras!$H$108,-1E+99),IF(Plan_Compras!$J$108>0,Plan_Compras!$K$108,-1E+99))) | H69: =IF(OR(F69="",G69=""),"",G69-F69) | I69: =IF(OR(D69="",SUM($D$67:$D$75)=0),"",D69/SUM($D$67:$D$75)) | J69: =IF(COUNT(Plan_Compras!$F$9,Plan_Compras!$F$18,Plan_Compras!$F$27,Plan_Compras!$F$36,Plan_Compras!$F$45,Plan_Compras!$F$54,Plan_Compras!$F$63,Plan_Compras!$F$72,Plan_Compras!$F$81,Plan_Compras!$F$90,Plan_Compras!$F$99,Plan_Compras!$F$108)=0,"",SUM(Plan_Compras!$F$9,Plan_Compras!$F$18,Plan_Compras!$F$27,Plan_Compras!$F$36,Plan_Compras!$F$45,Plan_Compras!$F$54,Plan_Compras!$F$63,Plan_Compras!$F$72,Plan_Compras!$F$81,Plan_Compras!$F$90,Plan_Compras!$F$99,Plan_Compras!$F$108)-SUM(Plan_Compras!$E$9,Plan_Compras!$E$18,Plan_Compras!$E$27,Plan_Compras!$E$36,Plan_Compras!$E$45,Plan_Compras!$E$54,Plan_Compras!$E$63,Plan_Compras!$E$72,Plan_Compras!$E$81,Plan_Compras!$E$90,Plan_Compras!$E$99,Plan_Compras!$E$108)) -> 1288.2353 | K69: =IF(AND(ISNUMBER(E69),ISNUMBER(J69)),J69*E69,"")
A70: =Maestro_Ingredientes!$B$10 -> Cebolla | B70: =IF(COUNT(Plan_Compras!$F$10,Plan_Compras!$F$19,Plan_Compras!$F$28,Plan_Compras!$F$37,Plan_Compras!$F$46,Plan_Compras!$F$55,Plan_Compras!$F$64,Plan_Compras!$F$73,Plan_Compras!$F$82,Plan_Compras!$F$91,Plan_Compras!$F$100,Plan_Compras!$F$109)=0,"",SUM(Plan_Compras!$F$10,Plan_Compras!$F$19,Plan_Compras!$F$28,Plan_Compras!$F$37,Plan_Compras!$F$46,Plan_Compras!$F$55,Plan_Compras!$F$64,Plan_Compras!$F$73,Plan_Compras!$F$82,Plan_Compras!$F$91,Plan_Compras!$F$100,Plan_Compras!$F$109)) -> 4888.8889 | C70: =IF(COUNT(Plan_Compras!$M$10,Plan_Compras!$M$19,Plan_Compras!$M$28,Plan_Compras!$M$37,Plan_Compras!$M$46,Plan_Compras!$M$55,Plan_Compras!$M$64,Plan_Compras!$M$73,Plan_Compras!$M$82,Plan_Compras!$M$91,Plan_Compras!$M$100,Plan_Compras!$M$109)=0,"",SUM(Plan_Compras!$M$10,Plan_Compras!$M$19,Plan_Compras!$M$28,Plan_Compras!$M$37,Plan_Compras!$M$46,Plan_Compras!$M$55,Plan_Compras!$M$64,Plan_Compras!$M$73,Plan_Compras!$M$82,Plan_Compras!$M$91,Plan_Compras!$M$100,Plan_Compras!$M$109)) -> 4888.8889 | D70: =IF(COUNT(Plan_Compras!$N$10,Plan_Compras!$N$19,Plan_Compras!$N$28,Plan_Compras!$N$37,Plan_Compras!$N$46,Plan_Compras!$N$55,Plan_Compras!$N$64,Plan_Compras!$N$73,Plan_Compras!$N$82,Plan_Compras!$N$91,Plan_Compras!$N$100,Plan_Compras!$N$109)=0,"",SUM(Plan_Compras!$N$10,Plan_Compras!$N$19,Plan_Compras!$N$28,Plan_Compras!$N$37,Plan_Compras!$N$46,Plan_Compras!$N$55,Plan_Compras!$N$64,Plan_Compras!$N$73,Plan_Compras!$N$82,Plan_Compras!$N$91,Plan_Compras!$N$100,Plan_Compras!$N$109)) | E70: =IF(OR(C70="",C70=0,OR(AND(Plan_Compras!$G$10>0,Plan_Compras!$H$10=""),AND(Plan_Compras!$J$10>0,Plan_Compras!$K$10=""),AND(Plan_Compras!$G$19>0,Plan_Compras!$H$19=""),AND(Plan_Compras!$J$19>0,Plan_Compras!$K$19=""),AND(Plan_Compras!$G$28>0,Plan_Compras!$H$28=""),AND(Plan_Compras!$J$28>0,Plan_Compras!$K$28=""),AND(Plan_Compras!$G$37>0,Plan_Compras!$H$37=""),AND(Plan_Compras!$J$37>0,Plan_Compras!$K$37=""),AND(Plan_Compras!$G$46>0,Plan_Compras!$H$46=""),AND(Plan_Compras!$J$46>0,Plan_Compras!$K$46=""),AND(Plan_Compras!$G$55>0,Plan_Compras!$H$55=""),AND(Plan_Compras!$J$55>0,Plan_Compras!$K$55=""),AND(Plan_Compras!$G$64>0,Plan_Compras!$H$64=""),AND(Plan_Compras!$J$64>0,Plan_Compras!$K$64=""),AND(Plan_Compras!$G$73>0,Plan_Compras!$H$73=""),AND(Plan_Compras!$J$73>0,Plan_Compras!$K$73=""),AND(Plan_Compras!$G$82>0,Plan_Compras!$H$82=""),AND(Plan_Compras!$J$82>0,Plan_Compras!$K$82=""),AND(Plan_Compras!$G$91>0,Plan_Compras!$H$91=""),AND(Plan_Compras!$J$91>0,Plan_Compras!$K$91=""),AND(Plan_Compras!$G$100>0,Plan_Compras!$H$100=""),AND(Plan_Compras!$J$100>0,Plan_Compras!$K$100=""),AND(Plan_Compras!$G$109>0,Plan_Compras!$H$109=""),AND(Plan_Compras!$J$109>0,Plan_Compras!$K$109=""))),"",D70/C70) | F70: =IF(OR(E70="",OR(AND(Plan_Compras!$G$10>0,Plan_Compras!$H$10=""),AND(Plan_Compras!$J$10>0,Plan_Compras!$K$10=""),AND(Plan_Compras!$G$19>0,Plan_Compras!$H$19=""),AND(Plan_Compras!$J$19>0,Plan_Compras!$K$19=""),AND(Plan_Compras!$G$28>0,Plan_Compras!$H$28=""),AND(Plan_Compras!$J$28>0,Plan_Compras!$K$28=""),AND(Plan_Compras!$G$37>0,Plan_Compras!$H$37=""),AND(Plan_Compras!$J$37>0,Plan_Compras!$K$37=""),AND(Plan_Compras!$G$46>0,Plan_Compras!$H$46=""),AND(Plan_Compras!$J$46>0,Plan_Compras!$K$46=""),AND(Plan_Compras!$G$55>0,Plan_Compras!$H$55=""),AND(Plan_Compras!$J$55>0,Plan_Compras!$K$55=""),AND(Plan_Compras!$G$64>0,Plan_Compras!$H$64=""),AND(Plan_Compras!$J$64>0,Plan_Compras!$K$64=""),AND(Plan_Compras!$G$73>0,Plan_Compras!$H$73=""),AND(Plan_Compras!$J$73>0,Plan_Compras!$K$73=""),AND(Plan_Compras!$G$82>0,Plan_Compras!$H$82=""),AND(Plan_Compras!$J$82>0,Plan_Compras!$K$82=""),AND(Plan_Compras!$G$91>0,Plan_Compras!$H$91=""),AND(Plan_Compras!$J$91>0,Plan_Compras!$K$91=""),AND(Plan_Compras!$G$100>0,Plan_Compras!$H$100=""),AND(Plan_Compras!$J$100>0,Plan_Compras!$K$100=""),AND(Plan_Compras!$G$109>0,Plan_Compras!$H$109=""),AND(Plan_Compras!$J$109>0,Plan_Compras!$K$109=""))),"",MIN(IF(Plan_Compras!$G$10>0,Plan_Compras!$H$10,1E+99),IF(Plan_Compras!$J$10>0,Plan_Compras!$K$10,1E+99),IF(Plan_Compras!$G$19>0,Plan_Compras!$H$19,1E+99),IF(Plan_Compras!$J$19>0,Plan_Compras!$K$19,1E+99),IF(Plan_Compras!$G$28>0,Plan_Compras!$H$28,1E+99),IF(Plan_Compras!$J$28>0,Plan_Compras!$K$28,1E+99),IF(Plan_Compras!$G$37>0,Plan_Compras!$H$37,1E+99),IF(Plan_Compras!$J$37>0,Plan_Compras!$K$37,1E+99),IF(Plan_Compras!$G$46>0,Plan_Compras!$H$46,1E+99),IF(Plan_Compras!$J$46>0,Plan_Compras!$K$46,1E+99),IF(Plan_Compras!$G$55>0,Plan_Compras!$H$55,1E+99),IF(Plan_Compras!$J$55>0,Plan_Compras!$K$55,1E+99),IF(Plan_Compras!$G$64>0,Plan_Compras!$H$64,1E+99),IF(Plan_Compras!$J$64>0,Plan_Compras!$K$64,1E+99),IF(Plan_Compras!$G$73>0,Plan_Compras!$H$73,1E+99),IF(Plan_Compras!$J$73>0,Plan_Compras!$K$73,1E+99),IF(Plan_Compras!$G$82>0,Plan_Compras!$H$82,1E+99),IF(Plan_Compras!$J$82>0,Plan_Compras!$K$82,1E+99),IF(Plan_Compras!$G$91>0,Plan_Compras!$H$91,1E+99),IF(Plan_Compras!$J$91>0,Plan_Compras!$K$91,1E+99),IF(Plan_Compras!$G$100>0,Plan_Compras!$H$100,1E+99),IF(Plan_Compras!$J$100>0,Plan_Compras!$K$100,1E+99),IF(Plan_Compras!$G$109>0,Plan_Compras!$H$109,1E+99),IF(Plan_Compras!$J$109>0,Plan_Compras!$K$109,1E+99))) | G70: =IF(OR(E70="",OR(AND(Plan_Compras!$G$10>0,Plan_Compras!$H$10=""),AND(Plan_Compras!$J$10>0,Plan_Compras!$K$10=""),AND(Plan_Compras!$G$19>0,Plan_Compras!$H$19=""),AND(Plan_Compras!$J$19>0,Plan_Compras!$K$19=""),AND(Plan_Compras!$G$28>0,Plan_Compras!$H$28=""),AND(Plan_Compras!$J$28>0,Plan_Compras!$K$28=""),AND(Plan_Compras!$G$37>0,Plan_Compras!$H$37=""),AND(Plan_Compras!$J$37>0,Plan_Compras!$K$37=""),AND(Plan_Compras!$G$46>0,Plan_Compras!$H$46=""),AND(Plan_Compras!$J$46>0,Plan_Compras!$K$46=""),AND(Plan_Compras!$G$55>0,Plan_Compras!$H$55=""),AND(Plan_Compras!$J$55>0,Plan_Compras!$K$55=""),AND(Plan_Compras!$G$64>0,Plan_Compras!$H$64=""),AND(Plan_Compras!$J$64>0,Plan_Compras!$K$64=""),AND(Plan_Compras!$G$73>0,Plan_Compras!$H$73=""),AND(Plan_Compras!$J$73>0,Plan_Compras!$K$73=""),AND(Plan_Compras!$G$82>0,Plan_Compras!$H$82=""),AND(Plan_Compras!$J$82>0,Plan_Compras!$K$82=""),AND(Plan_Compras!$G$91>0,Plan_Compras!$H$91=""),AND(Plan_Compras!$J$91>0,Plan_Compras!$K$91=""),AND(Plan_Compras!$G$100>0,Plan_Compras!$H$100=""),AND(Plan_Compras!$J$100>0,Plan_Compras!$K$100=""),AND(Plan_Compras!$G$109>0,Plan_Compras!$H$109=""),AND(Plan_Compras!$J$109>0,Plan_Compras!$K$109=""))),"",MAX(IF(Plan_Compras!$G$10>0,Plan_Compras!$H$10,-1E+99),IF(Plan_Compras!$J$10>0,Plan_Compras!$K$10,-1E+99),IF(Plan_Compras!$G$19>0,Plan_Compras!$H$19,-1E+99),IF(Plan_Compras!$J$19>0,Plan_Compras!$K$19,-1E+99),IF(Plan_Compras!$G$28>0,Plan_Compras!$H$28,-1E+99),IF(Plan_Compras!$J$28>0,Plan_Compras!$K$28,-1E+99),IF(Plan_Compras!$G$37>0,Plan_Compras!$H$37,-1E+99),IF(Plan_Compras!$J$37>0,Plan_Compras!$K$37,-1E+99),IF(Plan_Compras!$G$46>0,Plan_Compras!$H$46,-1E+99),IF(Plan_Compras!$J$46>0,Plan_Compras!$K$46,-1E+99),IF(Plan_Compras!$G$55>0,Plan_Compras!$H$55,-1E+99),IF(Plan_Compras!$J$55>0,Plan_Compras!$K$55,-1E+99),IF(Plan_Compras!$G$64>0,Plan_Compras!$H$64,-1E+99),IF(Plan_Compras!$J$64>0,Plan_Compras!$K$64,-1E+99),IF(Plan_Compras!$G$73>0,Plan_Compras!$H$73,-1E+99),IF(Plan_Compras!$J$73>0,Plan_Compras!$K$73,-1E+99),IF(Plan_Compras!$G$82>0,Plan_Compras!$H$82,-1E+99),IF(Plan_Compras!$J$82>0,Plan_Compras!$K$82,-1E+99),IF(Plan_Compras!$G$91>0,Plan_Compras!$H$91,-1E+99),IF(Plan_Compras!$J$91>0,Plan_Compras!$K$91,-1E+99),IF(Plan_Compras!$G$100>0,Plan_Compras!$H$100,-1E+99),IF(Plan_Compras!$J$100>0,Plan_Compras!$K$100,-1E+99),IF(Plan_Compras!$G$109>0,Plan_Compras!$H$109,-1E+99),IF(Plan_Compras!$J$109>0,Plan_Compras!$K$109,-1E+99))) | H70: =IF(OR(F70="",G70=""),"",G70-F70) | I70: =IF(OR(D70="",SUM($D$67:$D$75)=0),"",D70/SUM($D$67:$D$75)) | J70: =IF(COUNT(Plan_Compras!$F$10,Plan_Compras!$F$19,Plan_Compras!$F$28,Plan_Compras!$F$37,Plan_Compras!$F$46,Plan_Compras!$F$55,Plan_Compras!$F$64,Plan_Compras!$F$73,Plan_Compras!$F$82,Plan_Compras!$F$91,Plan_Compras!$F$100,Plan_Compras!$F$109)=0,"",SUM(Plan_Compras!$F$10,Plan_Compras!$F$19,Plan_Compras!$F$28,Plan_Compras!$F$37,Plan_Compras!$F$46,Plan_Compras!$F$55,Plan_Compras!$F$64,Plan_Compras!$F$73,Plan_Compras!$F$82,Plan_Compras!$F$91,Plan_Compras!$F$100,Plan_Compras!$F$109)-SUM(Plan_Compras!$E$10,Plan_Compras!$E$19,Plan_Compras!$E$28,Plan_Compras!$E$37,Plan_Compras!$E$46,Plan_Compras!$E$55,Plan_Compras!$E$64,Plan_Compras!$E$73,Plan_Compras!$E$82,Plan_Compras!$E$91,Plan_Compras!$E$100,Plan_Compras!$E$109)) -> 488.88889 | K70: =IF(AND(ISNUMBER(E70),ISNUMBER(J70)),J70*E70,"")
A71: =Maestro_Ingredientes!$B$11 -> Ajo | B71: =IF(COUNT(Plan_Compras!$F$11,Plan_Compras!$F$20,Plan_Compras!$F$29,Plan_Compras!$F$38,Plan_Compras!$F$47,Plan_Compras!$F$56,Plan_Compras!$F$65,Plan_Compras!$F$74,Plan_Compras!$F$83,Plan_Compras!$F$92,Plan_Compras!$F$101,Plan_Compras!$F$110)=0,"",SUM(Plan_Compras!$F$11,Plan_Compras!$F$20,Plan_Compras!$F$29,Plan_Compras!$F$38,Plan_Compras!$F$47,Plan_Compras!$F$56,Plan_Compras!$F$65,Plan_Compras!$F$74,Plan_Compras!$F$83,Plan_Compras!$F$92,Plan_Compras!$F$101,Plan_Compras!$F$110)) -> 869.56522 | C71: =IF(COUNT(Plan_Compras!$M$11,Plan_Compras!$M$20,Plan_Compras!$M$29,Plan_Compras!$M$38,Plan_Compras!$M$47,Plan_Compras!$M$56,Plan_Compras!$M$65,Plan_Compras!$M$74,Plan_Compras!$M$83,Plan_Compras!$M$92,Plan_Compras!$M$101,Plan_Compras!$M$110)=0,"",SUM(Plan_Compras!$M$11,Plan_Compras!$M$20,Plan_Compras!$M$29,Plan_Compras!$M$38,Plan_Compras!$M$47,Plan_Compras!$M$56,Plan_Compras!$M$65,Plan_Compras!$M$74,Plan_Compras!$M$83,Plan_Compras!$M$92,Plan_Compras!$M$101,Plan_Compras!$M$110)) -> 869.56522 | D71: =IF(COUNT(Plan_Compras!$N$11,Plan_Compras!$N$20,Plan_Compras!$N$29,Plan_Compras!$N$38,Plan_Compras!$N$47,Plan_Compras!$N$56,Plan_Compras!$N$65,Plan_Compras!$N$74,Plan_Compras!$N$83,Plan_Compras!$N$92,Plan_Compras!$N$101,Plan_Compras!$N$110)=0,"",SUM(Plan_Compras!$N$11,Plan_Compras!$N$20,Plan_Compras!$N$29,Plan_Compras!$N$38,Plan_Compras!$N$47,Plan_Compras!$N$56,Plan_Compras!$N$65,Plan_Compras!$N$74,Plan_Compras!$N$83,Plan_Compras!$N$92,Plan_Compras!$N$101,Plan_Compras!$N$110)) | E71: =IF(OR(C71="",C71=0,OR(AND(Plan_Compras!$G$11>0,Plan_Compras!$H$11=""),AND(Plan_Compras!$J$11>0,Plan_Compras!$K$11=""),AND(Plan_Compras!$G$20>0,Plan_Compras!$H$20=""),AND(Plan_Compras!$J$20>0,Plan_Compras!$K$20=""),AND(Plan_Compras!$G$29>0,Plan_Compras!$H$29=""),AND(Plan_Compras!$J$29>0,Plan_Compras!$K$29=""),AND(Plan_Compras!$G$38>0,Plan_Compras!$H$38=""),AND(Plan_Compras!$J$38>0,Plan_Compras!$K$38=""),AND(Plan_Compras!$G$47>0,Plan_Compras!$H$47=""),AND(Plan_Compras!$J$47>0,Plan_Compras!$K$47=""),AND(Plan_Compras!$G$56>0,Plan_Compras!$H$56=""),AND(Plan_Compras!$J$56>0,Plan_Compras!$K$56=""),AND(Plan_Compras!$G$65>0,Plan_Compras!$H$65=""),AND(Plan_Compras!$J$65>0,Plan_Compras!$K$65=""),AND(Plan_Compras!$G$74>0,Plan_Compras!$H$74=""),AND(Plan_Compras!$J$74>0,Plan_Compras!$K$74=""),AND(Plan_Compras!$G$83>0,Plan_Compras!$H$83=""),AND(Plan_Compras!$J$83>0,Plan_Compras!$K$83=""),AND(Plan_Compras!$G$92>0,Plan_Compras!$H$92=""),AND(Plan_Compras!$J$92>0,Plan_Compras!$K$92=""),AND(Plan_Compras!$G$101>0,Plan_Compras!$H$101=""),AND(Plan_Compras!$J$101>0,Plan_Compras!$K$101=""),AND(Plan_Compras!$G$110>0,Plan_Compras!$H$110=""),AND(Plan_Compras!$J$110>0,Plan_Compras!$K$110=""))),"",D71/C71) | F71: =IF(OR(E71="",OR(AND(Plan_Compras!$G$11>0,Plan_Compras!$H$11=""),AND(Plan_Compras!$J$11>0,Plan_Compras!$K$11=""),AND(Plan_Compras!$G$20>0,Plan_Compras!$H$20=""),AND(Plan_Compras!$J$20>0,Plan_Compras!$K$20=""),AND(Plan_Compras!$G$29>0,Plan_Compras!$H$29=""),AND(Plan_Compras!$J$29>0,Plan_Compras!$K$29=""),AND(Plan_Compras!$G$38>0,Plan_Compras!$H$38=""),AND(Plan_Compras!$J$38>0,Plan_Compras!$K$38=""),AND(Plan_Compras!$G$47>0,Plan_Compras!$H$47=""),AND(Plan_Compras!$J$47>0,Plan_Compras!$K$47=""),AND(Plan_Compras!$G$56>0,Plan_Compras!$H$56=""),AND(Plan_Compras!$J$56>0,Plan_Compras!$K$56=""),AND(Plan_Compras!$G$65>0,Plan_Compras!$H$65=""),AND(Plan_Compras!$J$65>0,Plan_Compras!$K$65=""),AND(Plan_Compras!$G$74>0,Plan_Compras!$H$74=""),AND(Plan_Compras!$J$74>0,Plan_Compras!$K$74=""),AND(Plan_Compras!$G$83>0,Plan_Compras!$H$83=""),AND(Plan_Compras!$J$83>0,Plan_Compras!$K$83=""),AND(Plan_Compras!$G$92>0,Plan_Compras!$H$92=""),AND(Plan_Compras!$J$92>0,Plan_Compras!$K$92=""),AND(Plan_Compras!$G$101>0,Plan_Compras!$H$101=""),AND(Plan_Compras!$J$101>0,Plan_Compras!$K$101=""),AND(Plan_Compras!$G$110>0,Plan_Compras!$H$110=""),AND(Plan_Compras!$J$110>0,Plan_Compras!$K$110=""))),"",MIN(IF(Plan_Compras!$G$11>0,Plan_Compras!$H$11,1E+99),IF(Plan_Compras!$J$11>0,Plan_Compras!$K$11,1E+99),IF(Plan_Compras!$G$20>0,Plan_Compras!$H$20,1E+99),IF(Plan_Compras!$J$20>0,Plan_Compras!$K$20,1E+99),IF(Plan_Compras!$G$29>0,Plan_Compras!$H$29,1E+99),IF(Plan_Compras!$J$29>0,Plan_Compras!$K$29,1E+99),IF(Plan_Compras!$G$38>0,Plan_Compras!$H$38,1E+99),IF(Plan_Compras!$J$38>0,Plan_Compras!$K$38,1E+99),IF(Plan_Compras!$G$47>0,Plan_Compras!$H$47,1E+99),IF(Plan_Compras!$J$47>0,Plan_Compras!$K$47,1E+99),IF(Plan_Compras!$G$56>0,Plan_Compras!$H$56,1E+99),IF(Plan_Compras!$J$56>0,Plan_Compras!$K$56,1E+99),IF(Plan_Compras!$G$65>0,Plan_Compras!$H$65,1E+99),IF(Plan_Compras!$J$65>0,Plan_Compras!$K$65,1E+99),IF(Plan_Compras!$G$74>0,Plan_Compras!$H$74,1E+99),IF(Plan_Compras!$J$74>0,Plan_Compras!$K$74,1E+99),IF(Plan_Compras!$G$83>0,Plan_Compras!$H$83,1E+99),IF(Plan_Compras!$J$83>0,Plan_Compras!$K$83,1E+99),IF(Plan_Compras!$G$92>0,Plan_Compras!$H$92,1E+99),IF(Plan_Compras!$J$92>0,Plan_Compras!$K$92,1E+99),IF(Plan_Compras!$G$101>0,Plan_Compras!$H$101,1E+99),IF(Plan_Compras!$J$101>0,Plan_Compras!$K$101,1E+99),IF(Plan_Compras!$G$110>0,Plan_Compras!$H$110,1E+99),IF(Plan_Compras!$J$110>0,Plan_Compras!$K$110,1E+99))) | G71: =IF(OR(E71="",OR(AND(Plan_Compras!$G$11>0,Plan_Compras!$H$11=""),AND(Plan_Compras!$J$11>0,Plan_Compras!$K$11=""),AND(Plan_Compras!$G$20>0,Plan_Compras!$H$20=""),AND(Plan_Compras!$J$20>0,Plan_Compras!$K$20=""),AND(Plan_Compras!$G$29>0,Plan_Compras!$H$29=""),AND(Plan_Compras!$J$29>0,Plan_Compras!$K$29=""),AND(Plan_Compras!$G$38>0,Plan_Compras!$H$38=""),AND(Plan_Compras!$J$38>0,Plan_Compras!$K$38=""),AND(Plan_Compras!$G$47>0,Plan_Compras!$H$47=""),AND(Plan_Compras!$J$47>0,Plan_Compras!$K$47=""),AND(Plan_Compras!$G$56>0,Plan_Compras!$H$56=""),AND(Plan_Compras!$J$56>0,Plan_Compras!$K$56=""),AND(Plan_Compras!$G$65>0,Plan_Compras!$H$65=""),AND(Plan_Compras!$J$65>0,Plan_Compras!$K$65=""),AND(Plan_Compras!$G$74>0,Plan_Compras!$H$74=""),AND(Plan_Compras!$J$74>0,Plan_Compras!$K$74=""),AND(Plan_Compras!$G$83>0,Plan_Compras!$H$83=""),AND(Plan_Compras!$J$83>0,Plan_Compras!$K$83=""),AND(Plan_Compras!$G$92>0,Plan_Compras!$H$92=""),AND(Plan_Compras!$J$92>0,Plan_Compras!$K$92=""),AND(Plan_Compras!$G$101>0,Plan_Compras!$H$101=""),AND(Plan_Compras!$J$101>0,Plan_Compras!$K$101=""),AND(Plan_Compras!$G$110>0,Plan_Compras!$H$110=""),AND(Plan_Compras!$J$110>0,Plan_Compras!$K$110=""))),"",MAX(IF(Plan_Compras!$G$11>0,Plan_Compras!$H$11,-1E+99),IF(Plan_Compras!$J$11>0,Plan_Compras!$K$11,-1E+99),IF(Plan_Compras!$G$20>0,Plan_Compras!$H$20,-1E+99),IF(Plan_Compras!$J$20>0,Plan_Compras!$K$20,-1E+99),IF(Plan_Compras!$G$29>0,Plan_Compras!$H$29,-1E+99),IF(Plan_Compras!$J$29>0,Plan_Compras!$K$29,-1E+99),IF(Plan_Compras!$G$38>0,Plan_Compras!$H$38,-1E+99),IF(Plan_Compras!$J$38>0,Plan_Compras!$K$38,-1E+99),IF(Plan_Compras!$G$47>0,Plan_Compras!$H$47,-1E+99),IF(Plan_Compras!$J$47>0,Plan_Compras!$K$47,-1E+99),IF(Plan_Compras!$G$56>0,Plan_Compras!$H$56,-1E+99),IF(Plan_Compras!$J$56>0,Plan_Compras!$K$56,-1E+99),IF(Plan_Compras!$G$65>0,Plan_Compras!$H$65,-1E+99),IF(Plan_Compras!$J$65>0,Plan_Compras!$K$65,-1E+99),IF(Plan_Compras!$G$74>0,Plan_Compras!$H$74,-1E+99),IF(Plan_Compras!$J$74>0,Plan_Compras!$K$74,-1E+99),IF(Plan_Compras!$G$83>0,Plan_Compras!$H$83,-1E+99),IF(Plan_Compras!$J$83>0,Plan_Compras!$K$83,-1E+99),IF(Plan_Compras!$G$92>0,Plan_Compras!$H$92,-1E+99),IF(Plan_Compras!$J$92>0,Plan_Compras!$K$92,-1E+99),IF(Plan_Compras!$G$101>0,Plan_Compras!$H$101,-1E+99),IF(Plan_Compras!$J$101>0,Plan_Compras!$K$101,-1E+99),IF(Plan_Compras!$G$110>0,Plan_Compras!$H$110,-1E+99),IF(Plan_Compras!$J$110>0,Plan_Compras!$K$110,-1E+99))) | H71: =IF(OR(F71="",G71=""),"",G71-F71) | I71: =IF(OR(D71="",SUM($D$67:$D$75)=0),"",D71/SUM($D$67:$D$75)) | J71: =IF(COUNT(Plan_Compras!$F$11,Plan_Compras!$F$20,Plan_Compras!$F$29,Plan_Compras!$F$38,Plan_Compras!$F$47,Plan_Compras!$F$56,Plan_Compras!$F$65,Plan_Compras!$F$74,Plan_Compras!$F$83,Plan_Compras!$F$92,Plan_Compras!$F$101,Plan_Compras!$F$110)=0,"",SUM(Plan_Compras!$F$11,Plan_Compras!$F$20,Plan_Compras!$F$29,Plan_Compras!$F$38,Plan_Compras!$F$47,Plan_Compras!$F$56,Plan_Compras!$F$65,Plan_Compras!$F$74,Plan_Compras!$F$83,Plan_Compras!$F$92,Plan_Compras!$F$101,Plan_Compras!$F$110)-SUM(Plan_Compras!$E$11,Plan_Compras!$E$20,Plan_Compras!$E$29,Plan_Compras!$E$38,Plan_Compras!$E$47,Plan_Compras!$E$56,Plan_Compras!$E$65,Plan_Compras!$E$74,Plan_Compras!$E$83,Plan_Compras!$E$92,Plan_Compras!$E$101,Plan_Compras!$E$110)) -> 69.565217 | K71: =IF(AND(ISNUMBER(E71),ISNUMBER(J71)),J71*E71,"")
A72: =Maestro_Ingredientes!$B$12 -> Aceite de oliva virgen extra | B72: =IF(COUNT(Plan_Compras!$F$12,Plan_Compras!$F$21,Plan_Compras!$F$30,Plan_Compras!$F$39,Plan_Compras!$F$48,Plan_Compras!$F$57,Plan_Compras!$F$66,Plan_Compras!$F$75,Plan_Compras!$F$84,Plan_Compras!$F$93,Plan_Compras!$F$102,Plan_Compras!$F$111)=0,"",SUM(Plan_Compras!$F$12,Plan_Compras!$F$21,Plan_Compras!$F$30,Plan_Compras!$F$39,Plan_Compras!$F$48,Plan_Compras!$F$57,Plan_Compras!$F$66,Plan_Compras!$F$75,Plan_Compras!$F$84,Plan_Compras!$F$93,Plan_Compras!$F$102,Plan_Compras!$F$111)) -> 2613.0653 | C72: =IF(COUNT(Plan_Compras!$M$12,Plan_Compras!$M$21,Plan_Compras!$M$30,Plan_Compras!$M$39,Plan_Compras!$M$48,Plan_Compras!$M$57,Plan_Compras!$M$66,Plan_Compras!$M$75,Plan_Compras!$M$84,Plan_Compras!$M$93,Plan_Compras!$M$102,Plan_Compras!$M$111)=0,"",SUM(Plan_Compras!$M$12,Plan_Compras!$M$21,Plan_Compras!$M$30,Plan_Compras!$M$39,Plan_Compras!$M$48,Plan_Compras!$M$57,Plan_Compras!$M$66,Plan_Compras!$M$75,Plan_Compras!$M$84,Plan_Compras!$M$93,Plan_Compras!$M$102,Plan_Compras!$M$111)) -> 2613.0653 | D72: =IF(COUNT(Plan_Compras!$N$12,Plan_Compras!$N$21,Plan_Compras!$N$30,Plan_Compras!$N$39,Plan_Compras!$N$48,Plan_Compras!$N$57,Plan_Compras!$N$66,Plan_Compras!$N$75,Plan_Compras!$N$84,Plan_Compras!$N$93,Plan_Compras!$N$102,Plan_Compras!$N$111)=0,"",SUM(Plan_Compras!$N$12,Plan_Compras!$N$21,Plan_Compras!$N$30,Plan_Compras!$N$39,Plan_Compras!$N$48,Plan_Compras!$N$57,Plan_Compras!$N$66,Plan_Compras!$N$75,Plan_Compras!$N$84,Plan_Compras!$N$93,Plan_Compras!$N$102,Plan_Compras!$N$111)) | E72: =IF(OR(C72="",C72=0,OR(AND(Plan_Compras!$G$12>0,Plan_Compras!$H$12=""),AND(Plan_Compras!$J$12>0,Plan_Compras!$K$12=""),AND(Plan_Compras!$G$21>0,Plan_Compras!$H$21=""),AND(Plan_Compras!$J$21>0,Plan_Compras!$K$21=""),AND(Plan_Compras!$G$30>0,Plan_Compras!$H$30=""),AND(Plan_Compras!$J$30>0,Plan_Compras!$K$30=""),AND(Plan_Compras!$G$39>0,Plan_Compras!$H$39=""),AND(Plan_Compras!$J$39>0,Plan_Compras!$K$39=""),AND(Plan_Compras!$G$48>0,Plan_Compras!$H$48=""),AND(Plan_Compras!$J$48>0,Plan_Compras!$K$48=""),AND(Plan_Compras!$G$57>0,Plan_Compras!$H$57=""),AND(Plan_Compras!$J$57>0,Plan_Compras!$K$57=""),AND(Plan_Compras!$G$66>0,Plan_Compras!$H$66=""),AND(Plan_Compras!$J$66>0,Plan_Compras!$K$66=""),AND(Plan_Compras!$G$75>0,Plan_Compras!$H$75=""),AND(Plan_Compras!$J$75>0,Plan_Compras!$K$75=""),AND(Plan_Compras!$G$84>0,Plan_Compras!$H$84=""),AND(Plan_Compras!$J$84>0,Plan_Compras!$K$84=""),AND(Plan_Compras!$G$93>0,Plan_Compras!$H$93=""),AND(Plan_Compras!$J$93>0,Plan_Compras!$K$93=""),AND(Plan_Compras!$G$102>0,Plan_Compras!$H$102=""),AND(Plan_Compras!$J$102>0,Plan_Compras!$K$102=""),AND(Plan_Compras!$G$111>0,Plan_Compras!$H$111=""),AND(Plan_Compras!$J$111>0,Plan_Compras!$K$111=""))),"",D72/C72) | F72: =IF(OR(E72="",OR(AND(Plan_Compras!$G$12>0,Plan_Compras!$H$12=""),AND(Plan_Compras!$J$12>0,Plan_Compras!$K$12=""),AND(Plan_Compras!$G$21>0,Plan_Compras!$H$21=""),AND(Plan_Compras!$J$21>0,Plan_Compras!$K$21=""),AND(Plan_Compras!$G$30>0,Plan_Compras!$H$30=""),AND(Plan_Compras!$J$30>0,Plan_Compras!$K$30=""),AND(Plan_Compras!$G$39>0,Plan_Compras!$H$39=""),AND(Plan_Compras!$J$39>0,Plan_Compras!$K$39=""),AND(Plan_Compras!$G$48>0,Plan_Compras!$H$48=""),AND(Plan_Compras!$J$48>0,Plan_Compras!$K$48=""),AND(Plan_Compras!$G$57>0,Plan_Compras!$H$57=""),AND(Plan_Compras!$J$57>0,Plan_Compras!$K$57=""),AND(Plan_Compras!$G$66>0,Plan_Compras!$H$66=""),AND(Plan_Compras!$J$66>0,Plan_Compras!$K$66=""),AND(Plan_Compras!$G$75>0,Plan_Compras!$H$75=""),AND(Plan_Compras!$J$75>0,Plan_Compras!$K$75=""),AND(Plan_Compras!$G$84>0,Plan_Compras!$H$84=""),AND(Plan_Compras!$J$84>0,Plan_Compras!$K$84=""),AND(Plan_Compras!$G$93>0,Plan_Compras!$H$93=""),AND(Plan_Compras!$J$93>0,Plan_Compras!$K$93=""),AND(Plan_Compras!$G$102>0,Plan_Compras!$H$102=""),AND(Plan_Compras!$J$102>0,Plan_Compras!$K$102=""),AND(Plan_Compras!$G$111>0,Plan_Compras!$H$111=""),AND(Plan_Compras!$J$111>0,Plan_Compras!$K$111=""))),"",MIN(IF(Plan_Compras!$G$12>0,Plan_Compras!$H$12,1E+99),IF(Plan_Compras!$J$12>0,Plan_Compras!$K$12,1E+99),IF(Plan_Compras!$G$21>0,Plan_Compras!$H$21,1E+99),IF(Plan_Compras!$J$21>0,Plan_Compras!$K$21,1E+99),IF(Plan_Compras!$G$30>0,Plan_Compras!$H$30,1E+99),IF(Plan_Compras!$J$30>0,Plan_Compras!$K$30,1E+99),IF(Plan_Compras!$G$39>0,Plan_Compras!$H$39,1E+99),IF(Plan_Compras!$J$39>0,Plan_Compras!$K$39,1E+99),IF(Plan_Compras!$G$48>0,Plan_Compras!$H$48,1E+99),IF(Plan_Compras!$J$48>0,Plan_Compras!$K$48,1E+99),IF(Plan_Compras!$G$57>0,Plan_Compras!$H$57,1E+99),IF(Plan_Compras!$J$57>0,Plan_Compras!$K$57,1E+99),IF(Plan_Compras!$G$66>0,Plan_Compras!$H$66,1E+99),IF(Plan_Compras!$J$66>0,Plan_Compras!$K$66,1E+99),IF(Plan_Compras!$G$75>0,Plan_Compras!$H$75,1E+99),IF(Plan_Compras!$J$75>0,Plan_Compras!$K$75,1E+99),IF(Plan_Compras!$G$84>0,Plan_Compras!$H$84,1E+99),IF(Plan_Compras!$J$84>0,Plan_Compras!$K$84,1E+99),IF(Plan_Compras!$G$93>0,Plan_Compras!$H$93,1E+99),IF(Plan_Compras!$J$93>0,Plan_Compras!$K$93,1E+99),IF(Plan_Compras!$G$102>0,Plan_Compras!$H$102,1E+99),IF(Plan_Compras!$J$102>0,Plan_Compras!$K$102,1E+99),IF(Plan_Compras!$G$111>0,Plan_Compras!$H$111,1E+99),IF(Plan_Compras!$J$111>0,Plan_Compras!$K$111,1E+99))) | G72: =IF(OR(E72="",OR(AND(Plan_Compras!$G$12>0,Plan_Compras!$H$12=""),AND(Plan_Compras!$J$12>0,Plan_Compras!$K$12=""),AND(Plan_Compras!$G$21>0,Plan_Compras!$H$21=""),AND(Plan_Compras!$J$21>0,Plan_Compras!$K$21=""),AND(Plan_Compras!$G$30>0,Plan_Compras!$H$30=""),AND(Plan_Compras!$J$30>0,Plan_Compras!$K$30=""),AND(Plan_Compras!$G$39>0,Plan_Compras!$H$39=""),AND(Plan_Compras!$J$39>0,Plan_Compras!$K$39=""),AND(Plan_Compras!$G$48>0,Plan_Compras!$H$48=""),AND(Plan_Compras!$J$48>0,Plan_Compras!$K$48=""),AND(Plan_Compras!$G$57>0,Plan_Compras!$H$57=""),AND(Plan_Compras!$J$57>0,Plan_Compras!$K$57=""),AND(Plan_Compras!$G$66>0,Plan_Compras!$H$66=""),AND(Plan_Compras!$J$66>0,Plan_Compras!$K$66=""),AND(Plan_Compras!$G$75>0,Plan_Compras!$H$75=""),AND(Plan_Compras!$J$75>0,Plan_Compras!$K$75=""),AND(Plan_Compras!$G$84>0,Plan_Compras!$H$84=""),AND(Plan_Compras!$J$84>0,Plan_Compras!$K$84=""),AND(Plan_Compras!$G$93>0,Plan_Compras!$H$93=""),AND(Plan_Compras!$J$93>0,Plan_Compras!$K$93=""),AND(Plan_Compras!$G$102>0,Plan_Compras!$H$102=""),AND(Plan_Compras!$J$102>0,Plan_Compras!$K$102=""),AND(Plan_Compras!$G$111>0,Plan_Compras!$H$111=""),AND(Plan_Compras!$J$111>0,Plan_Compras!$K$111=""))),"",MAX(IF(Plan_Compras!$G$12>0,Plan_Compras!$H$12,-1E+99),IF(Plan_Compras!$J$12>0,Plan_Compras!$K$12,-1E+99),IF(Plan_Compras!$G$21>0,Plan_Compras!$H$21,-1E+99),IF(Plan_Compras!$J$21>0,Plan_Compras!$K$21,-1E+99),IF(Plan_Compras!$G$30>0,Plan_Compras!$H$30,-1E+99),IF(Plan_Compras!$J$30>0,Plan_Compras!$K$30,-1E+99),IF(Plan_Compras!$G$39>0,Plan_Compras!$H$39,-1E+99),IF(Plan_Compras!$J$39>0,Plan_Compras!$K$39,-1E+99),IF(Plan_Compras!$G$48>0,Plan_Compras!$H$48,-1E+99),IF(Plan_Compras!$J$48>0,Plan_Compras!$K$48,-1E+99),IF(Plan_Compras!$G$57>0,Plan_Compras!$H$57,-1E+99),IF(Plan_Compras!$J$57>0,Plan_Compras!$K$57,-1E+99),IF(Plan_Compras!$G$66>0,Plan_Compras!$H$66,-1E+99),IF(Plan_Compras!$J$66>0,Plan_Compras!$K$66,-1E+99),IF(Plan_Compras!$G$75>0,Plan_Compras!$H$75,-1E+99),IF(Plan_Compras!$J$75>0,Plan_Compras!$K$75,-1E+99),IF(Plan_Compras!$G$84>0,Plan_Compras!$H$84,-1E+99),IF(Plan_Compras!$J$84>0,Plan_Compras!$K$84,-1E+99),IF(Plan_Compras!$G$93>0,Plan_Compras!$H$93,-1E+99),IF(Plan_Compras!$J$93>0,Plan_Compras!$K$93,-1E+99),IF(Plan_Compras!$G$102>0,Plan_Compras!$H$102,-1E+99),IF(Plan_Compras!$J$102>0,Plan_Compras!$K$102,-1E+99),IF(Plan_Compras!$G$111>0,Plan_Compras!$H$111,-1E+99),IF(Plan_Compras!$J$111>0,Plan_Compras!$K$111,-1E+99))) | H72: =IF(OR(F72="",G72=""),"",G72-F72) | I72: =IF(OR(D72="",SUM($D$67:$D$75)=0),"",D72/SUM($D$67:$D$75)) | J72: =IF(COUNT(Plan_Compras!$F$12,Plan_Compras!$F$21,Plan_Compras!$F$30,Plan_Compras!$F$39,Plan_Compras!$F$48,Plan_Compras!$F$57,Plan_Compras!$F$66,Plan_Compras!$F$75,Plan_Compras!$F$84,Plan_Compras!$F$93,Plan_Compras!$F$102,Plan_Compras!$F$111)=0,"",SUM(Plan_Compras!$F$12,Plan_Compras!$F$21,Plan_Compras!$F$30,Plan_Compras!$F$39,Plan_Compras!$F$48,Plan_Compras!$F$57,Plan_Compras!$F$66,Plan_Compras!$F$75,Plan_Compras!$F$84,Plan_Compras!$F$93,Plan_Compras!$F$102,Plan_Compras!$F$111)-SUM(Plan_Compras!$E$12,Plan_Compras!$E$21,Plan_Compras!$E$30,Plan_Compras!$E$39,Plan_Compras!$E$48,Plan_Compras!$E$57,Plan_Compras!$E$66,Plan_Compras!$E$75,Plan_Compras!$E$84,Plan_Compras!$E$93,Plan_Compras!$E$102,Plan_Compras!$E$111)) -> 13.065327 | K72: =IF(AND(ISNUMBER(E72),ISNUMBER(J72)),J72*E72,"")
A73: =Maestro_Ingredientes!$B$13 -> Vinagre de Jerez | B73: =IF(COUNT(Plan_Compras!$F$13,Plan_Compras!$F$22,Plan_Compras!$F$31,Plan_Compras!$F$40,Plan_Compras!$F$49,Plan_Compras!$F$58,Plan_Compras!$F$67,Plan_Compras!$F$76,Plan_Compras!$F$85,Plan_Compras!$F$94,Plan_Compras!$F$103,Plan_Compras!$F$112)=0,"",SUM(Plan_Compras!$F$13,Plan_Compras!$F$22,Plan_Compras!$F$31,Plan_Compras!$F$40,Plan_Compras!$F$49,Plan_Compras!$F$58,Plan_Compras!$F$67,Plan_Compras!$F$76,Plan_Compras!$F$85,Plan_Compras!$F$94,Plan_Compras!$F$103,Plan_Compras!$F$112)) -> 1306.5327 | C73: =IF(COUNT(Plan_Compras!$M$13,Plan_Compras!$M$22,Plan_Compras!$M$31,Plan_Compras!$M$40,Plan_Compras!$M$49,Plan_Compras!$M$58,Plan_Compras!$M$67,Plan_Compras!$M$76,Plan_Compras!$M$85,Plan_Compras!$M$94,Plan_Compras!$M$103,Plan_Compras!$M$112)=0,"",SUM(Plan_Compras!$M$13,Plan_Compras!$M$22,Plan_Compras!$M$31,Plan_Compras!$M$40,Plan_Compras!$M$49,Plan_Compras!$M$58,Plan_Compras!$M$67,Plan_Compras!$M$76,Plan_Compras!$M$85,Plan_Compras!$M$94,Plan_Compras!$M$103,Plan_Compras!$M$112)) -> 1306.5327 | D73: =IF(COUNT(Plan_Compras!$N$13,Plan_Compras!$N$22,Plan_Compras!$N$31,Plan_Compras!$N$40,Plan_Compras!$N$49,Plan_Compras!$N$58,Plan_Compras!$N$67,Plan_Compras!$N$76,Plan_Compras!$N$85,Plan_Compras!$N$94,Plan_Compras!$N$103,Plan_Compras!$N$112)=0,"",SUM(Plan_Compras!$N$13,Plan_Compras!$N$22,Plan_Compras!$N$31,Plan_Compras!$N$40,Plan_Compras!$N$49,Plan_Compras!$N$58,Plan_Compras!$N$67,Plan_Compras!$N$76,Plan_Compras!$N$85,Plan_Compras!$N$94,Plan_Compras!$N$103,Plan_Compras!$N$112)) | E73: =IF(OR(C73="",C73=0,OR(AND(Plan_Compras!$G$13>0,Plan_Compras!$H$13=""),AND(Plan_Compras!$J$13>0,Plan_Compras!$K$13=""),AND(Plan_Compras!$G$22>0,Plan_Compras!$H$22=""),AND(Plan_Compras!$J$22>0,Plan_Compras!$K$22=""),AND(Plan_Compras!$G$31>0,Plan_Compras!$H$31=""),AND(Plan_Compras!$J$31>0,Plan_Compras!$K$31=""),AND(Plan_Compras!$G$40>0,Plan_Compras!$H$40=""),AND(Plan_Compras!$J$40>0,Plan_Compras!$K$40=""),AND(Plan_Compras!$G$49>0,Plan_Compras!$H$49=""),AND(Plan_Compras!$J$49>0,Plan_Compras!$K$49=""),AND(Plan_Compras!$G$58>0,Plan_Compras!$H$58=""),AND(Plan_Compras!$J$58>0,Plan_Compras!$K$58=""),AND(Plan_Compras!$G$67>0,Plan_Compras!$H$67=""),AND(Plan_Compras!$J$67>0,Plan_Compras!$K$67=""),AND(Plan_Compras!$G$76>0,Plan_Compras!$H$76=""),AND(Plan_Compras!$J$76>0,Plan_Compras!$K$76=""),AND(Plan_Compras!$G$85>0,Plan_Compras!$H$85=""),AND(Plan_Compras!$J$85>0,Plan_Compras!$K$85=""),AND(Plan_Compras!$G$94>0,Plan_Compras!$H$94=""),AND(Plan_Compras!$J$94>0,Plan_Compras!$K$94=""),AND(Plan_Compras!$G$103>0,Plan_Compras!$H$103=""),AND(Plan_Compras!$J$103>0,Plan_Compras!$K$103=""),AND(Plan_Compras!$G$112>0,Plan_Compras!$H$112=""),AND(Plan_Compras!$J$112>0,Plan_Compras!$K$112=""))),"",D73/C73) | F73: =IF(OR(E73="",OR(AND(Plan_Compras!$G$13>0,Plan_Compras!$H$13=""),AND(Plan_Compras!$J$13>0,Plan_Compras!$K$13=""),AND(Plan_Compras!$G$22>0,Plan_Compras!$H$22=""),AND(Plan_Compras!$J$22>0,Plan_Compras!$K$22=""),AND(Plan_Compras!$G$31>0,Plan_Compras!$H$31=""),AND(Plan_Compras!$J$31>0,Plan_Compras!$K$31=""),AND(Plan_Compras!$G$40>0,Plan_Compras!$H$40=""),AND(Plan_Compras!$J$40>0,Plan_Compras!$K$40=""),AND(Plan_Compras!$G$49>0,Plan_Compras!$H$49=""),AND(Plan_Compras!$J$49>0,Plan_Compras!$K$49=""),AND(Plan_Compras!$G$58>0,Plan_Compras!$H$58=""),AND(Plan_Compras!$J$58>0,Plan_Compras!$K$58=""),AND(Plan_Compras!$G$67>0,Plan_Compras!$H$67=""),AND(Plan_Compras!$J$67>0,Plan_Compras!$K$67=""),AND(Plan_Compras!$G$76>0,Plan_Compras!$H$76=""),AND(Plan_Compras!$J$76>0,Plan_Compras!$K$76=""),AND(Plan_Compras!$G$85>0,Plan_Compras!$H$85=""),AND(Plan_Compras!$J$85>0,Plan_Compras!$K$85=""),AND(Plan_Compras!$G$94>0,Plan_Compras!$H$94=""),AND(Plan_Compras!$J$94>0,Plan_Compras!$K$94=""),AND(Plan_Compras!$G$103>0,Plan_Compras!$H$103=""),AND(Plan_Compras!$J$103>0,Plan_Compras!$K$103=""),AND(Plan_Compras!$G$112>0,Plan_Compras!$H$112=""),AND(Plan_Compras!$J$112>0,Plan_Compras!$K$112=""))),"",MIN(IF(Plan_Compras!$G$13>0,Plan_Compras!$H$13,1E+99),IF(Plan_Compras!$J$13>0,Plan_Compras!$K$13,1E+99),IF(Plan_Compras!$G$22>0,Plan_Compras!$H$22,1E+99),IF(Plan_Compras!$J$22>0,Plan_Compras!$K$22,1E+99),IF(Plan_Compras!$G$31>0,Plan_Compras!$H$31,1E+99),IF(Plan_Compras!$J$31>0,Plan_Compras!$K$31,1E+99),IF(Plan_Compras!$G$40>0,Plan_Compras!$H$40,1E+99),IF(Plan_Compras!$J$40>0,Plan_Compras!$K$40,1E+99),IF(Plan_Compras!$G$49>0,Plan_Compras!$H$49,1E+99),IF(Plan_Compras!$J$49>0,Plan_Compras!$K$49,1E+99),IF(Plan_Compras!$G$58>0,Plan_Compras!$H$58,1E+99),IF(Plan_Compras!$J$58>0,Plan_Compras!$K$58,1E+99),IF(Plan_Compras!$G$67>0,Plan_Compras!$H$67,1E+99),IF(Plan_Compras!$J$67>0,Plan_Compras!$K$67,1E+99),IF(Plan_Compras!$G$76>0,Plan_Compras!$H$76,1E+99),IF(Plan_Compras!$J$76>0,Plan_Compras!$K$76,1E+99),IF(Plan_Compras!$G$85>0,Plan_Compras!$H$85,1E+99),IF(Plan_Compras!$J$85>0,Plan_Compras!$K$85,1E+99),IF(Plan_Compras!$G$94>0,Plan_Compras!$H$94,1E+99),IF(Plan_Compras!$J$94>0,Plan_Compras!$K$94,1E+99),IF(Plan_Compras!$G$103>0,Plan_Compras!$H$103,1E+99),IF(Plan_Compras!$J$103>0,Plan_Compras!$K$103,1E+99),IF(Plan_Compras!$G$112>0,Plan_Compras!$H$112,1E+99),IF(Plan_Compras!$J$112>0,Plan_Compras!$K$112,1E+99))) | G73: =IF(OR(E73="",OR(AND(Plan_Compras!$G$13>0,Plan_Compras!$H$13=""),AND(Plan_Compras!$J$13>0,Plan_Compras!$K$13=""),AND(Plan_Compras!$G$22>0,Plan_Compras!$H$22=""),AND(Plan_Compras!$J$22>0,Plan_Compras!$K$22=""),AND(Plan_Compras!$G$31>0,Plan_Compras!$H$31=""),AND(Plan_Compras!$J$31>0,Plan_Compras!$K$31=""),AND(Plan_Compras!$G$40>0,Plan_Compras!$H$40=""),AND(Plan_Compras!$J$40>0,Plan_Compras!$K$40=""),AND(Plan_Compras!$G$49>0,Plan_Compras!$H$49=""),AND(Plan_Compras!$J$49>0,Plan_Compras!$K$49=""),AND(Plan_Compras!$G$58>0,Plan_Compras!$H$58=""),AND(Plan_Compras!$J$58>0,Plan_Compras!$K$58=""),AND(Plan_Compras!$G$67>0,Plan_Compras!$H$67=""),AND(Plan_Compras!$J$67>0,Plan_Compras!$K$67=""),AND(Plan_Compras!$G$76>0,Plan_Compras!$H$76=""),AND(Plan_Compras!$J$76>0,Plan_Compras!$K$76=""),AND(Plan_Compras!$G$85>0,Plan_Compras!$H$85=""),AND(Plan_Compras!$J$85>0,Plan_Compras!$K$85=""),AND(Plan_Compras!$G$94>0,Plan_Compras!$H$94=""),AND(Plan_Compras!$J$94>0,Plan_Compras!$K$94=""),AND(Plan_Compras!$G$103>0,Plan_Compras!$H$103=""),AND(Plan_Compras!$J$103>0,Plan_Compras!$K$103=""),AND(Plan_Compras!$G$112>0,Plan_Compras!$H$112=""),AND(Plan_Compras!$J$112>0,Plan_Compras!$K$112=""))),"",MAX(IF(Plan_Compras!$G$13>0,Plan_Compras!$H$13,-1E+99),IF(Plan_Compras!$J$13>0,Plan_Compras!$K$13,-1E+99),IF(Plan_Compras!$G$22>0,Plan_Compras!$H$22,-1E+99),IF(Plan_Compras!$J$22>0,Plan_Compras!$K$22,-1E+99),IF(Plan_Compras!$G$31>0,Plan_Compras!$H$31,-1E+99),IF(Plan_Compras!$J$31>0,Plan_Compras!$K$31,-1E+99),IF(Plan_Compras!$G$40>0,Plan_Compras!$H$40,-1E+99),IF(Plan_Compras!$J$40>0,Plan_Compras!$K$40,-1E+99),IF(Plan_Compras!$G$49>0,Plan_Compras!$H$49,-1E+99),IF(Plan_Compras!$J$49>0,Plan_Compras!$K$49,-1E+99),IF(Plan_Compras!$G$58>0,Plan_Compras!$H$58,-1E+99),IF(Plan_Compras!$J$58>0,Plan_Compras!$K$58,-1E+99),IF(Plan_Compras!$G$67>0,Plan_Compras!$H$67,-1E+99),IF(Plan_Compras!$J$67>0,Plan_Compras!$K$67,-1E+99),IF(Plan_Compras!$G$76>0,Plan_Compras!$H$76,-1E+99),IF(Plan_Compras!$J$76>0,Plan_Compras!$K$76,-1E+99),IF(Plan_Compras!$G$85>0,Plan_Compras!$H$85,-1E+99),IF(Plan_Compras!$J$85>0,Plan_Compras!$K$85,-1E+99),IF(Plan_Compras!$G$94>0,Plan_Compras!$H$94,-1E+99),IF(Plan_Compras!$J$94>0,Plan_Compras!$K$94,-1E+99),IF(Plan_Compras!$G$103>0,Plan_Compras!$H$103,-1E+99),IF(Plan_Compras!$J$103>0,Plan_Compras!$K$103,-1E+99),IF(Plan_Compras!$G$112>0,Plan_Compras!$H$112,-1E+99),IF(Plan_Compras!$J$112>0,Plan_Compras!$K$112,-1E+99))) | H73: =IF(OR(F73="",G73=""),"",G73-F73) | I73: =IF(OR(D73="",SUM($D$67:$D$75)=0),"",D73/SUM($D$67:$D$75)) | J73: =IF(COUNT(Plan_Compras!$F$13,Plan_Compras!$F$22,Plan_Compras!$F$31,Plan_Compras!$F$40,Plan_Compras!$F$49,Plan_Compras!$F$58,Plan_Compras!$F$67,Plan_Compras!$F$76,Plan_Compras!$F$85,Plan_Compras!$F$94,Plan_Compras!$F$103,Plan_Compras!$F$112)=0,"",SUM(Plan_Compras!$F$13,Plan_Compras!$F$22,Plan_Compras!$F$31,Plan_Compras!$F$40,Plan_Compras!$F$49,Plan_Compras!$F$58,Plan_Compras!$F$67,Plan_Compras!$F$76,Plan_Compras!$F$85,Plan_Compras!$F$94,Plan_Compras!$F$103,Plan_Compras!$F$112)-SUM(Plan_Compras!$E$13,Plan_Compras!$E$22,Plan_Compras!$E$31,Plan_Compras!$E$40,Plan_Compras!$E$49,Plan_Compras!$E$58,Plan_Compras!$E$67,Plan_Compras!$E$76,Plan_Compras!$E$85,Plan_Compras!$E$94,Plan_Compras!$E$103,Plan_Compras!$E$112)) -> 6.5326633 | K73: =IF(AND(ISNUMBER(E73),ISNUMBER(J73)),J73*E73,"")
A74: =Maestro_Ingredientes!$B$14 -> Sal | B74: =IF(COUNT(Plan_Compras!$F$14,Plan_Compras!$F$23,Plan_Compras!$F$32,Plan_Compras!$F$41,Plan_Compras!$F$50,Plan_Compras!$F$59,Plan_Compras!$F$68,Plan_Compras!$F$77,Plan_Compras!$F$86,Plan_Compras!$F$95,Plan_Compras!$F$104,Plan_Compras!$F$113)=0,"",SUM(Plan_Compras!$F$14,Plan_Compras!$F$23,Plan_Compras!$F$32,Plan_Compras!$F$41,Plan_Compras!$F$50,Plan_Compras!$F$59,Plan_Compras!$F$68,Plan_Compras!$F$77,Plan_Compras!$F$86,Plan_Compras!$F$95,Plan_Compras!$F$104,Plan_Compras!$F$113)) -> 700 | C74: =IF(COUNT(Plan_Compras!$M$14,Plan_Compras!$M$23,Plan_Compras!$M$32,Plan_Compras!$M$41,Plan_Compras!$M$50,Plan_Compras!$M$59,Plan_Compras!$M$68,Plan_Compras!$M$77,Plan_Compras!$M$86,Plan_Compras!$M$95,Plan_Compras!$M$104,Plan_Compras!$M$113)=0,"",SUM(Plan_Compras!$M$14,Plan_Compras!$M$23,Plan_Compras!$M$32,Plan_Compras!$M$41,Plan_Compras!$M$50,Plan_Compras!$M$59,Plan_Compras!$M$68,Plan_Compras!$M$77,Plan_Compras!$M$86,Plan_Compras!$M$95,Plan_Compras!$M$104,Plan_Compras!$M$113)) -> 700 | D74: =IF(COUNT(Plan_Compras!$N$14,Plan_Compras!$N$23,Plan_Compras!$N$32,Plan_Compras!$N$41,Plan_Compras!$N$50,Plan_Compras!$N$59,Plan_Compras!$N$68,Plan_Compras!$N$77,Plan_Compras!$N$86,Plan_Compras!$N$95,Plan_Compras!$N$104,Plan_Compras!$N$113)=0,"",SUM(Plan_Compras!$N$14,Plan_Compras!$N$23,Plan_Compras!$N$32,Plan_Compras!$N$41,Plan_Compras!$N$50,Plan_Compras!$N$59,Plan_Compras!$N$68,Plan_Compras!$N$77,Plan_Compras!$N$86,Plan_Compras!$N$95,Plan_Compras!$N$104,Plan_Compras!$N$113)) | E74: =IF(OR(C74="",C74=0,OR(AND(Plan_Compras!$G$14>0,Plan_Compras!$H$14=""),AND(Plan_Compras!$J$14>0,Plan_Compras!$K$14=""),AND(Plan_Compras!$G$23>0,Plan_Compras!$H$23=""),AND(Plan_Compras!$J$23>0,Plan_Compras!$K$23=""),AND(Plan_Compras!$G$32>0,Plan_Compras!$H$32=""),AND(Plan_Compras!$J$32>0,Plan_Compras!$K$32=""),AND(Plan_Compras!$G$41>0,Plan_Compras!$H$41=""),AND(Plan_Compras!$J$41>0,Plan_Compras!$K$41=""),AND(Plan_Compras!$G$50>0,Plan_Compras!$H$50=""),AND(Plan_Compras!$J$50>0,Plan_Compras!$K$50=""),AND(Plan_Compras!$G$59>0,Plan_Compras!$H$59=""),AND(Plan_Compras!$J$59>0,Plan_Compras!$K$59=""),AND(Plan_Compras!$G$68>0,Plan_Compras!$H$68=""),AND(Plan_Compras!$J$68>0,Plan_Compras!$K$68=""),AND(Plan_Compras!$G$77>0,Plan_Compras!$H$77=""),AND(Plan_Compras!$J$77>0,Plan_Compras!$K$77=""),AND(Plan_Compras!$G$86>0,Plan_Compras!$H$86=""),AND(Plan_Compras!$J$86>0,Plan_Compras!$K$86=""),AND(Plan_Compras!$G$95>0,Plan_Compras!$H$95=""),AND(Plan_Compras!$J$95>0,Plan_Compras!$K$95=""),AND(Plan_Compras!$G$104>0,Plan_Compras!$H$104=""),AND(Plan_Compras!$J$104>0,Plan_Compras!$K$104=""),AND(Plan_Compras!$G$113>0,Plan_Compras!$H$113=""),AND(Plan_Compras!$J$113>0,Plan_Compras!$K$113=""))),"",D74/C74) | F74: =IF(OR(E74="",OR(AND(Plan_Compras!$G$14>0,Plan_Compras!$H$14=""),AND(Plan_Compras!$J$14>0,Plan_Compras!$K$14=""),AND(Plan_Compras!$G$23>0,Plan_Compras!$H$23=""),AND(Plan_Compras!$J$23>0,Plan_Compras!$K$23=""),AND(Plan_Compras!$G$32>0,Plan_Compras!$H$32=""),AND(Plan_Compras!$J$32>0,Plan_Compras!$K$32=""),AND(Plan_Compras!$G$41>0,Plan_Compras!$H$41=""),AND(Plan_Compras!$J$41>0,Plan_Compras!$K$41=""),AND(Plan_Compras!$G$50>0,Plan_Compras!$H$50=""),AND(Plan_Compras!$J$50>0,Plan_Compras!$K$50=""),AND(Plan_Compras!$G$59>0,Plan_Compras!$H$59=""),AND(Plan_Compras!$J$59>0,Plan_Compras!$K$59=""),AND(Plan_Compras!$G$68>0,Plan_Compras!$H$68=""),AND(Plan_Compras!$J$68>0,Plan_Compras!$K$68=""),AND(Plan_Compras!$G$77>0,Plan_Compras!$H$77=""),AND(Plan_Compras!$J$77>0,Plan_Compras!$K$77=""),AND(Plan_Compras!$G$86>0,Plan_Compras!$H$86=""),AND(Plan_Compras!$J$86>0,Plan_Compras!$K$86=""),AND(Plan_Compras!$G$95>0,Plan_Compras!$H$95=""),AND(Plan_Compras!$J$95>0,Plan_Compras!$K$95=""),AND(Plan_Compras!$G$104>0,Plan_Compras!$H$104=""),AND(Plan_Compras!$J$104>0,Plan_Compras!$K$104=""),AND(Plan_Compras!$G$113>0,Plan_Compras!$H$113=""),AND(Plan_Compras!$J$113>0,Plan_Compras!$K$113=""))),"",MIN(IF(Plan_Compras!$G$14>0,Plan_Compras!$H$14,1E+99),IF(Plan_Compras!$J$14>0,Plan_Compras!$K$14,1E+99),IF(Plan_Compras!$G$23>0,Plan_Compras!$H$23,1E+99),IF(Plan_Compras!$J$23>0,Plan_Compras!$K$23,1E+99),IF(Plan_Compras!$G$32>0,Plan_Compras!$H$32,1E+99),IF(Plan_Compras!$J$32>0,Plan_Compras!$K$32,1E+99),IF(Plan_Compras!$G$41>0,Plan_Compras!$H$41,1E+99),IF(Plan_Compras!$J$41>0,Plan_Compras!$K$41,1E+99),IF(Plan_Compras!$G$50>0,Plan_Compras!$H$50,1E+99),IF(Plan_Compras!$J$50>0,Plan_Compras!$K$50,1E+99),IF(Plan_Compras!$G$59>0,Plan_Compras!$H$59,1E+99),IF(Plan_Compras!$J$59>0,Plan_Compras!$K$59,1E+99),IF(Plan_Compras!$G$68>0,Plan_Compras!$H$68,1E+99),IF(Plan_Compras!$J$68>0,Plan_Compras!$K$68,1E+99),IF(Plan_Compras!$G$77>0,Plan_Compras!$H$77,1E+99),IF(Plan_Compras!$J$77>0,Plan_Compras!$K$77,1E+99),IF(Plan_Compras!$G$86>0,Plan_Compras!$H$86,1E+99),IF(Plan_Compras!$J$86>0,Plan_Compras!$K$86,1E+99),IF(Plan_Compras!$G$95>0,Plan_Compras!$H$95,1E+99),IF(Plan_Compras!$J$95>0,Plan_Compras!$K$95,1E+99),IF(Plan_Compras!$G$104>0,Plan_Compras!$H$104,1E+99),IF(Plan_Compras!$J$104>0,Plan_Compras!$K$104,1E+99),IF(Plan_Compras!$G$113>0,Plan_Compras!$H$113,1E+99),IF(Plan_Compras!$J$113>0,Plan_Compras!$K$113,1E+99))) | G74: =IF(OR(E74="",OR(AND(Plan_Compras!$G$14>0,Plan_Compras!$H$14=""),AND(Plan_Compras!$J$14>0,Plan_Compras!$K$14=""),AND(Plan_Compras!$G$23>0,Plan_Compras!$H$23=""),AND(Plan_Compras!$J$23>0,Plan_Compras!$K$23=""),AND(Plan_Compras!$G$32>0,Plan_Compras!$H$32=""),AND(Plan_Compras!$J$32>0,Plan_Compras!$K$32=""),AND(Plan_Compras!$G$41>0,Plan_Compras!$H$41=""),AND(Plan_Compras!$J$41>0,Plan_Compras!$K$41=""),AND(Plan_Compras!$G$50>0,Plan_Compras!$H$50=""),AND(Plan_Compras!$J$50>0,Plan_Compras!$K$50=""),AND(Plan_Compras!$G$59>0,Plan_Compras!$H$59=""),AND(Plan_Compras!$J$59>0,Plan_Compras!$K$59=""),AND(Plan_Compras!$G$68>0,Plan_Compras!$H$68=""),AND(Plan_Compras!$J$68>0,Plan_Compras!$K$68=""),AND(Plan_Compras!$G$77>0,Plan_Compras!$H$77=""),AND(Plan_Compras!$J$77>0,Plan_Compras!$K$77=""),AND(Plan_Compras!$G$86>0,Plan_Compras!$H$86=""),AND(Plan_Compras!$J$86>0,Plan_Compras!$K$86=""),AND(Plan_Compras!$G$95>0,Plan_Compras!$H$95=""),AND(Plan_Compras!$J$95>0,Plan_Compras!$K$95=""),AND(Plan_Compras!$G$104>0,Plan_Compras!$H$104=""),AND(Plan_Compras!$J$104>0,Plan_Compras!$K$104=""),AND(Plan_Compras!$G$113>0,Plan_Compras!$H$113=""),AND(Plan_Compras!$J$113>0,Plan_Compras!$K$113=""))),"",MAX(IF(Plan_Compras!$G$14>0,Plan_Compras!$H$14,-1E+99),IF(Plan_Compras!$J$14>0,Plan_Compras!$K$14,-1E+99),IF(Plan_Compras!$G$23>0,Plan_Compras!$H$23,-1E+99),IF(Plan_Compras!$J$23>0,Plan_Compras!$K$23,-1E+99),IF(Plan_Compras!$G$32>0,Plan_Compras!$H$32,-1E+99),IF(Plan_Compras!$J$32>0,Plan_Compras!$K$32,-1E+99),IF(Plan_Compras!$G$41>0,Plan_Compras!$H$41,-1E+99),IF(Plan_Compras!$J$41>0,Plan_Compras!$K$41,-1E+99),IF(Plan_Compras!$G$50>0,Plan_Compras!$H$50,-1E+99),IF(Plan_Compras!$J$50>0,Plan_Compras!$K$50,-1E+99),IF(Plan_Compras!$G$59>0,Plan_Compras!$H$59,-1E+99),IF(Plan_Compras!$J$59>0,Plan_Compras!$K$59,-1E+99),IF(Plan_Compras!$G$68>0,Plan_Compras!$H$68,-1E+99),IF(Plan_Compras!$J$68>0,Plan_Compras!$K$68,-1E+99),IF(Plan_Compras!$G$77>0,Plan_Compras!$H$77,-1E+99),IF(Plan_Compras!$J$77>0,Plan_Compras!$K$77,-1E+99),IF(Plan_Compras!$G$86>0,Plan_Compras!$H$86,-1E+99),IF(Plan_Compras!$J$86>0,Plan_Compras!$K$86,-1E+99),IF(Plan_Compras!$G$95>0,Plan_Compras!$H$95,-1E+99),IF(Plan_Compras!$J$95>0,Plan_Compras!$K$95,-1E+99),IF(Plan_Compras!$G$104>0,Plan_Compras!$H$104,-1E+99),IF(Plan_Compras!$J$104>0,Plan_Compras!$K$104,-1E+99),IF(Plan_Compras!$G$113>0,Plan_Compras!$H$113,-1E+99),IF(Plan_Compras!$J$113>0,Plan_Compras!$K$113,-1E+99))) | H74: =IF(OR(F74="",G74=""),"",G74-F74) | I74: =IF(OR(D74="",SUM($D$67:$D$75)=0),"",D74/SUM($D$67:$D$75)) | J74: =IF(COUNT(Plan_Compras!$F$14,Plan_Compras!$F$23,Plan_Compras!$F$32,Plan_Compras!$F$41,Plan_Compras!$F$50,Plan_Compras!$F$59,Plan_Compras!$F$68,Plan_Compras!$F$77,Plan_Compras!$F$86,Plan_Compras!$F$95,Plan_Compras!$F$104,Plan_Compras!$F$113)=0,"",SUM(Plan_Compras!$F$14,Plan_Compras!$F$23,Plan_Compras!$F$32,Plan_Compras!$F$41,Plan_Compras!$F$50,Plan_Compras!$F$59,Plan_Compras!$F$68,Plan_Compras!$F$77,Plan_Compras!$F$86,Plan_Compras!$F$95,Plan_Compras!$F$104,Plan_Compras!$F$113)-SUM(Plan_Compras!$E$14,Plan_Compras!$E$23,Plan_Compras!$E$32,Plan_Compras!$E$41,Plan_Compras!$E$50,Plan_Compras!$E$59,Plan_Compras!$E$68,Plan_Compras!$E$77,Plan_Compras!$E$86,Plan_Compras!$E$95,Plan_Compras!$E$104,Plan_Compras!$E$113)) -> 0 | K74: =IF(AND(ISNUMBER(E74),ISNUMBER(J74)),J74*E74,"")
A75: =Maestro_Ingredientes!$B$15 -> Zumo de limón | B75: =IF(COUNT(Plan_Compras!$F$15,Plan_Compras!$F$24,Plan_Compras!$F$33,Plan_Compras!$F$42,Plan_Compras!$F$51,Plan_Compras!$F$60,Plan_Compras!$F$69,Plan_Compras!$F$78,Plan_Compras!$F$87,Plan_Compras!$F$96,Plan_Compras!$F$105,Plan_Compras!$F$114)=0,"",SUM(Plan_Compras!$F$15,Plan_Compras!$F$24,Plan_Compras!$F$33,Plan_Compras!$F$42,Plan_Compras!$F$51,Plan_Compras!$F$60,Plan_Compras!$F$69,Plan_Compras!$F$78,Plan_Compras!$F$87,Plan_Compras!$F$96,Plan_Compras!$F$105,Plan_Compras!$F$114)) -> 408.16327 | C75: =IF(COUNT(Plan_Compras!$M$15,Plan_Compras!$M$24,Plan_Compras!$M$33,Plan_Compras!$M$42,Plan_Compras!$M$51,Plan_Compras!$M$60,Plan_Compras!$M$69,Plan_Compras!$M$78,Plan_Compras!$M$87,Plan_Compras!$M$96,Plan_Compras!$M$105,Plan_Compras!$M$114)=0,"",SUM(Plan_Compras!$M$15,Plan_Compras!$M$24,Plan_Compras!$M$33,Plan_Compras!$M$42,Plan_Compras!$M$51,Plan_Compras!$M$60,Plan_Compras!$M$69,Plan_Compras!$M$78,Plan_Compras!$M$87,Plan_Compras!$M$96,Plan_Compras!$M$105,Plan_Compras!$M$114)) -> 408.16327 | D75: =IF(COUNT(Plan_Compras!$N$15,Plan_Compras!$N$24,Plan_Compras!$N$33,Plan_Compras!$N$42,Plan_Compras!$N$51,Plan_Compras!$N$60,Plan_Compras!$N$69,Plan_Compras!$N$78,Plan_Compras!$N$87,Plan_Compras!$N$96,Plan_Compras!$N$105,Plan_Compras!$N$114)=0,"",SUM(Plan_Compras!$N$15,Plan_Compras!$N$24,Plan_Compras!$N$33,Plan_Compras!$N$42,Plan_Compras!$N$51,Plan_Compras!$N$60,Plan_Compras!$N$69,Plan_Compras!$N$78,Plan_Compras!$N$87,Plan_Compras!$N$96,Plan_Compras!$N$105,Plan_Compras!$N$114)) | E75: =IF(OR(C75="",C75=0,OR(AND(Plan_Compras!$G$15>0,Plan_Compras!$H$15=""),AND(Plan_Compras!$J$15>0,Plan_Compras!$K$15=""),AND(Plan_Compras!$G$24>0,Plan_Compras!$H$24=""),AND(Plan_Compras!$J$24>0,Plan_Compras!$K$24=""),AND(Plan_Compras!$G$33>0,Plan_Compras!$H$33=""),AND(Plan_Compras!$J$33>0,Plan_Compras!$K$33=""),AND(Plan_Compras!$G$42>0,Plan_Compras!$H$42=""),AND(Plan_Compras!$J$42>0,Plan_Compras!$K$42=""),AND(Plan_Compras!$G$51>0,Plan_Compras!$H$51=""),AND(Plan_Compras!$J$51>0,Plan_Compras!$K$51=""),AND(Plan_Compras!$G$60>0,Plan_Compras!$H$60=""),AND(Plan_Compras!$J$60>0,Plan_Compras!$K$60=""),AND(Plan_Compras!$G$69>0,Plan_Compras!$H$69=""),AND(Plan_Compras!$J$69>0,Plan_Compras!$K$69=""),AND(Plan_Compras!$G$78>0,Plan_Compras!$H$78=""),AND(Plan_Compras!$J$78>0,Plan_Compras!$K$78=""),AND(Plan_Compras!$G$87>0,Plan_Compras!$H$87=""),AND(Plan_Compras!$J$87>0,Plan_Compras!$K$87=""),AND(Plan_Compras!$G$96>0,Plan_Compras!$H$96=""),AND(Plan_Compras!$J$96>0,Plan_Compras!$K$96=""),AND(Plan_Compras!$G$105>0,Plan_Compras!$H$105=""),AND(Plan_Compras!$J$105>0,Plan_Compras!$K$105=""),AND(Plan_Compras!$G$114>0,Plan_Compras!$H$114=""),AND(Plan_Compras!$J$114>0,Plan_Compras!$K$114=""))),"",D75/C75) | F75: =IF(OR(E75="",OR(AND(Plan_Compras!$G$15>0,Plan_Compras!$H$15=""),AND(Plan_Compras!$J$15>0,Plan_Compras!$K$15=""),AND(Plan_Compras!$G$24>0,Plan_Compras!$H$24=""),AND(Plan_Compras!$J$24>0,Plan_Compras!$K$24=""),AND(Plan_Compras!$G$33>0,Plan_Compras!$H$33=""),AND(Plan_Compras!$J$33>0,Plan_Compras!$K$33=""),AND(Plan_Compras!$G$42>0,Plan_Compras!$H$42=""),AND(Plan_Compras!$J$42>0,Plan_Compras!$K$42=""),AND(Plan_Compras!$G$51>0,Plan_Compras!$H$51=""),AND(Plan_Compras!$J$51>0,Plan_Compras!$K$51=""),AND(Plan_Compras!$G$60>0,Plan_Compras!$H$60=""),AND(Plan_Compras!$J$60>0,Plan_Compras!$K$60=""),AND(Plan_Compras!$G$69>0,Plan_Compras!$H$69=""),AND(Plan_Compras!$J$69>0,Plan_Compras!$K$69=""),AND(Plan_Compras!$G$78>0,Plan_Compras!$H$78=""),AND(Plan_Compras!$J$78>0,Plan_Compras!$K$78=""),AND(Plan_Compras!$G$87>0,Plan_Compras!$H$87=""),AND(Plan_Compras!$J$87>0,Plan_Compras!$K$87=""),AND(Plan_Compras!$G$96>0,Plan_Compras!$H$96=""),AND(Plan_Compras!$J$96>0,Plan_Compras!$K$96=""),AND(Plan_Compras!$G$105>0,Plan_Compras!$H$105=""),AND(Plan_Compras!$J$105>0,Plan_Compras!$K$105=""),AND(Plan_Compras!$G$114>0,Plan_Compras!$H$114=""),AND(Plan_Compras!$J$114>0,Plan_Compras!$K$114=""))),"",MIN(IF(Plan_Compras!$G$15>0,Plan_Compras!$H$15,1E+99),IF(Plan_Compras!$J$15>0,Plan_Compras!$K$15,1E+99),IF(Plan_Compras!$G$24>0,Plan_Compras!$H$24,1E+99),IF(Plan_Compras!$J$24>0,Plan_Compras!$K$24,1E+99),IF(Plan_Compras!$G$33>0,Plan_Compras!$H$33,1E+99),IF(Plan_Compras!$J$33>0,Plan_Compras!$K$33,1E+99),IF(Plan_Compras!$G$42>0,Plan_Compras!$H$42,1E+99),IF(Plan_Compras!$J$42>0,Plan_Compras!$K$42,1E+99),IF(Plan_Compras!$G$51>0,Plan_Compras!$H$51,1E+99),IF(Plan_Compras!$J$51>0,Plan_Compras!$K$51,1E+99),IF(Plan_Compras!$G$60>0,Plan_Compras!$H$60,1E+99),IF(Plan_Compras!$J$60>0,Plan_Compras!$K$60,1E+99),IF(Plan_Compras!$G$69>0,Plan_Compras!$H$69,1E+99),IF(Plan_Compras!$J$69>0,Plan_Compras!$K$69,1E+99),IF(Plan_Compras!$G$78>0,Plan_Compras!$H$78,1E+99),IF(Plan_Compras!$J$78>0,Plan_Compras!$K$78,1E+99),IF(Plan_Compras!$G$87>0,Plan_Compras!$H$87,1E+99),IF(Plan_Compras!$J$87>0,Plan_Compras!$K$87,1E+99),IF(Plan_Compras!$G$96>0,Plan_Compras!$H$96,1E+99),IF(Plan_Compras!$J$96>0,Plan_Compras!$K$96,1E+99),IF(Plan_Compras!$G$105>0,Plan_Compras!$H$105,1E+99),IF(Plan_Compras!$J$105>0,Plan_Compras!$K$105,1E+99),IF(Plan_Compras!$G$114>0,Plan_Compras!$H$114,1E+99),IF(Plan_Compras!$J$114>0,Plan_Compras!$K$114,1E+99))) | G75: =IF(OR(E75="",OR(AND(Plan_Compras!$G$15>0,Plan_Compras!$H$15=""),AND(Plan_Compras!$J$15>0,Plan_Compras!$K$15=""),AND(Plan_Compras!$G$24>0,Plan_Compras!$H$24=""),AND(Plan_Compras!$J$24>0,Plan_Compras!$K$24=""),AND(Plan_Compras!$G$33>0,Plan_Compras!$H$33=""),AND(Plan_Compras!$J$33>0,Plan_Compras!$K$33=""),AND(Plan_Compras!$G$42>0,Plan_Compras!$H$42=""),AND(Plan_Compras!$J$42>0,Plan_Compras!$K$42=""),AND(Plan_Compras!$G$51>0,Plan_Compras!$H$51=""),AND(Plan_Compras!$J$51>0,Plan_Compras!$K$51=""),AND(Plan_Compras!$G$60>0,Plan_Compras!$H$60=""),AND(Plan_Compras!$J$60>0,Plan_Compras!$K$60=""),AND(Plan_Compras!$G$69>0,Plan_Compras!$H$69=""),AND(Plan_Compras!$J$69>0,Plan_Compras!$K$69=""),AND(Plan_Compras!$G$78>0,Plan_Compras!$H$78=""),AND(Plan_Compras!$J$78>0,Plan_Compras!$K$78=""),AND(Plan_Compras!$G$87>0,Plan_Compras!$H$87=""),AND(Plan_Compras!$J$87>0,Plan_Compras!$K$87=""),AND(Plan_Compras!$G$96>0,Plan_Compras!$H$96=""),AND(Plan_Compras!$J$96>0,Plan_Compras!$K$96=""),AND(Plan_Compras!$G$105>0,Plan_Compras!$H$105=""),AND(Plan_Compras!$J$105>0,Plan_Compras!$K$105=""),AND(Plan_Compras!$G$114>0,Plan_Compras!$H$114=""),AND(Plan_Compras!$J$114>0,Plan_Compras!$K$114=""))),"",MAX(IF(Plan_Compras!$G$15>0,Plan_Compras!$H$15,-1E+99),IF(Plan_Compras!$J$15>0,Plan_Compras!$K$15,-1E+99),IF(Plan_Compras!$G$24>0,Plan_Compras!$H$24,-1E+99),IF(Plan_Compras!$J$24>0,Plan_Compras!$K$24,-1E+99),IF(Plan_Compras!$G$33>0,Plan_Compras!$H$33,-1E+99),IF(Plan_Compras!$J$33>0,Plan_Compras!$K$33,-1E+99),IF(Plan_Compras!$G$42>0,Plan_Compras!$H$42,-1E+99),IF(Plan_Compras!$J$42>0,Plan_Compras!$K$42,-1E+99),IF(Plan_Compras!$G$51>0,Plan_Compras!$H$51,-1E+99),IF(Plan_Compras!$J$51>0,Plan_Compras!$K$51,-1E+99),IF(Plan_Compras!$G$60>0,Plan_Compras!$H$60,-1E+99),IF(Plan_Compras!$J$60>0,Plan_Compras!$K$60,-1E+99),IF(Plan_Compras!$G$69>0,Plan_Compras!$H$69,-1E+99),IF(Plan_Compras!$J$69>0,Plan_Compras!$K$69,-1E+99),IF(Plan_Compras!$G$78>0,Plan_Compras!$H$78,-1E+99),IF(Plan_Compras!$J$78>0,Plan_Compras!$K$78,-1E+99),IF(Plan_Compras!$G$87>0,Plan_Compras!$H$87,-1E+99),IF(Plan_Compras!$J$87>0,Plan_Compras!$K$87,-1E+99),IF(Plan_Compras!$G$96>0,Plan_Compras!$H$96,-1E+99),IF(Plan_Compras!$J$96>0,Plan_Compras!$K$96,-1E+99),IF(Plan_Compras!$G$105>0,Plan_Compras!$H$105,-1E+99),IF(Plan_Compras!$J$105>0,Plan_Compras!$K$105,-1E+99),IF(Plan_Compras!$G$114>0,Plan_Compras!$H$114,-1E+99),IF(Plan_Compras!$J$114>0,Plan_Compras!$K$114,-1E+99))) | H75: =IF(OR(F75="",G75=""),"",G75-F75) | I75: =IF(OR(D75="",SUM($D$67:$D$75)=0),"",D75/SUM($D$67:$D$75)) | J75: =IF(COUNT(Plan_Compras!$F$15,Plan_Compras!$F$24,Plan_Compras!$F$33,Plan_Compras!$F$42,Plan_Compras!$F$51,Plan_Compras!$F$60,Plan_Compras!$F$69,Plan_Compras!$F$78,Plan_Compras!$F$87,Plan_Compras!$F$96,Plan_Compras!$F$105,Plan_Compras!$F$114)=0,"",SUM(Plan_Compras!$F$15,Plan_Compras!$F$24,Plan_Compras!$F$33,Plan_Compras!$F$42,Plan_Compras!$F$51,Plan_Compras!$F$60,Plan_Compras!$F$69,Plan_Compras!$F$78,Plan_Compras!$F$87,Plan_Compras!$F$96,Plan_Compras!$F$105,Plan_Compras!$F$114)-SUM(Plan_Compras!$E$15,Plan_Compras!$E$24,Plan_Compras!$E$33,Plan_Compras!$E$42,Plan_Compras!$E$51,Plan_Compras!$E$60,Plan_Compras!$E$69,Plan_Compras!$E$78,Plan_Compras!$E$87,Plan_Compras!$E$96,Plan_Compras!$E$105,Plan_Compras!$E$114)) -> 8.1632653 | K75: =IF(AND(ISNUMBER(E75),ISNUMBER(J75)),J75*E75,"")
